Workbook

Sheet Cover
B2: Brookfield India Real Estate Trust (BIRET)
B4: Business Analysis & Valuation – Complete DCF Model
B6: Equity research valuation · Built on the asset-wise revenue engine of the user's model · Valuation date 10 October 2026 · Rs crore unless stated
B10: Sheet index (click to navigate)
B11: Sheet | C11: Purpose
B12: Summary | C12: Target price, football field, key financials, checks status
B13: Inputs | C13: Market data, pro-forma net-debt bridge, global assumptions with sources
B14: Hist_Quality | C14: Historical analysis, cash-flow quality, Du Pont, normalisations
B15: Rev_Build | C15: Asset-wise leasing engine rebuilt live from the user's Revenue Estimation
B16: Fin_Proj | C16: Income statement, debt schedule, capex, NDCF and DPU, FY27E–FY36E
B17: WACC | C17: CAPM (INR Rf, CRP, bottom-up beta), cost of debt, synthetic rating, WACC
B18: DCF_FCFF | C18: FCFF DCF, terminal value, EV-to-unit bridge, sensitivities, reverse DCF, value of growth
B19: DDM_NDCF | C19: Dividend discount / NDCF model at cost of equity
B20: Relative | C20: Peer REIT P/NAV, EV/NOI, distribution yield
B21: NAV_Asset | C21: Asset-by-asset NAV: going concern, cap-rate range, stress/liquidation, replacement cost
B22: EVA | C22: EVA, ROIC vs WACC, EVA↔DCF reconciliation, value-enhancement levers, capital structure
... B26: Checks | C26: Reconciliation to user's model and integrity tests
B28: Colour legend
B29: Green = assumption behind a forecast (the cells to change)
B30: Blue = forecast value calculated by the model (FY27E onward)
B31: Black = historical and market data, formulas, labels
B32: No fills or other colours are used; key outputs are bold and boxed
B34: Methodology notes and limitations
B35: 1. Not applicable to this asset: private-company valuation and start-up valuation (Sessions 14–16) – BIRET is a listed, stabilised REIT. The JV-stake illiquidity discount applies the private-asset concept.
B36: 2. Revenue FY27E–FY29E reproduces the user's engine exactly (see Checks); FY30E–FY36E fade at 5% growth. Interest defaults to a debt schedule – switch to the user's coverage-ratio method on Inputs.
B37: 3. Market data (price, units, G-sec, peers) were gathered from public sources on 8–10 Oct 2026; Brookfield's own PDFs could not be opened, so some company figures come from secondary summaries – verify before external use.
B38: 4. Net debt for Mindspace and KRT is derived from reported LTV; partner share of value, cap rates, development cost and the NDCF calibration are analyst assumptions flagged on the sheets.
B39: 5. Valuation outputs are model estimates for coursework/research purposes, not investment advice.

Sheet Summary
B1: BROOKFIELD INDIA REAL ESTATE TRUST (NSE: BIRET) – VALUATION SUMMARY
B2: Equity research DCF built on the user's asset-wise revenue model · Valuation date 10-Oct-2026 · Rs per unit unless stated
B4: 1. Valuation and recommendation | K4: 2. Key assumptions & market snapshot
B5: Method | C5: Value / unit (Rs) | D5: Weight | E5: Contribution | F5: vs CMP | K5: Current price (Rs) | L5: =Inputs!$C$10 -> 328.8
B6: FCFF DCF (WACC, Gordon TV) | C6: =DCF_FCFF!$C$61 -> 331.89843 | D6: =Inputs!$C$63 -> 0.3 | E6: =C6*D6 -> 99.56953 | F6: =C6/Inputs!$C$10-1 -> 0.0094234631 | K6: Market cap (Rs cr) | L6: =Inputs!$C$12 -> 27286.483
B7: NDCF dividend discount model | C7: =DDM_NDCF!$C$18 -> 387.85402 | D7: =Inputs!$C$64 -> 0.2 | E7: =C7*D7 -> 77.570804 | F7: =C7/Inputs!$C$10-1 -> 0.17960468 | K7: Units (crore) | L7: =Inputs!$C$11 -> 82.988087
B8: NAV – asset-based (cap-rate) | C8: =NAV_Asset!$G$33 -> 317.66065 | D8: =Inputs!$C$65 -> 0.25 | E8: =C8*D8 -> 79.415164 | F8: =C8/Inputs!$C$10-1 -> -0.03387879 | K8: Pro-forma net debt (Rs cr) | L8: =Inputs!$C$34 -> 14060.565
B9: Relative – peer REIT multiples | C9: =Relative!$D$24 -> 363.55931 | D9: =Inputs!$C$66 -> 0.25 | E9: =C9*D9 -> 90.889826 | F9: =C9/Inputs!$C$10-1 -> 0.10571565 | K9: Risk-free (INR, Damodaran) | L9: =WACC!$C$8 -> 0.0536
B10: Blended intrinsic value | D10: =SUM(D6:D9) -> 1 | E10: =SUM(E6:E9) -> 347.44532 | K10: Cost of equity | L10: =WACC!$C$26 -> 0.10727921
B11: + Real-option value (after haircut) | E11: =Real_Options!$C$42 -> 5.665419 | K11: WACC | L11: =WACC!$C$44 -> 0.090397496
B12: TARGET PRICE (Rs per unit) | E12: =E10+E11 -> 353.11074 | K12: Terminal growth | L12: =DCF_FCFF!C26 -> 0.04
B13: Current market price (Rs) | E13: =Inputs!$C$10 -> 328.8 | K13: Market-implied WACC (reverse DCF) | L13: =DCF_FCFF!$C$106 -> 0.090834012
B14: Upside / (downside) | E14: =E12/E13-1 -> 0.073937783 | K14: DCF EV (Rs cr, 100% consolidated) | L14: =DCF_FCFF!C43 -> 44624.773
B15: Rating | E15: =IF(E14>Inputs!$C$69,"BUY",IF(E14<Inputs!$C$70,"SELL","HOLD")) -> HOLD | K15: Implied EV / NOI FY28E | L15: =DCF_FCFF!C66 -> 13.896105
B16: Probability-weighted scenario value (Rs) | E16: =Scenario_DT!$U$21 -> 336.87227 | K16: Implied exit cap rate | L16: =DCF_FCFF!C37 -> 0.073205783
B17: Monte Carlo mean / P(value > price) | E17: =Monte_Carlo!$C$13 -> 342.99344 | F17: =Monte_Carlo!$C$22 -> 0.548 | K17: Distribution yield (annualised Q1) | L17: =Relative!N16 -> 0.068126521
B18: Reported NAV per unit (Mar-26) / pro-forma post-QIP | E18: =Inputs!$C$13 -> 386.66 | F18: =NAV_Asset!$G$34 -> 379.85862 | K18: P / NAV (pro-forma) | L18: =Relative!M16 -> 0.8655852
B19: Model integrity | E19: =Checks!$F$29 -> ALL PASS | K19: Partners' share of value | L19: =Rev_Build!$D$75 -> 0.20341657
B22: 3. Key financials (Rs crore)
C23: FY25A | D23: FY26A | E23: FY27E | F23: FY28E | G23: FY29E | H23: FY31E | I23: FY36E
B24: Revenue | C24: =Fin_Proj!G24 -> 2385.592 | D24: =Fin_Proj!H24 -> 2962.259 | E24: =Fin_Proj!I24 -> 3936.7405 | F24: =Fin_Proj!J24 -> 4143.6326 | G24: =Fin_Proj!K24 -> 4352.1901 | H24: =Fin_Proj!M24 -> 4798.2896 | I24: =Fin_Proj!R24 -> 6123.9685
B25: EBITDA | C25: =Fin_Proj!G29 -> 1729.884 | D25: =Fin_Proj!H29 -> 2136.3393 | E25: =Fin_Proj!I29 -> 2776.0209 | F25: =Fin_Proj!J29 -> 3005.6346 | G25: =Fin_Proj!K29 -> 3200.1394 | H25: =Fin_Proj!M29 -> 3528.1537 | I25: =Fin_Proj!R29 -> 4502.9175
B26: EBITDA margin | C26: =Fin_Proj!G30 -> 0.72513823 | D26: =Fin_Proj!H30 -> 0.72118586 | E26: =Fin_Proj!I30 -> 0.70515719 | F26: =Fin_Proj!J30 -> 0.72536224 | G26: =Fin_Proj!K30 -> 0.73529403 | H26: =Fin_Proj!M30 -> 0.73529403 | I26: =Fin_Proj!R30 -> 0.73529403
B27: Net profit to unitholders | C27: =Fin_Proj!G40 -> 188.64397 | D27: =Fin_Proj!H40 -> 474.87129 | E27: =Fin_Proj!I40 -> 833.16758 | F27: =Fin_Proj!J40 -> 966.52523 | G27: =Fin_Proj!K40 -> 1067.7065 | H27: =Fin_Proj!M40 -> 1309.3662 | I27: =Fin_Proj!R40 -> 2021.9834
B28: Distribution per unit (Rs) | E28: =Fin_Proj!I86 -> 22.6 | F28: =Fin_Proj!J86 -> 24.586689 | G28: =Fin_Proj!K86 -> 25.886529 | H28: =Fin_Proj!M86 -> 28.248721 | I28: =Fin_Proj!R86 -> 35.615167
B29: Interest cover (EBITDA/interest) | E29: =Fin_Proj!I59 -> 2.4869879 | F29: =Fin_Proj!J59 -> 2.6218972 | G29: =Fin_Proj!K59 -> 2.7144282 | H29: =Fin_Proj!M59 -> 2.9310085 | I29: =Fin_Proj!R59 -> 3.6277757
B30: FCFF | E30: =DCF_FCFF!I17 -> 1933.1939 | F30: =DCF_FCFF!J17 -> 1831.9088 | G30: =DCF_FCFF!K17 -> 2096.4935 | H30: =DCF_FCFF!M17 -> 2621.6774 | I30: =DCF_FCFF!R17 -> 3341.3263
B31: ROIC on book capital | E31: =EVA!I19 -> 0.053768039 | F31: =EVA!J19 -> 0.058888045 | G31: =EVA!K19 -> 0.062500669 | H31: =EVA!M19 -> 0.072328281 | I31: =EVA!R19 -> 0.10341702
B33: 4. Football field – value per unit (Rs)
B34: Method | C34: Low | D34: Spread | E34: High | F34: Point
B35: DCF (WACC ±0.5pp, g ±0.5pp) | C35: =MIN(MIN(DCF_FCFF!D77:F79),MAX(DCF_FCFF!D77:F79)) -> 273.21523 | D35: =E35-C35 -> 145.75039 | E35: =MAX(MIN(DCF_FCFF!D77:F79),MAX(DCF_FCFF!D77:F79)) -> 418.96562 | F35: =DCF_FCFF!$C$61 -> 331.89843
B36: DDM (CoE ±0.5pp, g ±0.5pp) | C36: =MIN(MIN(DDM_NDCF!D28:F30),MAX(DDM_NDCF!D28:F30)) -> 348.93581 | D36: =E36-C36 -> 90.97425 | E36: =MAX(MIN(DDM_NDCF!D28:F30),MAX(DDM_NDCF!D28:F30)) -> 439.91006 | F36: =DDM_NDCF!$C$18 -> 387.85402
B37: NAV (cap rate ±25bp) | C37: =MIN(NAV_Asset!$I$33,NAV_Asset!$H$33) -> 302.93275 | D37: =E37-C37 -> 30.466933 | E37: =MAX(NAV_Asset!$I$33,NAV_Asset!$H$33) -> 333.39968 | F37: =NAV_Asset!$G$33 -> 317.66065
B38: Relative (peer min–max) | C38: =MIN(Relative!$C$24,Relative!$E$24) -> 340.40995 | D38: =E38-C38 -> 42.314658 | E38: =MAX(Relative!$C$24,Relative!$E$24) -> 382.72461 | F38: =Relative!$D$24 -> 363.55931
B39: Scenarios (bear – bull) | C39: =MIN(Scenario_DT!$U$6,Scenario_DT!$U$8) -> 223.18443 | D39: =E39-C39 -> 237.32336 | E39: =MAX(Scenario_DT!$U$6,Scenario_DT!$U$8) -> 460.50779 | F39: =Scenario_DT!$U$21 -> 336.87227
B40: Monte Carlo (P10 – P90) | C40: =MIN(Monte_Carlo!$C$17,Monte_Carlo!$C$20) -> 266.63161 | D40: =E40-C40 -> 162.10283 | E40: =MAX(Monte_Carlo!$C$17,Monte_Carlo!$C$20) -> 428.73443 | F40: =Monte_Carlo!$C$13 -> 342.99344
B41: 52-week trading range | C41: =MIN(Inputs!$C$15,Inputs!$C$14) -> 311.26 | D41: =E41-C41 -> 65.24 | E41: =MAX(Inputs!$C$15,Inputs!$C$14) -> 376.5 | F41: =Inputs!$C$10 -> 328.8
B62: Notes: (1) FCFF DCF is on 100% consolidated cash flows, bridged to unitholders after net debt, partners' share and the NCP JV. (2) Real options are shown separately and haircut. (3) All inputs, sources and assumptions are on the Inputs and method sheets (green cells).

Sheet Inputs
B1: INPUTS – market data, balance-sheet bridge and global assumptions
B2: Green = assumption behind a forecast · Blue = forecast value calculated by the model · Black = everything else · Rs crore unless stated
B5: A. Market data & valuation date
B6: Item | C6: Value | D6: Unit | E6: Source / note
B7: Valuation date | C7: 46305 | D7: date | E7: Date of this analysis
B8: FY27 year-end | C8: 46477 | D8: date | E8: Indian fiscal year ends 31 March
B9: Fraction of FY27 remaining after valuation date | C9: =($C$8-$C$7)/365 -> 0.47123288 | D9: years | E9: Used for stub-period cash flow and mid-period discounting
B10: Current market price (Rs/unit) | C10: 328.8 | D10: Rs | E10: NSE close 8-Oct-2026 (Kotak Neo / Tickertape quotes: Rs 328.8–330.3)
B11: Units outstanding | C11: 82.988087 | D11: crore | E11: 829,880,869 units post April-2026 QIP (Q1 FY27 distribution Rs 464.73 cr / DPU Rs 5.60 cross-checks)
B12: Market capitalisation | C12: =$C$10*$C$11 -> 27286.483 | D12: Rs cr
B13: Reported NAV per unit (31-Mar-2026) | C13: 386.66 | D13: Rs | E13: Brookfield India REIT Annual Report FY26 (consolidated NAV at fair value)
B14: 52-week high | C14: 376.5 | D14: Rs | E14: Kotak Neo, 8-Oct-2026
B15: 52-week low | C15: 311.26 | D15: Rs | E15: Kotak Neo, 8-Oct-2026
B16: Q1 FY27 DPU (declared Aug-2026) | C16: 5.6 | D16: Rs | E16: Q1 FY27 press release; record date 13-Aug-2026
B17: Annualised DPU (Q1 x 4) | C17: =$C$16*4 -> 22.4 | D17: Rs
B18: FY26 DPU | C18: 21.4 | D18: Rs | E18: FY26 results (incl. Rs 5.50 for Q4)
B19: April-2026 QIP issue price | C19: 323 | D19: Rs | E19: Institutional placement closed 21-Apr-2026
B21: B. Capital structure & pro-forma net debt bridge (consolidated)
B22: Item | C22: Value | D22: Unit | E22: Source / note
B23: Borrowings incl. accrued interest, 31-Mar-2026 | C23: 16432.783 | D23: Rs cr | E23: FY26 Annual Report (Rs 164,327.82 mn)
B24: Cash & equivalents, 31-Mar-2026 | C24: 674.218 | D24: Rs cr | E24: FY26 Annual Report (Rs 6,742.18 mn)
B25: Ecoworld Tranche-2 deferred consideration | C25: 1125 | D25: Rs cr | E25: Q4 FY26 investor update (counted in LTV); settled from 360 ONE proceeds
B26: April-2026 QIP gross proceeds | C26: 2600 | D26: Rs cr | E26: Rs 26 bn raised at Rs 323/unit (~8.05 cr units); used to repay debt
B27: QIP issue costs (% of proceeds) | C27: 0.02 | D27: % | E27: ASSUMPTION – typical placement cost 1.5–2.5%
B28: QIP net proceeds applied to debt | C28: =$C$26*(1-$C$27) -> 2548 | D28: Rs cr
B29: 360 ONE primary investment in Ecoworld SPV | C29: 1125 | D29: Rs cr | E29: 22-Apr-2026: ~13% stake for Rs 1,125 cr; settles Tranche-2 liability
B30: BKC (GBKC) acquisition – enterprise value, 100% | C30: 1700 | D30: Rs cr | E30: Announced 10-Aug-2026; closed 29-Sep-2026 as 50:50 JV with NCW/Nuvama
B31: REIT share of BKC JV | C31: 0.5 | D31: % | E31: Press release
B32: REIT funding of BKC stake (assumed debt-funded) | C32: =$C$30*$C$31 -> 850 | D32: Rs cr | E32: ASSUMPTION – funded by debt/cash; value-neutral in the bridge (asset added back at cost)
B33: Pro-forma gross debt | C33: =$C$23-$C$28+$C$32 -> 14734.783 | D33: Rs cr | E33: Mar-26 borrowings less QIP repayment plus BKC funding
B34: Pro-forma consolidated net debt | C34: =$C$33-$C$24+$C$25-$C$29 -> 14060.565 | D34: Rs cr | E34: Tranche-2 liability and 360 ONE cash offset; cross-check: mgmt pro-forma net debt Rs 15,363 cr incl. NCP share
B35: North Commercial Portfolio gross debt (100%) | C35: 3400 | D35: Rs cr | E35: User model 'Operational Metrics'!Y55 (Rs 34 bn, Q4 FY26)
B36: REIT share of North Commercial Portfolio (NCP) | C36: 0.5 | D36: % | E36: Equity-accounted JV (Worldmark Delhi/Gurugram, Airtel Center, Pavilion Mall)
B37: Illiquidity / non-control discount on JV stakes (BAV: private-asset adjustment) | C37: 0.1 | D37: % | E37: ASSUMPTION – Damodaran range 10–30% for illiquid stakes; low end used (JV is joint-controlled)
B38: Memo: minority interest, book value FY25 | C38: 1980.695 | D38: Rs cr | E38: User model 'Balance Sheet'!F13
B40: C. Operating & capex assumptions
B41: Item | C41: Value | D41: Unit | E41: Source / note
B42: Statutory SPV tax rate (new regime, 22% + surcharge + cess) | C42: 0.2517 | D42: % | E42: Income-tax rate; user model uses 24–26% effective on PBT
B43: Maintenance capex (Rs per sq ft per month, on operating area) | C43: 2 | D43: Rs | E43: Valuer assumption in Brookfield valuation report (Rs 2 psf/month)
B44: Maintenance capex inflation | C44: 0.045 | D44: % | E44: ASSUMPTION – ~RBI CPI
B45: Construction cost for committed area additions (Rs/sq ft) | C45: 6500 | D45: Rs | E45: ASSUMPTION – campus expansions on owned land
B46: Net working capital (% of revenue) | C46: -0.05 | D46: % | E46: ASSUMPTION – FY25 balance sheet shows negative operating NWC (deposits/payables > receivables)
B47: Share of growth capex funded by debt | C47: 1 | D47: % | E47: ASSUMPTION – LTV headroom ~10pp to 35% cap
B48: Depreciation per '000 sq ft per quarter (Rs cr) | C48: 0.0050984529 | D48: Rs cr | E48: User model 'Revenue Estimation'!S55 (avg of Q1FY25–Q3FY26 ratio)
B49: NOI as multiple of rental revenue | C49: 1.07 | D49: x | E49: FY26 NOI Rs 22.9 bn / operating lease rentals Rs 21.5 bn (FY26 annual report)
B50: NOI margin on total revenue (consolidated) | C50: 0.775 | D50: % | E50: Q1 FY27 NOI 756.6 / revenue 973.8 = 77.7%; FY26 77%
B51: Interest method (1 = debt schedule, 2 = user's coverage-ratio method FY27–29) | C51: 1 | D51: switch | E51: Default 1 – see Fin_Proj note on the inconsistency in method 2
B53: D. Equity-level (NDCF / DPU) assumptions
B54: Item | C54: Value | D54: Unit | E54: Source / note
B55: FY27E DPU anchor (Rs/unit) | C55: 22.6 | D55: Rs | E55: Q1 actual Rs 5.60 + ~Rs 5.67 average for Q2–Q4 (mgmt guides ~15% embedded growth over ~2 years)
B56: Partners' share of consolidated NDCF (GIC in G1/Powai, 360 ONE in Ecoworld) | C56: 0.15 | D56: % | E56: ASSUMPTION – below 20% value share because partner shareholder-loan structure shifts cash to partners as interest
B57: NDCF payout ratio | C57: 1 | D57: % | E57: Q1 FY27 distribution ≈ 100% of NDCF; SEBI minimum 90%
B58: BKC NDCF yield on REIT funding | C58: 0.071 | D58: % | E58: Management: ~7.1% DPU yield on acquisition
B59: Growth of BKC distributions | C59: 0.04 | D59: % | E59: ASSUMPTION
B61: E. Valuation blend & output switches
B62: Item | C62: Value | D62: Unit | E62: Source / note
B63: Weight – FCFF DCF | C63: 0.3 | D63: % | E63: Judgement: intrinsic, cash-flow based
B64: Weight – NDCF dividend discount model | C64: 0.2 | D64: % | E64: Equity-level cross-check
B65: Weight – NAV (asset-based) | C65: 0.25 | D65: % | E65: Standard REIT anchor
B66: Weight – relative valuation | C66: 0.25 | D66: % | E66: Peer REIT multiples
B67: Include real-option value in target price (1/0) | C67: 1 | D67: switch
B68: Haircut applied to real-option value | C68: 0.5 | D68: % | E68: ASSUMPTION – execution/timing risk
B69: Rating threshold: BUY if upside above | C69: 0.15 | D69: %
B70: Rating threshold: SELL if upside below | C70: -0.05 | D70: %

Sheet Hist_Quality
B1: HISTORICAL ANALYSIS & ACCOUNTING QUALITY – what to trust, what to normalise
B2: FY22–FY25 balance sheet and cash flow from user model (Ace Equity extracts) · FY26 P&L from 'Quarterly-data' · FY26 balance sheet from FY26 annual report (partial)
B4: Rs crore | C4: Unit | D4: FY22A | E4: FY23A | F4: FY24A | G4: FY25A | H4: FY26A
B5: A. Reported performance
B6: Revenue from operations | C6: Rs cr | D6: =Fin_Proj!D24 -> 876.791 | E6: =Fin_Proj!E24 -> 1196.999 | F6: =Fin_Proj!F24 -> 1780.481 | G6: =Fin_Proj!G24 -> 2385.592 | H6: =Fin_Proj!H24 -> 2962.259
B7: growth | C7: % | E7: =Fin_Proj!E25 -> 0.36520448 | F7: =Fin_Proj!F25 -> 0.48745404 | G7: =Fin_Proj!G25 -> 0.33985816 | H7: =Fin_Proj!H25 -> 0.2417291 | I7: FY26 includes Ecoworld from Dec-2025 and a full year of the NCP/G1/Powai step-ups – not organic
B8: EBITDA | C8: Rs cr | D8: =Fin_Proj!D29 -> 618.31094 | E8: =Fin_Proj!E29 -> 815.55074 | F8: =Fin_Proj!F29 -> 1254.6933 | G8: =Fin_Proj!G29 -> 1729.884 | H8: =Fin_Proj!H29 -> 2136.3393
B9: EBITDA margin | C9: % | D9: =Fin_Proj!D30 -> 0.70519763 | E9: =Fin_Proj!E30 -> 0.68132951 | F9: =Fin_Proj!F30 -> 0.70469344 | G9: =Fin_Proj!G30 -> 0.72513823 | H9: =Fin_Proj!H30 -> 0.72118586
B10: Net profit to unitholders | C10: Rs cr | D10: =Fin_Proj!D40 -> 246.27394 | E10: =Fin_Proj!E40 -> 131.21374 | F10: =Fin_Proj!F40 -> 20.732279 | G10: =Fin_Proj!G40 -> 188.64397 | H10: =Fin_Proj!H40 -> 474.87129
B11: net margin | C11: % | D11: =D10/D6 -> 0.28088101 | E11: =E10/E6 -> 0.10961892 | F11: =F10/F6 -> 0.011644201 | G11: =G10/G6 -> 0.079076375 | H11: =H10/H6 -> 0.16030715
B12: Interest expense | C12: Rs cr | D12: =Fin_Proj!D34 -> 208.069 | E12: =Fin_Proj!E34 -> 432.457 | F12: =Fin_Proj!F34 -> 852.199 | G12: =Fin_Proj!G34 -> 1078.177 | H12: =Fin_Proj!H34 -> 974.78
B13: B. Balance sheet (FY26: partial)
B14: Shareholders' funds (book equity) | C14: Rs cr | D14: 8882.093 | E14: 8333.738 | F14: 10124.159 | G14: 14029.92 | I14: 'Balance Sheet' row 12
B15: Minority interest | C15: Rs cr | D15: 0 | E15: 0 | F15: 2005.5 | G15: 1980.695 | I15: 'Balance Sheet' row 13
B16: Total debt | C16: Rs cr | D16: 5165.534 | E16: 5452.038 | F16: 12056.296 | G16: 9058.525 | H16: =Inputs!$C$23 -> 16432.783 | I16: FY26: borrowings incl. accrued interest, annual report
B17: Cash & bank | C17: Rs cr | D17: 255.014 | E17: 258.019 | F17: 517.403 | G17: 665.744 | H17: =Inputs!$C$24 -> 674.218
B18: Total assets | C18: Rs cr | D18: 14410.252 | E18: 14271.619 | F18: 25076.145 | G18: 26196.848
B19: Net debt | C19: Rs cr | D19: =D16-D17 -> 4910.52 | E19: =E16-E17 -> 5194.019 | F19: =F16-F17 -> 11538.893 | G19: =G16-G17 -> 8392.781 | H19: =H16-H17 -> 15758.565
B21: C. Cash-flow quality (is profit backed by cash?)
B22: Cash from operations | C22: Rs cr | D22: 605.92 | E22: 953.117 | F22: 1282.101 | G22: 1847.952 | I22: 'Cash Flow' row 45
B23: Tax paid per cash-flow statement | C23: Rs cr | D23: -17.485 | E23: 25.863 | F23: 25.612 | G23: -8.096 | I23: Sign convention in the extract is inconsistent; magnitude used
B24: Purchase of fixed assets | C24: Rs cr | D24: -4.242 | E24: -5.37 | F24: -18.166 | G24: -1.296 | I24: Investment property additions sit in 'investment in subsidiaries' for acquisitions
B25: CFO / EBITDA | C25: x | D25: =D22/D8 -> 0.97996002 | E25: =E22/E8 -> 1.168679 | F25: =F22/F8 -> 1.0218442 | G25: =G22/G8 -> 1.068252 | I25: Below 1.0 because interest is deducted inside CFO (Ind-AS 7 presentation)
B26: CFO / net profit | C26: x | D26: =D22/D10 -> 2.4603496 | E26: =E22/E10 -> 7.2638504 | F26: =F22/F10 -> 61.840814 | G26: =G22/G10 -> 9.7959772 | I26: Very high: depreciation Rs 430–470 cr and interest accretion are non-cash/financing-related
B27: Accruals ratio = (net profit − CFO) / average total assets | C27: % | E27: =(E10-E22)/AVERAGE(D18,E18) -> -0.05731169 | F27: =(F10-F22)/AVERAGE(E18,F18) -> -0.06411387 | G27: =(G10-G22)/AVERAGE(F18,G18) -> -0.064724446 | I27: Strongly negative = conservative earnings (cash > accounting profit)
B28: Free cash flow after capex / EBITDA | C28: x | D28: =(D22+D24)/D8 -> 0.97309939 | E28: =(E22+E24)/E8 -> 1.1620945 | F28: =(F22+F24)/F8 -> 1.0073657 | G28: =(G22+G24)/G8 -> 1.0675028
B29: Cash tax as % of P&L tax | C29: % | D29: =IFERROR(ABS(D23)/ABS(Fin_Proj!D36),0) -> 0.79167799 | E29: =IFERROR(ABS(E23)/ABS(Fin_Proj!E36),0) -> 2.8240882 | F29: =IFERROR(ABS(F23)/ABS(Fin_Proj!F36),0) -> 0.37220793 | G29: =IFERROR(ABS(G23)/ABS(Fin_Proj!G36),0) -> 0.091734179 | I29: Most REIT SPV tax is deferred; supports cash-tax ramp assumption in Fin_Proj row 14 (FY25: ~9%)
B31: D. Leverage and coverage
B32: Net debt / EBITDA | C32: x | D32: =D19/D8 -> 7.9418294 | E32: =E19/E8 -> 6.3687257 | F32: =F19/F8 -> 9.1965847 | G32: =G19/G8 -> 4.8516439 | H32: =H19/H8 -> 7.3764335 | I32: FY26 uses year-end debt on a full-year EBITDA that includes only ~4 months of Ecoworld – overstated
B33: EBIT / interest | C33: x | D33: =Fin_Proj!D32/Fin_Proj!D34 -> 1.9697021 | E33: =Fin_Proj!E32/Fin_Proj!E34 -> 1.2494855 | F33: =Fin_Proj!F32/Fin_Proj!F34 -> 0.9899217 | G33: =Fin_Proj!G32/Fin_Proj!G34 -> 1.2057324 | H33: =Fin_Proj!H32/Fin_Proj!H34 -> 1.7100651
B34: EBITDA / interest | C34: x | D34: =Fin_Proj!D29/Fin_Proj!D34 -> 2.971663 | E34: =Fin_Proj!E29/Fin_Proj!E34 -> 1.885854 | F34: =Fin_Proj!F29/Fin_Proj!F34 -> 1.4723008 | G34: =Fin_Proj!G29/Fin_Proj!G34 -> 1.6044527 | H34: =Fin_Proj!H29/Fin_Proj!H34 -> 2.1916117
B35: Debt / book equity | C35: x | D35: =D16/D14 -> 0.5815672 | E35: =E16/E14 -> 0.65421279 | F35: =F16/F14 -> 1.1908442 | G35: =G16/G14 -> 0.64565764
B37: E. Du Pont and returns on book capital
B38: Net margin | C38: % | D38: =D10/D6 -> 0.28088101 | E38: =E10/E6 -> 0.10961892 | F38: =F10/F6 -> 0.011644201 | G38: =G10/G6 -> 0.079076375
B39: Asset turnover (revenue / total assets) | C39: x | D39: =D6/D18 -> 0.060844946 | E39: =E6/E18 -> 0.083872685 | F39: =F6/F18 -> 0.071002979 | G39: =G6/G18 -> 0.091064085
B40: Equity multiplier (total assets / book equity) | C40: x | D40: =D18/D14 -> 1.6223937 | E40: =E18/E14 -> 1.7125111 | F40: =F18/F14 -> 2.476862 | G40: =G18/G14 -> 1.8672129
B41: ROE (Du Pont product) | C41: % | D41: =D38*D39*D40 -> 0.027727017 | E41: =E38*E39*E40 -> 0.015744885 | F41: =F38*F39*F40 -> 0.0020478026 | G41: =G38*G39*G40 -> 0.013445833
B42: ROIC = EBIT x (1 − t) / (equity + MI + debt − cash) | C42: % | D42: =Fin_Proj!D32*(1-Inputs!$C$42)/(D14+D15+D19) -> 0.022234999 | E42: =Fin_Proj!E32*(1-Inputs!$C$42)/(E14+E15+E19) -> 0.029889875 | F42: =Fin_Proj!F32*(1-Inputs!$C$42)/(F14+F15+F19) -> 0.026671406 | G42: =Fin_Proj!G32*(1-Inputs!$C$42)/(G14+G15+G19) -> 0.039862679 | I42: Low because the cost model carries assets far below fair value – hence EVA is also run on fair-value capital
B43: Book value per unit | C43: Rs | G43: 230.847 | I43: 'Balance Sheet'!F62
B44: Reported NAV per unit (31-Mar-26) | C44: Rs | H44: =Inputs!$C$13 -> 386.66
B45: NAV / latest book value per unit | C45: x | H45: =H44/G43 -> 1.6749622 | I45: Hidden fair-value gain not in the Ind-AS balance sheet
B47: F. Normalising FY26 earnings – Q4 FY26 tax charge
D48: Q1 FY26 | E48: Q2 FY26 | F48: Q3 FY26 | G48: Q4 FY26 | H48: FY26
B49: Profit before tax | D49: 167.53608 | E49: 191.19454 | F49: 208.70129 | G49: 224.91237 | H49: =SUM(D49:G49) -> 792.34429
B50: Tax expense | D50: 20.436 | E50: 29.695 | F50: 2.002 | G50: 169.535 | H50: =SUM(D50:G50) -> 221.668
B51: Effective tax rate | D51: =D50/D49 -> 0.12197969 | E51: =E50/E49 -> 0.15531301 | F51: =F50/F49 -> 0.0095926574 | G51: =G50/G49 -> 0.75378245 | H51: =H50/H49 -> 0.27976222 | I51: Q4 FY26 tax of Rs 169.5 cr is 75% of Q4 PBT – consistent with a deferred-tax re-measurement; confirm against Ind-AS tax note
B52: Normalised FY26 tax at statutory rate | H52: =H49*Inputs!$C$42 -> 199.43306
B53: Non-recurring tax charge (reported − normalised) | H53: =H50-H52 -> 22.234942
B54: Reported profit after tax | H54: =Fin_Proj!H37 -> 570.67629
B55: Adjusted (normalised) profit after tax | H55: =H54+H53 -> 592.91123
B57: G. Accounting adjustments and how this model treats them
B58: Item | D58: Observation / treatment
B59: Investment property at cost (Ind-AS 40 cost model) | D59: Book assets far below fair value; EVA shown on book capital and DCF/NAV on fair value.
B60: Straight-line lease revenue | D60: Revenue/EBITDA include non-cash straight-lining; rent build uses contractual in-place rent, so DCF is cash-based.
B61: Shareholder CCD/NCD liability components of partners ('Reco entities') | D61: Economically partner claims: handled through partners' share of value (Rev_Build) rather than debt.
B62: Other income (treasury interest) | D62: Excluded from FCFF; cash enters the bridge through net debt. Included in NDCF.
B63: Minority interest (G1/Powai 50%, Ecoworld 13%) | D63: Deducted at fair value (share of equity value), not at book (Rs 1,981 cr FY25).
B64: Share of associates (North Commercial Portfolio) | D64: Valued separately: NOI ÷ cap rate − JV debt, x 50%, less illiquidity discount.
B65: Q4 FY26 tax charge | D65: Treated as non-recurring (section F); forecast uses 24–26% then 25.17%.
B66: FY26 revenue: user model Rs 2,962.3 cr vs reported Rs 2,971.1 cr | D66: 0.3% variance from quarterly data source; user's figure retained for consistency.
B67: Ecoworld consolidated from Dec-2025 | D67: FY26–FY27 growth is acquisition-driven; organic same-store NOI growth ~8–10%.
B68: Interest in user model (EBITDA ÷ ICR) | D68: Implies rising debt with no acquisition revenue; default here is a debt schedule (switch on Inputs).

Sheet Rev_Build
B1: REVENUE BUILD – asset-wise leasing engine (replicates 'Revenue Estimation' with live formulas)
B2: Area in '000 sq ft · Rent in Rs/sq ft/month · Revenue in Rs million unless stated · Inputs trace to user model sheets named in column U
B5: 1. Asset parameter table (inputs from user model: Property wise / Quarterly Expected Occupancy / Revenue Estimation)
B7: Asset | C7: REIT own % | D7: Op. area FY27 | E7: Leased area (Q4FY26) | F7: In-place rent | G7: Rent escalator | H7: Area expiring FY27 | I7: Area expiring FY28 | J7: Area expiring FY29 | K7: New-leasing rent FY27 | L7: Renewal rent FY27 | M7: Exp. occupancy FY27 | N7: Exp. occupancy FY28 | O7: Exp. occupancy FY29 | P7: New-lease rent growth factor | Q7: Renewal rent growth factor | R7: Area added FY28 | S7: Area added FY29 | T7: CAM % of rental (OLR) | U7: Source
B8: Ecoworld, Bangalore | C8: 0.87 | D8: 7052 | E8: 6615 | F8: 105 | G8: 1.0294 | H8: 760 | I8: 309 | J8: 660 | K8: 106 | L8: 110 | M8: 0.94 | N8: 0.945 | O8: 0.9525 | P8: 1.06 | Q8: 1.06 | R8: 50 | S8: 50 | T8: 0.24697739 | U8: 'Revenue Estimation' rows 4/19/36; 'Property wise' CL:CM, DM/DP/DS; 'Quarterly Expected Occupancy' DL:DN
B9: Downtown Powai, Mumbai | C9: 0.5 | D9: 4461 | E9: 4232 | F9: 168 | G9: 1.0182 | H9: 327 | I9: 613 | J9: 415 | K9: 174 | L9: 182 | M9: 0.935 | N9: 0.9525 | O9: 0.9575 | P9: 1.04 | Q9: 1.06 | R9: 0 | S9: 0 | T9: 0.11356953 | U9: 'Revenue Estimation' rows 5/20/37; 'Property wise' CL:CM, DM/DP/DS; 'Quarterly Expected Occupancy' DL:DN
B10: G1, Gurugram | C10: 0.5 | D10: 3778 | E10: 3238 | F10: 85 | G10: 1.0162378 | H10: 131 | I10: 226 | J10: 0 | K10: 86 | L10: 91 | M10: 0.8825 | N10: 0.91 | O10: 0.925 | P10: 1.03 | Q10: 1.06 | R10: 25 | S10: 25 | T10: 0.40788801 | U10: 'Revenue Estimation' rows 6/21/38; 'Property wise' CL:CM, DM/DP/DS; 'Quarterly Expected Occupancy' DL:DN
B11: G2, Gurugram | C11: 1 | D11: 4060 | E11: 3367 | F11: 92 | G11: 1.02 | H11: 151 | I11: 0 | J11: 13 | K11: 88 | L11: 88 | M11: 0.8275 | N11: 0.82 | O11: 0.84 | P11: 1.03 | Q11: 1.06 | R11: 25 | S11: 25 | T11: 0.5550621 | U11: 'Revenue Estimation' rows 7/22/39; 'Property wise' CL:CM, DM/DP/DS; 'Quarterly Expected Occupancy' DL:DN
B12: N1, Noida | C12: 1 | D12: 2017 | E12: 1944 | F12: 66 | G12: 1.0264569 | H12: 98 | I12: 0 | J12: 102 | K12: 69 | L12: 69 | M12: 0.98 | N12: 0.98 | O12: 0.98 | P12: 1.03 | Q12: 1.06 | R12: 100 | S12: 150 | T12: 0.75332786 | U12: 'Revenue Estimation' rows 8/23/40; 'Property wise' CL:CM, DM/DP/DS; 'Quarterly Expected Occupancy' DL:DN
B13: N2, Noida | C13: 1 | D13: 3905 | E13: 3573 | F13: 66 | G13: 1.0154 | H13: 818 | I13: 44 | J13: 130 | K13: 66 | L13: 71 | M13: 0.9425 | N13: 0.9475 | O13: 0.955 | P13: 1.03 | Q13: 1.06 | R13: 100 | S13: 150 | T13: 0.54869542 | U13: 'Revenue Estimation' rows 9/24/41; 'Property wise' CL:CM, DM/DP/DS; 'Quarterly Expected Occupancy' DL:DN
B14: K1, Kolkata | C14: 1 | D14: 3167 | E14: 3130 | F14: 49 | G14: 1.0091213 | H14: 306 | I14: 438 | J14: 5 | K14: 54 | L14: 62 | M14: 0.98 | N14: 0.98 | O14: 0.9875 | P14: 1.04 | Q14: 1.06 | R14: 150 | S14: 250 | T14: 0.5854376 | U14: 'Revenue Estimation' rows 10/25/42; 'Property wise' CL:CM, DM/DP/DS; 'Quarterly Expected Occupancy' DL:DN
B15: Worldmark, Delhi (NCP) | C15: 0.5 | D15: 1455 | E15: 1384 | F15: 230 | G15: 1.03 | H15: 136 | I15: 151 | J15: 36 | K15: 237 | L15: 236 | M15: 0.96 | N15: 0.96 | O15: 0.96 | P15: 1.1 | Q15: 1.06 | R15: 0 | S15: 0 | T15: 0 | U15: 'Revenue Estimation' rows 11/26/43; 'Property wise' CL:CM, DM/DP/DS; 'Quarterly Expected Occupancy' DL:DN
B16: Worldmark, Gurugram (NCP) | C16: 0.5 | D16: 751 | E16: 695 | F16: 94 | G16: 1.03 | H16: 27 | I16: 20 | J16: 37 | K16: 93 | L16: 95 | M16: 0.92 | N16: 0.92 | O16: 0.92 | P16: 1.05 | Q16: 1.06 | R16: 0 | S16: 0 | T16: 0 | U16: 'Revenue Estimation' rows 12/27/44; 'Property wise' CL:CM, DM/DP/DS; 'Quarterly Expected Occupancy' DL:DN
B17: Airtel Center + Pavilion (NCP) | C17: 0.5 | F17: 1404 | G17: 1.05 | U17: User hard-code 'Revenue Estimation'!T14 = 1404*1.05 (annual rental Rs mn), grown 5% p.a. (T29, T46)
B18: Airtel/Pavilion: F17 = FY26 run-rate rental (Rs mn), G17 = annual growth factor. NCP rows are equity-accounted (not in consolidated revenue).
B21: FY27E – asset engine (continuing + expiring + vacancy absorption)
B22: Asset | C22: Own % | D22: Operating area | E22: Leased area (open) | F22: Vacant | G22: Area expiring | H22: Continuing area | I22: In-place rent | J22: Escalator | K22: Continuing rent | L22: New-leasing rent | M22: Renewal rent | N22: Continuing rev | O22: Expiry rev (50%) | P22: Vacancy rev (50%) | Q22: Exp. occupancy | R22: Exp. leased area | S22: Absorbed area | T22: Absorption ratio | U22: Re-leasing rev | V22: Total rental | W22: CAM % | X22: CAM revenue | Y22: Total revenue (Rs mn) | Z22: Revenue (Rs cr)
B23: Ecoworld, Bangalore | C23: =C8 -> 0.87 | D23: =D8 -> 7052 | E23: =E8 -> 6615 | F23: =D23-E23 -> 437 | G23: =H8 -> 760 | H23: =E23-G23 -> 5855 | I23: =F8 -> 105 | J23: =G8 -> 1.0294 | K23: =I23*J23 -> 108.087 | L23: =K8 -> 106 | M23: =L8 -> 110 | N23: =H23*K23*12/1000 -> 7594.1926 | O23: =G23*M23*12/1000*0.5 -> 501.6 | P23: =F23*L23*12/1000*0.5 -> 277.932 | Q23: =M8 -> 0.94 | R23: =Q23*D23 -> 6628.88 | S23: =MAX(0,R23-H23) -> 773.88 | T23: =IFERROR(S23/(G23+F23),0) -> 0.64651629 | U23: =(O23+P23)*T23 -> 503.98014 | V23: =N23+U23 -> 8098.1728 | W23: =T8 -> 0.24697739 | X23: =V23*W23 -> 2000.0656 | Y23: =V23+X23 -> 10098.238 | Z23: =Y23/10 -> 1009.8238
B24: Downtown Powai, Mumbai | C24: =C9 -> 0.5 | D24: =D9 -> 4461 | E24: =E9 -> 4232 | F24: =D24-E24 -> 229 | G24: =H9 -> 327 | H24: =E24-G24 -> 3905 | I24: =F9 -> 168 | J24: =G9 -> 1.0182 | K24: =I24*J24 -> 171.0576 | L24: =K9 -> 174 | M24: =L9 -> 182 | N24: =H24*K24*12/1000 -> 8015.7591 | O24: =G24*M24*12/1000*0.5 -> 357.084 | P24: =F24*L24*12/1000*0.5 -> 239.076 | Q24: =M9 -> 0.935 | R24: =Q24*D24 -> 4171.035 | S24: =MAX(0,R24-H24) -> 266.035 | T24: =IFERROR(S24/(G24+F24),0) -> 0.47848022 | U24: =(O24+P24)*T24 -> 285.25077 | V24: =N24+U24 -> 8301.0099 | W24: =T9 -> 0.11356953 | X24: =V24*W24 -> 942.74176 | Y24: =V24+X24 -> 9243.7517 | Z24: =Y24/10 -> 924.37517
B25: G1, Gurugram | C25: =C10 -> 0.5 | D25: =D10 -> 3778 | E25: =E10 -> 3238 | F25: =D25-E25 -> 540 | G25: =H10 -> 131 | H25: =E25-G25 -> 3107 | I25: =F10 -> 85 | J25: =G10 -> 1.0162378 | K25: =I25*J25 -> 86.380213 | L25: =K10 -> 86 | M25: =L10 -> 91 | N25: =H25*K25*12/1000 -> 3220.5999 | O25: =G25*M25*12/1000*0.5 -> 71.526 | P25: =F25*L25*12/1000*0.5 -> 278.64 | Q25: =M10 -> 0.8825 | R25: =Q25*D25 -> 3334.085 | S25: =MAX(0,R25-H25) -> 227.085 | T25: =IFERROR(S25/(G25+F25),0) -> 0.33842772 | U25: =(O25+P25)*T25 -> 118.50588 | V25: =N25+U25 -> 3339.1057 | W25: =T10 -> 0.40788801 | X25: =V25*W25 -> 1361.9812 | Y25: =V25+X25 -> 4701.0869 | Z25: =Y25/10 -> 470.10869
B26: G2, Gurugram | C26: =C11 -> 1 | D26: =D11 -> 4060 | E26: =E11 -> 3367 | F26: =D26-E26 -> 693 | G26: =H11 -> 151 | H26: =E26-G26 -> 3216 | I26: =F11 -> 92 | J26: =G11 -> 1.02 | K26: =I26*J26 -> 93.84 | L26: =K11 -> 88 | M26: =L11 -> 88 | N26: =H26*K26*12/1000 -> 3621.4733 | O26: =G26*M26*12/1000*0.5 -> 79.728 | P26: =F26*L26*12/1000*0.5 -> 365.904 | Q26: =M11 -> 0.8275 | R26: =Q26*D26 -> 3359.65 | S26: =MAX(0,R26-H26) -> 143.65 | T26: =IFERROR(S26/(G26+F26),0) -> 0.17020142 | U26: =(O26+P26)*T26 -> 75.8472 | V26: =N26+U26 -> 3697.3205 | W26: =T11 -> 0.5550621 | X26: =V26*W26 -> 2052.2425 | Y26: =V26+X26 -> 5749.5629 | Z26: =Y26/10 -> 574.95629
B27: N1, Noida | C27: =C12 -> 1 | D27: =D12 -> 2017 | E27: =E12 -> 1944 | F27: =D27-E27 -> 73 | G27: =H12 -> 98 | H27: =E27-G27 -> 1846 | I27: =F12 -> 66 | J27: =G12 -> 1.0264569 | K27: =I27*J27 -> 67.746157 | L27: =K12 -> 69 | M27: =L12 -> 69 | N27: =H27*K27*12/1000 -> 1500.7129 | O27: =G27*M27*12/1000*0.5 -> 40.572 | P27: =F27*L27*12/1000*0.5 -> 30.222 | Q27: =M12 -> 0.98 | R27: =Q27*D27 -> 1976.66 | S27: =MAX(0,R27-H27) -> 130.66 | T27: =IFERROR(S27/(G27+F27),0) -> 0.76409357 | U27: =(O27+P27)*T27 -> 54.09324 | V27: =N27+U27 -> 1554.8061 | W27: =T12 -> 0.75332786 | X27: =V27*W27 -> 1171.2788 | Y27: =V27+X27 -> 2726.0849 | Z27: =Y27/10 -> 272.60849
B28: N2, Noida | C28: =C13 -> 1 | D28: =D13 -> 3905 | E28: =E13 -> 3573 | F28: =D28-E28 -> 332 | G28: =H13 -> 818 | H28: =E28-G28 -> 2755 | I28: =F13 -> 66 | J28: =G13 -> 1.0154 | K28: =I28*J28 -> 67.0164 | L28: =K13 -> 66 | M28: =L13 -> 71 | N28: =H28*K28*12/1000 -> 2215.5622 | O28: =G28*M28*12/1000*0.5 -> 348.468 | P28: =F28*L28*12/1000*0.5 -> 131.472 | Q28: =M13 -> 0.9425 | R28: =Q28*D28 -> 3680.4625 | S28: =MAX(0,R28-H28) -> 925.4625 | T28: =IFERROR(S28/(G28+F28),0) -> 0.80475 | U28: =(O28+P28)*T28 -> 386.23172 | V28: =N28+U28 -> 2601.7939 | W28: =T13 -> 0.54869542 | X28: =V28*W28 -> 1427.5924 | Y28: =V28+X28 -> 4029.3863 | Z28: =Y28/10 -> 402.93863
B29: K1, Kolkata | C29: =C14 -> 1 | D29: =D14 -> 3167 | E29: =E14 -> 3130 | F29: =D29-E29 -> 37 | G29: =H14 -> 306 | H29: =E29-G29 -> 2824 | I29: =F14 -> 49 | J29: =G14 -> 1.0091213 | K29: =I29*J29 -> 49.446943 | L29: =K14 -> 54 | M29: =L14 -> 62 | N29: =H29*K29*12/1000 -> 1675.658 | O29: =G29*M29*12/1000*0.5 -> 113.832 | P29: =F29*L29*12/1000*0.5 -> 11.988 | Q29: =M14 -> 0.98 | R29: =Q29*D29 -> 3103.66 | S29: =MAX(0,R29-H29) -> 279.66 | T29: =IFERROR(S29/(G29+F29),0) -> 0.81533528 | U29: =(O29+P29)*T29 -> 102.58548 | V29: =N29+U29 -> 1778.2435 | W29: =T14 -> 0.5854376 | X29: =V29*W29 -> 1041.0506 | Y29: =V29+X29 -> 2819.2941 | Z29: =Y29/10 -> 281.92941
B30: Worldmark, Delhi (NCP) | C30: =C15 -> 0.5 | D30: =D15 -> 1455 | E30: =E15 -> 1384 | F30: =D30-E30 -> 71 | G30: =H15 -> 136 | H30: =E30-G30 -> 1248 | I30: =F15 -> 230 | J30: =G15 -> 1.03 | K30: =I30*J30 -> 236.9 | L30: =K15 -> 237 | M30: =L15 -> 236 | N30: =H30*K30*12/1000 -> 3547.8144 | O30: =G30*M30*12/1000*0.5 -> 192.576 | P30: =F30*L30*12/1000*0.5 -> 100.962 | Q30: =M15 -> 0.96 | R30: =Q30*D30 -> 1396.8 | S30: =MAX(0,R30-H30) -> 148.8 | T30: =IFERROR(S30/(G30+F30),0) -> 0.71884058 | U30: =(O30+P30)*T30 -> 211.00703 | V30: =N30+U30 -> 3758.8214 | W30: =T15 -> 0 | X30: =V30*W30 -> 0 | Y30: =V30+X30 -> 3758.8214 | Z30: =Y30/10 -> 375.88214
B31: Worldmark, Gurugram (NCP) | C31: =C16 -> 0.5 | D31: =D16 -> 751 | E31: =E16 -> 695 | F31: =D31-E31 -> 56 | G31: =H16 -> 27 | H31: =E31-G31 -> 668 | I31: =F16 -> 94 | J31: =G16 -> 1.03 | K31: =I31*J31 -> 96.82 | L31: =K16 -> 93 | M31: =L16 -> 95 | N31: =H31*K31*12/1000 -> 776.10912 | O31: =G31*M31*12/1000*0.5 -> 15.39 | P31: =F31*L31*12/1000*0.5 -> 31.248 | Q31: =M16 -> 0.92 | R31: =Q31*D31 -> 690.92 | S31: =MAX(0,R31-H31) -> 22.92 | T31: =IFERROR(S31/(G31+F31),0) -> 0.27614458 | U31: =(O31+P31)*T31 -> 12.878831 | V31: =N31+U31 -> 788.98795 | W31: =T16 -> 0 | X31: =V31*W31 -> 0 | Y31: =V31+X31 -> 788.98795 | Z31: =Y31/10 -> 78.898795
B32: Airtel Center + Pavilion (NCP) | C32: =C17 -> 0.5 | V32: =$F$17*$G$17^1 -> 1474.2 | Y32: =V32 -> 1474.2 | Z32: =Y32/10 -> 147.42
B33: Consolidated assets (7) | D33: =SUM(D23:D29) -> 28440 | E33: =SUM(E23:E29) -> 26099 | F33: =SUM(F23:F29) -> 2341 | G33: =SUM(G23:G29) -> 2591 | H33: =SUM(H23:H29) -> 23508 | N33: =SUM(N23:N29) -> 27843.958 | O33: =SUM(O23:O29) -> 1512.81 | P33: =SUM(P23:P29) -> 1335.234 | Q33: =R33/D33 -> 0.92315164 | R33: =SUM(R23:R29) -> 26254.433 | S33: =SUM(S23:S29) -> 2746.4325 | U33: =SUM(U23:U29) -> 1526.4944 | V33: =SUM(V23:V29) -> 29370.452 | X33: =SUM(X23:X29) -> 9996.9528 | Y33: =SUM(Y23:Y29) -> 39367.405 | Z33: =SUM(Z23:Z29) -> 3936.7405
B34: North Commercial Portfolio rental (3 lines, 100%) | V34: =SUM(V30:V32) -> 6022.0094 | Z34: =V34/10 -> 602.20094
B35: Consolidated revenue (Rs cr) = (rental + CAM) / 10 | Z35: =Y33/10 -> 3936.7405
B38: FY28E – asset engine (continuing + expiring + vacancy absorption)
B39: Asset | C39: Own % | D39: Operating area | E39: Leased area (open) | F39: Vacant | G39: Area expiring | H39: Continuing area | I39: In-place rent | J39: Escalator | K39: Continuing rent | L39: New-leasing rent | M39: Renewal rent | N39: Continuing rev | O39: Expiry rev (50%) | P39: Vacancy rev (50%) | Q39: Exp. occupancy | R39: Exp. leased area | S39: Absorbed area | T39: Absorption ratio | U39: Re-leasing rev | V39: Total rental | W39: CAM % | X39: CAM revenue | Y39: Total revenue (Rs mn) | Z39: Revenue (Rs cr)
B40: Ecoworld, Bangalore | C40: =C8 -> 0.87 | D40: =D23+R8 -> 7102 | E40: =R23 -> 6628.88 | F40: =D40-E40 -> 473.12 | G40: =I8 -> 309 | H40: =E40-G40 -> 6319.88 | I40: =K23 -> 108.087 | J40: =G8 -> 1.0294 | K40: =I40*J40 -> 111.26476 | L40: =L23*P8 -> 112.36 | M40: =M23*Q8 -> 116.6 | N40: =H40*K40*12/1000 -> 8438.159 | O40: =G40*M40*12/1000*0.5 -> 216.1764 | P40: =F40*L40*12/1000*0.5 -> 318.95858 | Q40: =N8 -> 0.945 | R40: =Q40*D40 -> 6711.39 | S40: =MAX(0,R40-H40) -> 391.51 | T40: =IFERROR(S40/(G40+F40),0) -> 0.50057536 | U40: =(O40+P40)*T40 -> 267.87538 | V40: =N40+U40 -> 8706.0344 | W40: =T8 -> 0.24697739 | X40: =V40*W40 -> 2150.1936 | Y40: =V40+X40 -> 10856.228 | Z40: =Y40/10 -> 1085.6228
B41: Downtown Powai, Mumbai | C41: =C9 -> 0.5 | D41: =D24+R9 -> 4461 | E41: =R24 -> 4171.035 | F41: =D41-E41 -> 289.965 | G41: =I9 -> 613 | H41: =E41-G41 -> 3558.035 | I41: =K24 -> 171.0576 | J41: =G9 -> 1.0182 | K41: =I41*J41 -> 174.17085 | L41: =L24*P9 -> 180.96 | M41: =M24*Q9 -> 192.92 | N41: =H41*K41*12/1000 -> 7436.4717 | O41: =G41*M41*12/1000*0.5 -> 709.55976 | P41: =F41*L41*12/1000*0.5 -> 314.8324 | Q41: =N9 -> 0.9525 | R41: =Q41*D41 -> 4249.1025 | S41: =MAX(0,R41-H41) -> 691.0675 | T41: =IFERROR(S41/(G41+F41),0) -> 0.76533144 | U41: =(O41+P41)*T41 -> 783.99952 | V41: =N41+U41 -> 8220.4712 | W41: =T9 -> 0.11356953 | X41: =V41*W41 -> 933.59502 | Y41: =V41+X41 -> 9154.0662 | Z41: =Y41/10 -> 915.40662
B42: G1, Gurugram | C42: =C10 -> 0.5 | D42: =D25+R10 -> 3803 | E42: =R25 -> 3334.085 | F42: =D42-E42 -> 468.915 | G42: =I10 -> 226 | H42: =E42-G42 -> 3108.085 | I42: =K25 -> 86.380213 | J42: =G10 -> 1.0162378 | K42: =I42*J42 -> 87.782837 | L42: =L25*P10 -> 88.58 | M42: =M25*Q10 -> 96.46 | N42: =H42*K42*12/1000 -> 3274.0382 | O42: =G42*M42*12/1000*0.5 -> 130.79976 | P42: =F42*L42*12/1000*0.5 -> 249.21894 | Q42: =N10 -> 0.91 | R42: =Q42*D42 -> 3460.73 | S42: =MAX(0,R42-H42) -> 352.645 | T42: =IFERROR(S42/(G42+F42),0) -> 0.50746494 | U42: =(O42+P42)*T42 -> 192.84617 | V42: =N42+U42 -> 3466.8844 | W42: =T10 -> 0.40788801 | X42: =V42*W42 -> 1414.1006 | Y42: =V42+X42 -> 4880.985 | Z42: =Y42/10 -> 488.0985
B43: G2, Gurugram | C43: =C11 -> 1 | D43: =D26+R11 -> 4085 | E43: =R26 -> 3359.65 | F43: =D43-E43 -> 725.35 | G43: =I11 -> 0 | H43: =E43-G43 -> 3359.65 | I43: =K26 -> 93.84 | J43: =G11 -> 1.02 | K43: =I43*J43 -> 95.7168 | L43: =L26*P11 -> 90.64 | M43: =M26*Q11 -> 93.28 | N43: =H43*K43*12/1000 -> 3858.8994 | O43: =G43*M43*12/1000*0.5 -> 0 | P43: =F43*L43*12/1000*0.5 -> 394.47434 | Q43: =N11 -> 0.82 | R43: =Q43*D43 -> 3349.7 | S43: =MAX(0,R43-H43) -> 0 | T43: =IFERROR(S43/(G43+F43),0) -> 0 | U43: =(O43+P43)*T43 -> 0 | V43: =N43+U43 -> 3858.8994 | W43: =T11 -> 0.5550621 | X43: =V43*W43 -> 2141.9288 | Y43: =V43+X43 -> 6000.8281 | Z43: =Y43/10 -> 600.08281
B44: N1, Noida | C44: =C12 -> 1 | D44: =D27+R12 -> 2117 | E44: =R27 -> 1976.66 | F44: =D44-E44 -> 140.34 | G44: =I12 -> 0 | H44: =E44-G44 -> 1976.66 | I44: =K27 -> 67.746157 | J44: =G12 -> 1.0264569 | K44: =I44*J44 -> 69.538511 | L44: =L27*P12 -> 71.07 | M44: =M27*Q12 -> 73.14 | N44: =H44*K44*12/1000 -> 1649.4479 | O44: =G44*M44*12/1000*0.5 -> 0 | P44: =F44*L44*12/1000*0.5 -> 59.843783 | Q44: =N12 -> 0.98 | R44: =Q44*D44 -> 2074.66 | S44: =MAX(0,R44-H44) -> 98 | T44: =IFERROR(S44/(G44+F44),0) -> 0.69830412 | U44: =(O44+P44)*T44 -> 41.78916 | V44: =N44+U44 -> 1691.2371 | W44: =T12 -> 0.75332786 | X44: =V44*W44 -> 1274.056 | Y44: =V44+X44 -> 2965.2931 | Z44: =Y44/10 -> 296.52931
B45: N2, Noida | C45: =C13 -> 1 | D45: =D28+R13 -> 4005 | E45: =R28 -> 3680.4625 | F45: =D45-E45 -> 324.5375 | G45: =I13 -> 44 | H45: =E45-G45 -> 3636.4625 | I45: =K28 -> 67.0164 | J45: =G13 -> 1.0154 | K45: =I45*J45 -> 68.048453 | L45: =L28*P13 -> 67.98 | M45: =M28*Q13 -> 75.26 | N45: =H45*K45*12/1000 -> 2969.4678 | O45: =G45*M45*12/1000*0.5 -> 19.86864 | P45: =F45*L45*12/1000*0.5 -> 132.37236 | Q45: =N13 -> 0.9475 | R45: =Q45*D45 -> 3794.7375 | S45: =MAX(0,R45-H45) -> 158.275 | T45: =IFERROR(S45/(G45+F45),0) -> 0.42946783 | U45: =(O45+P45)*T45 -> 65.38261 | V45: =N45+U45 -> 3034.8504 | W45: =T13 -> 0.54869542 | X45: =V45*W45 -> 1665.2085 | Y45: =V45+X45 -> 4700.0588 | Z45: =Y45/10 -> 470.00588
B46: K1, Kolkata | C46: =C14 -> 1 | D46: =D29+R14 -> 3317 | E46: =R29 -> 3103.66 | F46: =D46-E46 -> 213.34 | G46: =I14 -> 438 | H46: =E46-G46 -> 2665.66 | I46: =K29 -> 49.446943 | J46: =G14 -> 1.0091213 | K46: =I46*J46 -> 49.897964 | L46: =L29*P14 -> 56.16 | M46: =M29*Q14 -> 65.72 | N46: =H46*K46*12/1000 -> 1596.1321 | O46: =G46*M46*12/1000*0.5 -> 172.71216 | P46: =F46*L46*12/1000*0.5 -> 71.887046 | Q46: =N14 -> 0.98 | R46: =Q46*D46 -> 3250.66 | S46: =MAX(0,R46-H46) -> 585 | T46: =IFERROR(S46/(G46+F46),0) -> 0.89814843 | U46: =(O46+P46)*T46 -> 219.68639 | V46: =N46+U46 -> 1815.8185 | W46: =T14 -> 0.5854376 | X46: =V46*W46 -> 1063.0484 | Y46: =V46+X46 -> 2878.8669 | Z46: =Y46/10 -> 287.88669
B47: Worldmark, Delhi (NCP) | C47: =C15 -> 0.5 | D47: =D30+R15 -> 1455 | E47: =R30 -> 1396.8 | F47: =D47-E47 -> 58.2 | G47: =I15 -> 151 | H47: =E47-G47 -> 1245.8 | I47: =K30 -> 236.9 | J47: =G15 -> 1.03 | K47: =I47*J47 -> 244.007 | L47: =L30*P15 -> 260.7 | M47: =M30*Q15 -> 250.16 | N47: =H47*K47*12/1000 -> 3647.807 | O47: =G47*M47*12/1000*0.5 -> 226.64496 | P47: =F47*L47*12/1000*0.5 -> 91.03644 | Q47: =N15 -> 0.96 | R47: =Q47*D47 -> 1396.8 | S47: =MAX(0,R47-H47) -> 151 | T47: =IFERROR(S47/(G47+F47),0) -> 0.72179732 | U47: =(O47+P47)*T47 -> 229.30158 | V47: =N47+U47 -> 3877.1086 | W47: =T15 -> 0 | X47: =V47*W47 -> 0 | Y47: =V47+X47 -> 3877.1086 | Z47: =Y47/10 -> 387.71086
B48: Worldmark, Gurugram (NCP) | C48: =C16 -> 0.5 | D48: =D31+R16 -> 751 | E48: =R31 -> 690.92 | F48: =D48-E48 -> 60.08 | G48: =I16 -> 20 | H48: =E48-G48 -> 670.92 | I48: =K31 -> 96.82 | J48: =G16 -> 1.03 | K48: =I48*J48 -> 99.7246 | L48: =L31*P16 -> 97.65 | M48: =M31*Q16 -> 100.7 | N48: =H48*K48*12/1000 -> 802.88674 | O48: =G48*M48*12/1000*0.5 -> 12.084 | P48: =F48*L48*12/1000*0.5 -> 35.200872 | Q48: =N16 -> 0.92 | R48: =Q48*D48 -> 690.92 | S48: =MAX(0,R48-H48) -> 20 | T48: =IFERROR(S48/(G48+F48),0) -> 0.24975025 | U48: =(O48+P48)*T48 -> 11.809409 | V48: =N48+U48 -> 814.69615 | W48: =T16 -> 0 | X48: =V48*W48 -> 0 | Y48: =V48+X48 -> 814.69615 | Z48: =Y48/10 -> 81.469615
B49: Airtel Center + Pavilion (NCP) | C49: =C17 -> 0.5 | V49: =$F$17*$G$17^2 -> 1547.91 | Y49: =V49 -> 1547.91 | Z49: =Y49/10 -> 154.791
B50: Consolidated assets (7) | D50: =SUM(D40:D46) -> 28890 | E50: =SUM(E40:E46) -> 26254.433 | F50: =SUM(F40:F46) -> 2635.5675 | G50: =SUM(G40:G46) -> 1630 | H50: =SUM(H40:H46) -> 24624.432 | N50: =SUM(N40:N46) -> 29222.616 | O50: =SUM(O40:O46) -> 1249.1167 | P50: =SUM(P40:P46) -> 1541.5875 | Q50: =R50/D50 -> 0.93080582 | R50: =SUM(R40:R46) -> 26890.98 | S50: =SUM(S40:S46) -> 2276.4975 | U50: =SUM(U40:U46) -> 1571.5792 | V50: =SUM(V40:V46) -> 30794.195 | X50: =SUM(X40:X46) -> 10642.131 | Y50: =SUM(Y40:Y46) -> 41436.326 | Z50: =SUM(Z40:Z46) -> 4143.6326
B51: North Commercial Portfolio rental (3 lines, 100%) | V51: =SUM(V47:V49) -> 6239.7148 | Z51: =V51/10 -> 623.97148
B52: Consolidated revenue (Rs cr) = (rental + CAM) / 10 | Z52: =Y50/10 -> 4143.6326
B55: FY29E – asset engine (continuing + expiring + vacancy absorption)
B56: Asset | C56: Own % | D56: Operating area | E56: Leased area (open) | F56: Vacant | G56: Area expiring | H56: Continuing area | I56: In-place rent | J56: Escalator | K56: Continuing rent | L56: New-leasing rent | M56: Renewal rent | N56: Continuing rev | O56: Expiry rev (50%) | P56: Vacancy rev (50%) | Q56: Exp. occupancy | R56: Exp. leased area | S56: Absorbed area | T56: Absorption ratio | U56: Re-leasing rev | V56: Total rental | W56: CAM % | X56: CAM revenue | Y56: Total revenue (Rs mn) | Z56: Revenue (Rs cr)
B57: Ecoworld, Bangalore | C57: =C8 -> 0.87 | D57: =D40+S8 -> 7152 | E57: =R40 -> 6711.39 | F57: =D57-E57 -> 440.61 | G57: =J8 -> 660 | H57: =E57-G57 -> 6051.39 | I57: =K40 -> 111.26476 | J57: =G8 -> 1.0294 | K57: =I57*J57 -> 114.53594 | L57: =L40*P8 -> 119.1016 | M57: =M40*Q8 -> 123.596 | N57: =H57*K57*12/1000 -> 8317.2198 | O57: =G57*M57*12/1000*0.5 -> 489.44016 | P57: =F57*L57*12/1000*0.5 -> 314.86414 | Q57: =O8 -> 0.9525 | R57: =Q57*D57 -> 6812.28 | S57: =MAX(0,R57-H57) -> 760.89 | T57: =IFERROR(S57/(G57+F57),0) -> 0.69133481 | U57: =(O57+P57)*T57 -> 556.04355 | V57: =N57+U57 -> 8873.2634 | W57: =T8 -> 0.24697739 | X57: =V57*W57 -> 2191.4954 | Y57: =V57+X57 -> 11064.759 | Z57: =Y57/10 -> 1106.4759
B58: Downtown Powai, Mumbai | C58: =C9 -> 0.5 | D58: =D41+S9 -> 4461 | E58: =R41 -> 4249.1025 | F58: =D58-E58 -> 211.8975 | G58: =J9 -> 415 | H58: =E58-G58 -> 3834.1025 | I58: =K41 -> 174.17085 | J58: =G9 -> 1.0182 | K58: =I58*J58 -> 177.34076 | L58: =L41*P9 -> 188.1984 | M58: =M41*Q9 -> 204.4952 | N58: =H58*K58*12/1000 -> 8159.3117 | O58: =G58*M58*12/1000*0.5 -> 509.19305 | P58: =F58*L58*12/1000*0.5 -> 239.27262 | Q58: =O9 -> 0.9575 | R58: =Q58*D58 -> 4271.4075 | S58: =MAX(0,R58-H58) -> 437.305 | T58: =IFERROR(S58/(G58+F58),0) -> 0.69757018 | U58: =(O58+P58)*T58 -> 522.10733 | V58: =N58+U58 -> 8681.419 | W58: =T9 -> 0.11356953 | X58: =V58*W58 -> 985.94465 | Y58: =V58+X58 -> 9667.3637 | Z58: =Y58/10 -> 966.73637
B59: G1, Gurugram | C59: =C10 -> 0.5 | D59: =D42+S10 -> 3828 | E59: =R42 -> 3460.73 | F59: =D59-E59 -> 367.27 | G59: =J10 -> 0 | H59: =E59-G59 -> 3460.73 | I59: =K42 -> 87.782837 | J59: =G10 -> 1.0162378 | K59: =I59*J59 -> 89.208237 | L59: =L42*P10 -> 91.2374 | M59: =M42*Q10 -> 102.2476 | N59: =H59*K59*12/1000 -> 3704.7075 | O59: =G59*M59*12/1000*0.5 -> 0 | P59: =F59*L59*12/1000*0.5 -> 201.05256 | Q59: =O10 -> 0.925 | R59: =Q59*D59 -> 3540.9 | S59: =MAX(0,R59-H59) -> 80.17 | T59: =IFERROR(S59/(G59+F59),0) -> 0.21828627 | U59: =(O59+P59)*T59 -> 43.887014 | V59: =N59+U59 -> 3748.5945 | W59: =T10 -> 0.40788801 | X59: =V59*W59 -> 1529.0068 | Y59: =V59+X59 -> 5277.6013 | Z59: =Y59/10 -> 527.76013
B60: G2, Gurugram | C60: =C11 -> 1 | D60: =D43+S11 -> 4110 | E60: =R43 -> 3349.7 | F60: =D60-E60 -> 760.3 | G60: =J11 -> 13 | H60: =E60-G60 -> 3336.7 | I60: =K43 -> 95.7168 | J60: =G11 -> 1.02 | K60: =I60*J60 -> 97.631136 | L60: =L43*P11 -> 93.3592 | M60: =M43*Q11 -> 98.8768 | N60: =H60*K60*12/1000 -> 3909.1897 | O60: =G60*M60*12/1000*0.5 -> 7.7123904 | P60: =F60*L60*12/1000*0.5 -> 425.886 | Q60: =O11 -> 0.84 | R60: =Q60*D60 -> 3452.4 | S60: =MAX(0,R60-H60) -> 115.7 | T60: =IFERROR(S60/(G60+F60),0) -> 0.14961852 | U60: =(O60+P60)*T60 -> 64.874348 | V60: =N60+U60 -> 3974.0641 | W60: =T11 -> 0.5550621 | X60: =V60*W60 -> 2205.8523 | Y60: =V60+X60 -> 6179.9164 | Z60: =Y60/10 -> 617.99164
B61: N1, Noida | C61: =C12 -> 1 | D61: =D44+S12 -> 2267 | E61: =R44 -> 2074.66 | F61: =D61-E61 -> 192.34 | G61: =J12 -> 102 | H61: =E61-G61 -> 1972.66 | I61: =K44 -> 69.538511 | J61: =G12 -> 1.0264569 | K61: =I61*J61 -> 71.378286 | L61: =L44*P12 -> 73.2021 | M61: =M44*Q12 -> 77.5284 | N61: =H61*K61*12/1000 -> 1689.6611 | O61: =G61*M61*12/1000*0.5 -> 47.447381 | P61: =F61*L61*12/1000*0.5 -> 84.478151 | Q61: =O12 -> 0.98 | R61: =Q61*D61 -> 2221.66 | S61: =MAX(0,R61-H61) -> 249 | T61: =IFERROR(S61/(G61+F61),0) -> 0.84596045 | U61: =(O61+P61)*T61 -> 111.60378 | V61: =N61+U61 -> 1801.2649 | W61: =T12 -> 0.75332786 | X61: =V61*W61 -> 1356.943 | Y61: =V61+X61 -> 3158.2079 | Z61: =Y61/10 -> 315.82079
B62: N2, Noida | C62: =C13 -> 1 | D62: =D45+S13 -> 4155 | E62: =R45 -> 3794.7375 | F62: =D62-E62 -> 360.2625 | G62: =J13 -> 130 | H62: =E62-G62 -> 3664.7375 | I62: =K45 -> 68.048453 | J62: =G13 -> 1.0154 | K62: =I62*J62 -> 69.096399 | L62: =L45*P13 -> 70.0194 | M62: =M45*Q13 -> 79.7756 | N62: =H62*K62*12/1000 -> 3038.642 | O62: =G62*M62*12/1000*0.5 -> 62.224968 | P62: =F62*L62*12/1000*0.5 -> 151.35218 | Q62: =O13 -> 0.955 | R62: =Q62*D62 -> 3968.025 | S62: =MAX(0,R62-H62) -> 303.2875 | T62: =IFERROR(S62/(G62+F62),0) -> 0.61862268 | U62: =(O62+P62)*T62 -> 132.12367 | V62: =N62+U62 -> 3170.7656 | W62: =T13 -> 0.54869542 | X62: =V62*W62 -> 1739.7846 | Y62: =V62+X62 -> 4910.5502 | Z62: =Y62/10 -> 491.05502
B63: K1, Kolkata | C63: =C14 -> 1 | D63: =D46+S14 -> 3567 | E63: =R46 -> 3250.66 | F63: =D63-E63 -> 316.34 | G63: =J14 -> 5 | H63: =E63-G63 -> 3245.66 | I63: =K46 -> 49.897964 | J63: =G14 -> 1.0091213 | K63: =I63*J63 -> 50.353098 | L63: =L46*P14 -> 58.4064 | M63: =M46*Q14 -> 69.6632 | N63: =H63*K63*12/1000 -> 1961.1484 | O63: =G63*M63*12/1000*0.5 -> 2.089896 | P63: =F63*L63*12/1000*0.5 -> 110.85768 | Q63: =O14 -> 0.9875 | R63: =Q63*D63 -> 3522.4125 | S63: =MAX(0,R63-H63) -> 276.7525 | T63: =IFERROR(S63/(G63+F63),0) -> 0.8612451 | U63: =(O63+P63)*T63 -> 97.275549 | V63: =N63+U63 -> 2058.424 | W63: =T14 -> 0.5854376 | X63: =V63*W63 -> 1205.0788 | Y63: =V63+X63 -> 3263.5028 | Z63: =Y63/10 -> 326.35028
B64: Worldmark, Delhi (NCP) | C64: =C15 -> 0.5 | D64: =D47+S15 -> 1455 | E64: =R47 -> 1396.8 | F64: =D64-E64 -> 58.2 | G64: =J15 -> 36 | H64: =E64-G64 -> 1360.8 | I64: =K47 -> 244.007 | J64: =G15 -> 1.03 | K64: =I64*J64 -> 251.32721 | L64: =L47*P15 -> 286.77 | M64: =M47*Q15 -> 265.1696 | N64: =H64*K64*12/1000 -> 4104.0728 | O64: =G64*M64*12/1000*0.5 -> 57.276634 | P64: =F64*L64*12/1000*0.5 -> 100.14008 | Q64: =O15 -> 0.96 | R64: =Q64*D64 -> 1396.8 | S64: =MAX(0,R64-H64) -> 36 | T64: =IFERROR(S64/(G64+F64),0) -> 0.38216561 | U64: =(O64+P64)*T64 -> 60.159255 | V64: =N64+U64 -> 4164.2321 | W64: =T15 -> 0 | X64: =V64*W64 -> 0 | Y64: =V64+X64 -> 4164.2321 | Z64: =Y64/10 -> 416.42321
B65: Worldmark, Gurugram (NCP) | C65: =C16 -> 0.5 | D65: =D48+S16 -> 751 | E65: =R48 -> 690.92 | F65: =D65-E65 -> 60.08 | G65: =J16 -> 37 | H65: =E65-G65 -> 653.92 | I65: =K48 -> 99.7246 | J65: =G16 -> 1.03 | K65: =I65*J65 -> 102.71634 | L65: =L48*P16 -> 102.5325 | M65: =M48*Q16 -> 106.742 | N65: =H65*K65*12/1000 -> 806.01921 | O65: =G65*M65*12/1000*0.5 -> 23.696724 | P65: =F65*L65*12/1000*0.5 -> 36.960916 | Q65: =O16 -> 0.92 | R65: =Q65*D65 -> 690.92 | S65: =MAX(0,R65-H65) -> 37 | T65: =IFERROR(S65/(G65+F65),0) -> 0.38112897 | U65: =(O65+P65)*T65 -> 23.118383 | V65: =N65+U65 -> 829.1376 | W65: =T16 -> 0 | X65: =V65*W65 -> 0 | Y65: =V65+X65 -> 829.1376 | Z65: =Y65/10 -> 82.91376
B66: Airtel Center + Pavilion (NCP) | C66: =C17 -> 0.5 | V66: =$F$17*$G$17^3 -> 1625.3055 | Y66: =V66 -> 1625.3055 | Z66: =Y66/10 -> 162.53055
B67: Consolidated assets (7) | D67: =SUM(D57:D63) -> 29540 | E67: =SUM(E57:E63) -> 26890.98 | F67: =SUM(F57:F63) -> 2649.02 | G67: =SUM(G57:G63) -> 1325 | H67: =SUM(H57:H63) -> 25565.98 | N67: =SUM(N57:N63) -> 30779.88 | O67: =SUM(O57:O63) -> 1118.1078 | P67: =SUM(P57:P63) -> 1527.7633 | Q67: =R67/D67 -> 0.94072732 | R67: =SUM(R57:R63) -> 27789.085 | S67: =SUM(S57:S63) -> 2223.105 | U67: =SUM(U57:U63) -> 1527.9152 | V67: =SUM(V57:V63) -> 32307.795 | X67: =SUM(X57:X63) -> 11214.106 | Y67: =SUM(Y57:Y63) -> 43521.901 | Z67: =SUM(Z57:Z63) -> 4352.1901
B68: North Commercial Portfolio rental (3 lines, 100%) | V68: =SUM(V64:V66) -> 6618.6752 | Z68: =V68/10 -> 661.86752
B69: Consolidated revenue (Rs cr) = (rental + CAM) / 10 | Z69: =Y67/10 -> 4352.1901
B74: 2. Partner (minority) share of consolidated value – FY28E revenue-weighted (used as proxy for value weights)
B75: Σ revenue_i x (1 − own%_i) / Σ revenue_i | D75: =SUMPRODUCT(Z40:Z46,1-C40:C46)/SUM(Z40:Z46) -> 0.20341657 | E75: Partners: GIC 50% of G1 & Downtown Powai; 360 ONE ~13% of Ecoworld. Cross-check: ~20% of 100%-basis equity implied by Mar-26 reported NAV vs GAV.
B77: 3. Quarterly phasing of annual revenue (user's assumed weights, 'Revenue Estimation'!AT5:AV8)
B78: Quarter | C78: FY27 weight | D78: FY28 weight | E78: FY29 weight | F78: FY27 Rs cr | G78: FY28 Rs cr | H78: FY29 Rs cr
B79: Q1 | C79: 0.24 | D79: 0.245 | E79: 0.24 | F79: =C79*Rev_Build!$Z$35 -> 944.81772 | G79: =D79*Rev_Build!$Z$52 -> 1015.19 | H79: =E79*Rev_Build!$Z$69 -> 1044.5256
B80: Q2 | C80: 0.245 | D80: 0.25 | E80: 0.2475 | F80: =C80*Rev_Build!$Z$35 -> 964.50143 | G80: =D80*Rev_Build!$Z$52 -> 1035.9082 | H80: =E80*Rev_Build!$Z$69 -> 1077.1671
B81: Q3 | C81: 0.26 | D81: 0.2575 | E81: 0.2575 | F81: =C81*Rev_Build!$Z$35 -> 1023.5525 | G81: =D81*Rev_Build!$Z$52 -> 1066.9854 | H81: =E81*Rev_Build!$Z$69 -> 1120.689
B82: Q4 | C82: 0.255 | D82: 0.2475 | E82: 0.255 | F82: =C82*Rev_Build!$Z$35 -> 1003.8688 | G82: =D82*Rev_Build!$Z$52 -> 1025.5491 | H82: =E82*Rev_Build!$Z$69 -> 1109.8085
B83: Total | C83: =SUM(C79:C82) -> 1 | D83: =SUM(D79:D82) -> 1 | E83: =SUM(E79:E82) -> 1 | F83: =SUM(F79:F82) -> 3936.7405 | G83: =SUM(G79:G82) -> 4143.6326 | H83: =SUM(H79:H82) -> 4352.1901

Sheet Fin_Proj
B1: FINANCIAL PROJECTIONS – income statement, debt schedule, capex and NDCF/DPU (consolidated, Rs crore)
B2: FY22A–FY26A from user model 'Quarterly-data'!AN:AR · FY27E–FY29E revenue from Rev_Build · FY30E–FY36E driver-based fade
B4: Rs crore | C4: Unit | D4: FY22A | E4: FY23A | F4: FY24A | G4: FY25A | H4: FY26A | I4: FY27E | J4: FY28E | K4: FY29E | L4: FY30E | M4: FY31E | N4: FY32E | O4: FY33E | P4: FY34E | Q4: FY35E | R4: FY36E
B5: Projection year index | I5: 1 | J5: 2 | K5: 3 | L5: 4 | M5: 5 | N5: 6 | O5: 7 | P5: 8 | Q5: 9 | R5: 10
B6: Forecast drivers (green = assumption)
B7: Revenue growth (FY30E+) | C7: % | L7: 0.05 | M7: 0.05 | N7: 0.05 | O7: 0.05 | P7: 0.05 | Q7: 0.05 | R7: 0.05 | T7: ASSUMPTION – ~in-place escalation 4.8%/yr + MTM; fades toward terminal growth. FY27–29 come from Rev_Build
B8: Cost of services (% of revenue) | C8: % | I8: 0.003792814 | J8: 0.0036627584 | K8: 0.0037059687 | L8: =K8 -> 0.0037059687 | M8: =K8 -> 0.0037059687 | N8: =K8 -> 0.0037059687 | O8: =K8 -> 0.0037059687 | P8: =K8 -> 0.0037059687 | Q8: =K8 -> 0.0037059687 | R8: =K8 -> 0.0037059687 | T8: User model Quarterly-data rows 11/3
B9: Operating expenses (% of revenue) | C9: % | I9: 0.28005 | J9: 0.259975 | K9: 0.25 | L9: =K9 -> 0.25 | M9: =K9 -> 0.25 | N9: =K9 -> 0.25 | O9: =K9 -> 0.25 | P9: =K9 -> 0.25 | Q9: =K9 -> 0.25 | R9: =K9 -> 0.25 | T9: User model: 28% / 26% / 25%; held at 25% thereafter
B10: Employee cost (% of revenue) | C10: % | I10: 0.011 | J10: 0.011 | K10: 0.011 | L10: =K10 -> 0.011 | M10: =K10 -> 0.011 | N10: =K10 -> 0.011 | O10: =K10 -> 0.011 | P10: =K10 -> 0.011 | Q10: =K10 -> 0.011 | R10: =K10 -> 0.011 | T10: User model: 1.1%
B11: Other income (% of revenue) | C11: % | I11: 0.036204967 | J11: 0.03531722 | K11: 0.035279573 | L11: 0.035 | M11: 0.035 | N11: 0.035 | O11: 0.035 | P11: 0.035 | Q11: 0.035 | R11: 0.035 | T11: User model average-ratio method; 3.5% thereafter
B12: Depreciation growth (FY30E+) | C12: % | L12: 0.01 | M12: 0.01 | N12: 0.01 | O12: 0.01 | P12: 0.01 | Q12: 0.01 | R12: 0.01 | T12: ASSUMPTION – operating area flat after FY29 in explicit build
B13: Effective tax rate on PBT (P&L) | C13: % | I13: 0.24 | J13: 0.25 | K13: 0.26 | L13: =Inputs!$C$42 -> 0.2517 | M13: =Inputs!$C$42 -> 0.2517 | N13: =Inputs!$C$42 -> 0.2517 | O13: =Inputs!$C$42 -> 0.2517 | P13: =Inputs!$C$42 -> 0.2517 | Q13: =Inputs!$C$42 -> 0.2517 | R13: =Inputs!$C$42 -> 0.2517 | T13: User model: 24%/25%/26%; statutory 25.17% from FY30E
B14: Cash (current) tax as % of P&L tax | C14: % | I14: 0.3 | J14: 0.4 | K14: 0.5 | L14: 0.6 | M14: 0.7 | N14: 0.8 | O14: 0.9 | P14: 1 | Q14: 1 | R14: 1 | T14: ASSUMPTION – FY25 tax paid Rs 8 cr vs P&L tax Rs 89.5 cr (~9%); shield assumed to erode to 100% by FY34E
B15: Refurbishment / repositioning capex | C15: Rs cr | I15: 150 | J15: 150 | K15: 150 | L15: 100 | M15: 100 | N15: 100 | O15: 100 | P15: 100 | Q15: 100 | R15: 100 | T15: ASSUMPTION – SEZ→NPA conversion, Ecoworld repositioning, tenant improvements
B16: Interest rate on average debt | C16: % | I16: 0.075 | J16: 0.075 | K16: 0.075 | L16: 0.075 | M16: 0.075 | N16: 0.075 | O16: 0.075 | P16: 0.075 | Q16: 0.075 | R16: 0.075 | T16: Q1 FY27 avg 7.3% (90% floating) + 25bp repo hike pass-through
B17: Minority interest in profit (P&L) | C17: Rs cr | I17: -55.521 | J17: -55.521 | K17: -55.521 | L17: -55.521 | M17: -55.521 | N17: -55.521 | O17: -55.521 | P17: -55.521 | Q17: -55.521 | R17: -55.521 | T17: User model Quarterly-data row 39 (held flat)
B18: Share of associates (NCP) | C18: Rs cr | I18: -40.284 | J18: -40.284 | K18: -40.284 | L18: -40.284 | M18: -40.284 | N18: -40.284 | O18: -40.284 | P18: -40.284 | Q18: -40.284 | R18: -40.284 | T18: User model Quarterly-data row 40 (held flat)
B19: Memo: user's coverage-ratio interest | C19: Rs cr | I19: 1027.2688 | J19: 1174.3513 | K19: 1319.6854 | T19: User model Quarterly-data row 32 (EBITDA/ICR − Rs 60 cr per quarter)
B22: Income statement
B24: Revenue from operations | D24: 876.791 | E24: 1196.999 | F24: 1780.481 | G24: 2385.592 | H24: 2962.259 | I24: =Rev_Build!$Z$35 -> 3936.7405 | J24: =Rev_Build!$Z$52 -> 4143.6326 | K24: =Rev_Build!$Z$69 -> 4352.1901 | L24: =K24*(1+L7) -> 4569.7996 | M24: =L24*(1+M7) -> 4798.2896 | N24: =M24*(1+N7) -> 5038.2041 | O24: =N24*(1+O7) -> 5290.1143 | P24: =O24*(1+P7) -> 5554.62 | Q24: =P24*(1+Q7) -> 5832.351 | R24: =Q24*(1+R7) -> 6123.9685
B25: growth % | E25: =E24/D24-1 -> 0.36520448 | F25: =F24/E24-1 -> 0.48745404 | G25: =G24/F24-1 -> 0.33985816 | H25: =H24/G24-1 -> 0.2417291 | I25: =I24/H24-1 -> 0.32896567 | J25: =J24/I24-1 -> 0.052554165 | K25: =K24/J24-1 -> 0.050332039 | L25: =L24/K24-1 -> 0.05 | ... R25: =R24/Q24-1 -> 0.05
B26: Cost of services | D26: 2.4130606 | E26: 5.5022564 | F26: 7.3817212 | G26: 8.3820322 | H26: 10.886709 | I26: =I24*I8 -> 14.931325 | J26: =J24*J8 -> 15.177125 | K26: =K24*K8 -> 16.12908 | L26: =L24*L8 -> 16.935534 | M26: =M24*M8 -> 17.782311 | N26: =N24*N8 -> 18.671427 | O26: =O24*O8 -> 19.604998 | P26: =P24*P8 -> 20.585248 | ... R26: =R24*R8 -> 22.695236
B27: Operating expenses | D27: 236.382 | E27: 341.215 | F27: 474.417 | G27: 622.578 | H27: 783.776 | I27: =I24*I9 -> 1102.4842 | J27: =J24*J9 -> 1077.2409 | K27: =K24*K9 -> 1088.0475 | L27: =L24*L9 -> 1142.4499 | M27: =M24*M9 -> 1199.5724 | N27: =N24*N9 -> 1259.551 | O27: =O24*O9 -> 1322.5286 | P27: =P24*P9 -> 1388.655 | ... R27: =R24*R9 -> 1530.9921
B28: Employee cost | D28: 19.685 | E28: 34.731 | F28: 43.989 | G28: 24.748 | H28: 31.257 | I28: =I24*I10 -> 43.304146 | J28: =J24*J10 -> 45.579959 | K28: =K24*K10 -> 47.874091 | L28: =L24*L10 -> 50.267796 | M28: =M24*M10 -> 52.781185 | N28: =N24*N10 -> 55.420245 | O28: =O24*O10 -> 58.191257 | P28: =P24*P10 -> 61.10082 | ... R28: =R24*R10 -> 67.363654
B29: EBITDA | D29: 618.31094 | E29: 815.55074 | F29: 1254.6933 | G29: 1729.884 | H29: 2136.3393 | I29: =I24-I26-I27-I28 -> 2776.0209 | J29: =J24-J26-J27-J28 -> 3005.6346 | K29: =K24-K26-K27-K28 -> 3200.1394 | L29: =L24-L26-L27-L28 -> 3360.1464 | M29: =M24-M26-M27-M28 -> 3528.1537 | N29: =N24-N26-N27-N28 -> 3704.5614 | O29: =O24-O26-O27-O28 -> 3889.7894 | P29: =P24-P26-P27-P28 -> 4084.2789 | ... R29: =R24-R26-R27-R28 -> 4502.9175
B30: EBITDA margin | D30: =D29/D24 -> 0.70519763 | E30: =E29/E24 -> 0.68132951 | F30: =F29/F24 -> 0.70469344 | G30: =G29/G24 -> 0.72513823 | H30: =H29/H24 -> 0.72118586 | I30: =I29/I24 -> 0.70515719 | J30: =J29/J24 -> 0.72536224 | K30: =K29/K24 -> 0.73529403 | ... R30: =R29/R24 -> 0.73529403
B31: Depreciation & amortisation | D31: 208.477 | E31: 275.202 | F31: 411.083 | G31: 429.891 | H31: 469.402 | I31: =Rev_Build!$D$33*Inputs!$C$48*4 -> 580 | J31: =Rev_Build!$D$50*Inputs!$C$48*4 -> 589.17722 | K31: =Rev_Build!$D$67*Inputs!$C$48*4 -> 602.43319 | L31: =K31*(1+L12) -> 608.45752 | M31: =L31*(1+M12) -> 614.5421 | N31: =M31*(1+N12) -> 620.68752 | O31: =N31*(1+O12) -> 626.8944 | P31: =O31*(1+P12) -> 633.16334 | Q31: =P31*(1+Q12) -> 639.49497 | R31: =Q31*(1+R12) -> 645.88992
B32: EBIT | D32: =D29-D31 -> 409.83394 | E32: =E29-E31 -> 540.34874 | F32: =F29-F31 -> 843.61028 | G32: =G29-G31 -> 1299.993 | H32: =H29-H31 -> 1666.9373 | I32: =I29-I31 -> 2196.0209 | J32: =J29-J31 -> 2416.4574 | K32: =K29-K31 -> 2597.7062 | ... R32: =R29-R31 -> 3857.0276
B33: Other income | D33: 22.423 | E33: 32.48 | F33: 70.673 | G33: 84.42 | H33: 100.187 | I33: =I24*I11 -> 142.52956 | J33: =J24*J11 -> 146.34159 | K33: =K24*K11 -> 153.54341 | L33: =L24*L11 -> 159.94299 | M33: =M24*M11 -> 167.94014 | N33: =N24*N11 -> 176.33714 | O33: =O24*O11 -> 185.154 | P33: =P24*P11 -> 194.4117 | ... R33: =R24*R11 -> 214.3389
B34: Interest expense | D34: 208.069 | E34: 432.457 | F34: 852.199 | G34: 1078.177 | H34: 974.78 | I34: =IF(Inputs!$C$51=1,I55,I19) -> 1116.2181 | J34: =IF(Inputs!$C$51=1,J55,J19) -> 1146.3587 | K34: =IF(Inputs!$C$51=1,K55,K19) -> 1178.9368 | L34: =L55 -> 1196.2337 | M34: =M55 -> 1203.7337 | N34: =N55 -> 1211.2337 | O34: =O55 -> 1218.7337 | P34: =P55 -> 1226.2337 | Q34: =Q55 -> 1233.7337 | R34: =R55 -> 1241.2337 | T34: Default = debt-schedule interest (rows 51–55). User's method implies debt rising ~Rs 4,000 cr by FY29 with no acquisition revenue in the build.
B35: Profit before tax | D35: =D32+D33-D34 -> 224.18794 | E35: =E32+E33-E34 -> 140.37174 | F35: =F32+F33-F34 -> 62.084279 | G35: =G32+G33-G34 -> 306.23597 | H35: =H32+H33-H34 -> 792.34429 | I35: =I32+I33-I34 -> 1222.3323 | J35: =J32+J33-J34 -> 1416.4403 | K35: =K32+K33-K34 -> 1572.3128 | ... R35: =R32+R33-R34 -> 2830.1328
B36: Tax | D36: -22.086 | E36: 9.158 | F36: 68.811 | G36: 88.255 | H36: 221.668 | I36: =I35*I13 -> 293.35976 | J36: =J35*J13 -> 354.11008 | K36: =K35*K13 -> 408.80132 | L36: =L35*L13 -> 431.76571 | M36: =M35*M13 -> 472.6468 | N36: =N35*N13 -> 515.72758 | O36: =O35*O13 -> 561.11867 | P36: =P35*P13 -> 608.93619 | ... R36: =R35*R13 -> 712.34442 | T36: FY26A tax Rs 221.7 cr includes Q4 charge of Rs 169.5 cr (75% of Q4 PBT) – treated as non-recurring in Hist_Quality.
B37: Profit after tax | D37: =D35-D36 -> 246.27394 | E37: =E35-E36 -> 131.21374 | F37: =F35-F36 -> -6.7267212 | G37: =G35-G36 -> 217.98097 | H37: =H35-H36 -> 570.67629 | I37: =I35-I36 -> 928.97258 | J37: =J35-J36 -> 1062.3302 | K37: =K35-K36 -> 1163.5115 | ... R37: =R35-R36 -> 2117.7884
B38: Minority interest | D38: 0 | E38: 0 | F38: 27.459 | G38: 24.807 | H38: -55.521 | I38: =I17 -> -55.521 | J38: =J17 -> -55.521 | K38: =K17 -> -55.521 | L38: =L17 -> -55.521 | M38: =M17 -> -55.521 | N38: =N17 -> -55.521 | O38: =O17 -> -55.521 | P38: =P17 -> -55.521 | ... R38: =R17 -> -55.521
B39: Share of associates (NCP) | D39: 0 | E39: 0 | F39: 0 | G39: -54.144 | H39: -40.284 | I39: =I18 -> -40.284 | J39: =J18 -> -40.284 | K39: =K18 -> -40.284 | L39: =L18 -> -40.284 | M39: =M18 -> -40.284 | N39: =N18 -> -40.284 | O39: =O18 -> -40.284 | P39: =P18 -> -40.284 | ... R39: =R18 -> -40.284
B40: Net profit to unitholders | D40: =D37+D38+D39 -> 246.27394 | E40: =E37+E38+E39 -> 131.21374 | F40: =F37+F38+F39 -> 20.732279 | G40: =G37+G38+G39 -> 188.64397 | H40: =H37+H38+H39 -> 474.87129 | I40: =I37+I38+I39 -> 833.16758 | J40: =J37+J38+J39 -> 966.52523 | K40: =K37+K38+K39 -> 1067.7065 | ... R40: =R37+R38+R39 -> 2021.9834
B41: Units outstanding (cr) | I41: =Inputs!$C$11 -> 82.988087 | J41: =Inputs!$C$11 -> 82.988087 | K41: =Inputs!$C$11 -> 82.988087 | L41: =Inputs!$C$11 -> 82.988087 | M41: =Inputs!$C$11 -> 82.988087 | N41: =Inputs!$C$11 -> 82.988087 | O41: =Inputs!$C$11 -> 82.988087 | P41: =Inputs!$C$11 -> 82.988087 | ... R41: =Inputs!$C$11 -> 82.988087
B42: Earnings per unit (Rs) | I42: =I40/I41 -> 10.039605 | J42: =J40/J41 -> 11.646554 | K42: =K40/K41 -> 12.86578 | L42: =L40/L41 -> 14.313228 | M42: =M40/M41 -> 15.777761 | N42: =N40/N41 -> 17.321097 | O42: =O40/O41 -> 18.947197 | P42: =P40/P41 -> 20.660223 | ... R42: =R40/R41 -> 24.364742
B43: Memo: reconciliation to user's model (uses user's interest, other income and tax rates)
B44: Net profit using user's interest | I44: =(I32+I33-I19)*(1-I13)+I38+I39 -> 900.76903 | J44: =(J32+J33-J19)*(1-J13)+J38+J39 -> 945.5308 | K44: =(K32+K33-K19)*(1-K13)+K38+K39 -> 963.5525
B45: User model net profit (Quarterly-data row 41) | I45: 900.76903 | J45: 945.5308 | K45: 963.5525
B46: Difference | I46: =I44-I45 -> -1.8189894e-12 | J46: =J44-J45 -> -3.2969183e-12 | K46: =K44-K45 -> 2.3874236e-12
B47: User model EBITDA (row 21) | I47: 2776.0209 | J47: 3005.6346 | K47: 3200.1394
B48: Difference (EBITDA) | I48: =I29-I47 -> -5.0022209e-12 | J48: =J29-J47 -> 0 | K48: =K29-K47 -> 0
B50: Debt schedule (gross debt held flat; growth capex debt-funded; refinancing assumed)
B51: Opening gross debt | I51: =Inputs!$C$33 -> 14734.783 | J51: =I53 -> 15031.033 | K51: =J53 -> 15538.533 | L51: =K53 -> 15899.783 | M51: =L53 -> 15999.783 | N51: =M53 -> 16099.783 | O51: =N53 -> 16199.783 | P51: =O53 -> 16299.783 | Q51: =P53 -> 16399.783 | R51: =Q53 -> 16499.783
B52: + Debt-funded growth & refurbishment capex | I52: =(I66+I67)*Inputs!$C$47 -> 296.25 | J52: =(J66+J67)*Inputs!$C$47 -> 507.5 | K52: =(K66+K67)*Inputs!$C$47 -> 361.25 | L52: =(L66+L67)*Inputs!$C$47 -> 100 | M52: =(M66+M67)*Inputs!$C$47 -> 100 | N52: =(N66+N67)*Inputs!$C$47 -> 100 | O52: =(O66+O67)*Inputs!$C$47 -> 100 | P52: =(P66+P67)*Inputs!$C$47 -> 100 | ... R52: =(R66+R67)*Inputs!$C$47 -> 100
B53: Closing gross debt | I53: =I51+I52 -> 15031.033 | J53: =J51+J52 -> 15538.533 | K53: =K51+K52 -> 15899.783 | L53: =L51+L52 -> 15999.783 | M53: =M51+M52 -> 16099.783 | N53: =N51+N52 -> 16199.783 | O53: =O51+O52 -> 16299.783 | P53: =P51+P52 -> 16399.783 | ... R53: =R51+R52 -> 16599.783
B54: Average gross debt | I54: =AVERAGE(I51,I53) -> 14882.908 | J54: =AVERAGE(J51,J53) -> 15284.783 | K54: =AVERAGE(K51,K53) -> 15719.158 | L54: =AVERAGE(L51,L53) -> 15949.783 | M54: =AVERAGE(M51,M53) -> 16049.783 | N54: =AVERAGE(N51,N53) -> 16149.783 | O54: =AVERAGE(O51,O53) -> 16249.783 | P54: =AVERAGE(P51,P53) -> 16349.783 | ... R54: =AVERAGE(R51,R53) -> 16549.783
B55: Interest expense (schedule) | I55: =I54*I16 -> 1116.2181 | J55: =J54*J16 -> 1146.3587 | K55: =K54*K16 -> 1178.9368 | L55: =L54*L16 -> 1196.2337 | M55: =M54*M16 -> 1203.7337 | N55: =N54*N16 -> 1211.2337 | O55: =O54*O16 -> 1218.7337 | P55: =P54*P16 -> 1226.2337 | ... R55: =R54*R16 -> 1241.2337
B56: Cash & equivalents (held flat) | I56: =Inputs!$C$24 -> 674.218 | J56: =Inputs!$C$24 -> 674.218 | K56: =Inputs!$C$24 -> 674.218 | L56: =Inputs!$C$24 -> 674.218 | M56: =Inputs!$C$24 -> 674.218 | N56: =Inputs!$C$24 -> 674.218 | O56: =Inputs!$C$24 -> 674.218 | P56: =Inputs!$C$24 -> 674.218 | ... R56: =Inputs!$C$24 -> 674.218
B57: Net debt | I57: =I53-I56 -> 14356.815 | J57: =J53-J56 -> 14864.315 | K57: =K53-K56 -> 15225.565 | L57: =L53-L56 -> 15325.565 | M57: =M53-M56 -> 15425.565 | N57: =N53-N56 -> 15525.565 | O57: =O53-O56 -> 15625.565 | P57: =P53-P56 -> 15725.565 | ... R57: =R53-R56 -> 15925.565
B58: Net debt / EBITDA (x) | I58: =I57/I29 -> 5.1717244 | J58: =J57/J29 -> 4.9454829 | K58: =K57/K29 -> 4.7577817 | L58: =L57/L29 -> 4.5609813 | M58: =M57/M29 -> 4.3721352 | N58: =N57/N29 -> 4.190932 | O58: =O57/O29 -> 4.0170721 | P58: =P57/P29 -> 3.8502671 | ... R58: =R57/R29 -> 3.5367214
B59: EBITDA / interest (x) | I59: =I29/I34 -> 2.4869879 | J59: =J29/J34 -> 2.6218972 | K59: =K29/K34 -> 2.7144282 | L59: =L29/L34 -> 2.808938 | M59: =M29/M34 -> 2.9310085 | N59: =N29/N34 -> 3.0585025 | O59: =O29/O34 -> 3.1916648 | P59: =P29/P34 -> 3.3307508 | ... R59: =R29/R34 -> 3.6277757
B60: EBIT / interest (x) | I60: =I32/I34 -> 1.9673762 | J60: =J32/J34 -> 2.1079418 | K60: =K32/K34 -> 2.2034312 | L60: =L32/L34 -> 2.3002937 | M60: =M32/M34 -> 2.4204785 | N60: =N32/N34 -> 2.5460601 | O60: =O32/O34 -> 2.677283 | P60: =P32/P34 -> 2.8144028 | ... R60: =R32/R34 -> 3.1074145
B62: Capex, area and working capital
B63: Operating area – consolidated ('000 sq ft) | I63: =Rev_Build!$D$33 -> 28440 | J63: =Rev_Build!$D$50 -> 28890 | K63: =Rev_Build!$D$67 -> 29540 | L63: =K63 -> 29540 | M63: =L63 -> 29540 | N63: =M63 -> 29540 | O63: =N63 -> 29540 | P63: =O63 -> 29540 | Q63: =P63 -> 29540 | R63: =Q63 -> 29540
B64: Area added ('000 sq ft) | I64: =0 -> 0 | J64: =J63-I63 -> 450 | K64: =K63-J63 -> 650 | L64: =L63-K63 -> 0 | M64: =M63-L63 -> 0 | N64: =N63-M63 -> 0 | O64: =O63-N63 -> 0 | P64: =P63-O63 -> 0 | Q64: =Q63-P63 -> 0 | R64: =R63-Q63 -> 0
B65: Maintenance capex (Rs 2 psf/month, inflated) | I65: =I63*Inputs!$C$43*12/10000*(1+Inputs!$C$44)^(I5-1) -> 68.256 | J65: =J63*Inputs!$C$43*12/10000*(1+Inputs!$C$44)^(J5-1) -> 72.45612 | K65: =K63*Inputs!$C$43*12/10000*(1+Inputs!$C$44)^(K5-1) -> 77.420204 | L65: =L63*Inputs!$C$43*12/10000*(1+Inputs!$C$44)^(L5-1) -> 80.904114 | M65: =M63*Inputs!$C$43*12/10000*(1+Inputs!$C$44)^(M5-1) -> 84.544799 | N65: =N63*Inputs!$C$43*12/10000*(1+Inputs!$C$44)^(N5-1) -> 88.349315 | O65: =O63*Inputs!$C$43*12/10000*(1+Inputs!$C$44)^(O5-1) -> 92.325034 | P65: =P63*Inputs!$C$43*12/10000*(1+Inputs!$C$44)^(P5-1) -> 96.47966 | ... R65: =R63*Inputs!$C$43*12/10000*(1+Inputs!$C$44)^(R5-1) -> 105.3582
B66: Growth capex (committed area additions) | I66: =(I64+J64)/2*Inputs!$C$45/10000 -> 146.25 | J66: =(J64+K64)/2*Inputs!$C$45/10000 -> 357.5 | K66: =(K64+L64)/2*Inputs!$C$45/10000 -> 211.25 | L66: =(L64+M64)/2*Inputs!$C$45/10000 -> 0 | M66: =(M64+N64)/2*Inputs!$C$45/10000 -> 0 | N66: =(N64+O64)/2*Inputs!$C$45/10000 -> 0 | O66: =(O64+P64)/2*Inputs!$C$45/10000 -> 0 | P66: =(P64+Q64)/2*Inputs!$C$45/10000 -> 0 | Q66: =(Q64+R64)/2*Inputs!$C$45/10000 -> 0 | R66: =R64/2*Inputs!$C$45/10000 -> 0
B67: Refurbishment capex | I67: =I15 -> 150 | J67: =J15 -> 150 | K67: =K15 -> 150 | L67: =L15 -> 100 | M67: =M15 -> 100 | N67: =N15 -> 100 | O67: =O15 -> 100 | P67: =P15 -> 100 | ... R67: =R15 -> 100
B68: Total capex | I68: =SUM(I65:I67) -> 364.506 | J68: =SUM(J65:J67) -> 579.95612 | K68: =SUM(K65:K67) -> 438.6702 | L68: =SUM(L65:L67) -> 180.90411 | M68: =SUM(M65:M67) -> 184.5448 | N68: =SUM(N65:N67) -> 188.34931 | O68: =SUM(O65:O67) -> 192.32503 | P68: =SUM(P65:P67) -> 196.47966 | ... R68: =SUM(R65:R67) -> 205.3582
B69: Net working capital | H69: =H24*Inputs!$C$46 -> -148.11295 | I69: =I24*Inputs!$C$46 -> -196.83703 | J69: =J24*Inputs!$C$46 -> -207.18163 | K69: =K24*Inputs!$C$46 -> -217.60951 | L69: =L24*Inputs!$C$46 -> -228.48998 | M69: =M24*Inputs!$C$46 -> -239.91448 | N69: =N24*Inputs!$C$46 -> -251.9102 | O69: =O24*Inputs!$C$46 -> -264.50571 | ... R69: =R24*Inputs!$C$46 -> -306.19843
B70: Increase in NWC (cash outflow if positive) | I70: =I69-H69 -> -48.724076 | J70: =J69-I69 -> -10.344606 | K70: =K69-J69 -> -10.427874 | L70: =L69-K69 -> -10.880475 | M70: =M69-L69 -> -11.424499 | N70: =N69-M69 -> -11.995724 | O70: =O69-N69 -> -12.59551 | P70: =P69-O69 -> -13.225286 | ... R70: =R69-Q69 -> -14.580877
B72: NDCF and distribution per unit (REIT-level, equity view)
B73: EBITDA | I73: =I29 -> 2776.0209 | J73: =J29 -> 3005.6346 | K73: =K29 -> 3200.1394 | L73: =L29 -> 3360.1464 | M73: =M29 -> 3528.1537 | N73: =N29 -> 3704.5614 | O73: =O29 -> 3889.7894 | P73: =P29 -> 4084.2789 | ... R73: =R29 -> 4502.9175
B74: + Other income | I74: =I33 -> 142.52956 | J74: =J33 -> 146.34159 | K74: =K33 -> 153.54341 | L74: =L33 -> 159.94299 | M74: =M33 -> 167.94014 | N74: =N33 -> 176.33714 | O74: =O33 -> 185.154 | P74: =P33 -> 194.4117 | ... R74: =R33 -> 214.3389
B75: − Interest | I75: =I34 -> 1116.2181 | J75: =J34 -> 1146.3587 | K75: =K34 -> 1178.9368 | L75: =L34 -> 1196.2337 | M75: =M34 -> 1203.7337 | N75: =N34 -> 1211.2337 | O75: =O34 -> 1218.7337 | P75: =P34 -> 1226.2337 | ... R75: =R34 -> 1241.2337
B76: − Cash tax (P&L tax x cash ratio) | I76: =I36*I14 -> 88.007928 | J76: =J36*J14 -> 141.64403 | K76: =K36*K14 -> 204.40066 | L76: =L36*L14 -> 259.05943 | M76: =M36*M14 -> 330.85276 | N76: =N36*N14 -> 412.58207 | O76: =O36*O14 -> 505.0068 | P76: =P36*P14 -> 608.93619 | ... R76: =R36*R14 -> 712.34442
B77: − Maintenance capex | I77: =I65 -> 68.256 | J77: =J65 -> 72.45612 | K77: =K65 -> 77.420204 | L77: =L65 -> 80.904114 | M77: =M65 -> 84.544799 | N77: =N65 -> 88.349315 | O77: =O65 -> 92.325034 | P77: =P65 -> 96.47966 | ... R77: =R65 -> 105.3582
B78: Consolidated NDCF (100%, pre-calibration) | I78: =I73+I74-I75-I76-I77 -> 1646.0684 | J78: =J73+J74-J75-J76-J77 -> 1791.5174 | K78: =K73+K74-K75-K76-K77 -> 1892.9251 | L78: =L73+L74-L75-L76-L77 -> 1983.8921 | M78: =M73+M74-M75-M76-M77 -> 2076.9626 | N78: =N73+N74-N75-N76-N77 -> 2168.7334 | O78: =O73+O74-O75-O76-O77 -> 2258.8779 | P78: =P73+P74-P75-P76-P77 -> 2347.0411 | ... R78: =R73+R74-R75-R76-R77 -> 2658.3201
B79: Unitholders' share (1 − partners' share) | I79: =I78*(1-Inputs!$C$56) -> 1399.1581 | J79: =J78*(1-Inputs!$C$56) -> 1522.7898 | K79: =K78*(1-Inputs!$C$56) -> 1608.9863 | L79: =L78*(1-Inputs!$C$56) -> 1686.3083 | M79: =M78*(1-Inputs!$C$56) -> 1765.4182 | N79: =N78*(1-Inputs!$C$56) -> 1843.4234 | O79: =O78*(1-Inputs!$C$56) -> 1920.0462 | P79: =P78*(1-Inputs!$C$56) -> 1994.9849 | ... R79: =R78*(1-Inputs!$C$56) -> 2259.5721
B80: NCP NOI (100%) | I80: =Rev_Build!$Z$34*Inputs!$C$49 -> 644.355 | J80: =Rev_Build!$Z$51*Inputs!$C$49 -> 667.64948 | K80: =Rev_Build!$Z$68*Inputs!$C$49 -> 708.19824 | L80: =K80*(1+L7) -> 743.60815 | M80: =L80*(1+M7) -> 780.78856 | N80: =M80*(1+N7) -> 819.82799 | O80: =N80*(1+O7) -> 860.81939 | P80: =O80*(1+P7) -> 903.86036 | Q80: =P80*(1+Q7) -> 949.05338 | R80: =Q80*(1+R7) -> 996.50605
B81: NCP NDCF (100%) = 95% NOI − interest on NCP debt | I81: =I80*0.95-Inputs!$C$35*I16 -> 357.13725 | J81: =J80*0.95-Inputs!$C$35*J16 -> 379.26701 | K81: =K80*0.95-Inputs!$C$35*K16 -> 417.78833 | L81: =L80*0.95-Inputs!$C$35*L16 -> 451.42775 | M81: =M80*0.95-Inputs!$C$35*M16 -> 486.74913 | N81: =N80*0.95-Inputs!$C$35*N16 -> 523.83659 | O81: =O80*0.95-Inputs!$C$35*O16 -> 562.77842 | P81: =P80*0.95-Inputs!$C$35*P16 -> 603.66734 | ... R81: =R80*0.95-Inputs!$C$35*R16 -> 691.68074
B82: + Distribution from NCP (REIT share) | I82: =I81*Inputs!$C$36 -> 178.56863 | J82: =J81*Inputs!$C$36 -> 189.6335 | K82: =K81*Inputs!$C$36 -> 208.89417 | L82: =L81*Inputs!$C$36 -> 225.71387 | M82: =M81*Inputs!$C$36 -> 243.37457 | N82: =N81*Inputs!$C$36 -> 261.9183 | O82: =O81*Inputs!$C$36 -> 281.38921 | P82: =P81*Inputs!$C$36 -> 301.83367 | ... R82: =R81*Inputs!$C$36 -> 345.84037
B83: + Distribution from BKC JV | I83: =0.5*Inputs!$C$58*Inputs!$C$32 -> 30.175 | J83: =Inputs!$C$58*Inputs!$C$32 -> 60.35 | K83: =J83*(1+Inputs!$C$59) -> 62.764 | L83: =K83*(1+Inputs!$C$59) -> 65.27456 | M83: =L83*(1+Inputs!$C$59) -> 67.885542 | N83: =M83*(1+Inputs!$C$59) -> 70.600964 | O83: =N83*(1+Inputs!$C$59) -> 73.425003 | P83: =O83*(1+Inputs!$C$59) -> 76.362003 | Q83: =P83*(1+Inputs!$C$59) -> 79.416483 | R83: =Q83*(1+Inputs!$C$59) -> 82.593142
B84: + Calibration to Q1 FY27 run-rate DPU (constant) | I84: =Inputs!$C$55*Inputs!$C$11-(I79+I82+I83) -> 267.62899 | J84: =I84 -> 267.62899 | K84: =J84 -> 267.62899 | L84: =K84 -> 267.62899 | M84: =L84 -> 267.62899 | N84: =M84 -> 267.62899 | O84: =N84 -> 267.62899 | P84: =O84 -> 267.62899 | Q84: =P84 -> 267.62899 | R84: =Q84 -> 267.62899 | T84: Reconciles the P&L-based build to the observed Q1 FY27 run-rate (non-cash interest, actual cash taxes and JV timing are not visible in the P&L).
B85: NDCF to unitholders | I85: =I79+I82+I83+I84 -> 1875.5308 | J85: =J79+J82+J83+J84 -> 2040.4023 | K85: =K79+K82+K83+K84 -> 2148.2735 | L85: =L79+L82+L83+L84 -> 2244.9257 | M85: =M79+M82+M83+M84 -> 2344.3073 | N85: =N79+N82+N83+N84 -> 2443.5717 | O85: =O79+O82+O83+O84 -> 2542.4894 | P85: =P79+P82+P83+P84 -> 2640.8096 | ... R85: =R79+R82+R83+R84 -> 2955.6346
B86: Distribution per unit (Rs) | I86: =I85*Inputs!$C$57/Inputs!$C$11 -> 22.6 | J86: =J85*Inputs!$C$57/Inputs!$C$11 -> 24.586689 | K86: =K85*Inputs!$C$57/Inputs!$C$11 -> 25.886529 | L86: =L85*Inputs!$C$57/Inputs!$C$11 -> 27.051181 | M86: =M85*Inputs!$C$57/Inputs!$C$11 -> 28.248721 | N86: =N85*Inputs!$C$57/Inputs!$C$11 -> 29.444849 | O86: =O85*Inputs!$C$57/Inputs!$C$11 -> 30.6368 | P86: =P85*Inputs!$C$57/Inputs!$C$11 -> 31.82155 | ... R86: =R85*Inputs!$C$57/Inputs!$C$11 -> 35.615167 | T86: Management guides ~15% embedded DPU growth over ~2 years; compare FY29E vs FY27E.
B87: DPU growth % | I87: =I86/Inputs!$C$18-1 -> 0.056074766 | J87: =J86/I86-1 -> 0.087906582 | K87: =K86/J86-1 -> 0.052867634 | L87: =L86/K86-1 -> 0.044990648 | M87: =M86/L86-1 -> 0.04426942 | N87: =N86/M86-1 -> 0.042342737 | O87: =O86/N86-1 -> 0.040480807 | P87: =P86/O86-1 -> 0.038670818 | Q87: =Q86/P86-1 -> 0.058122008 | R87: =R86/Q86-1 -> 0.057737511

Sheet WACC
B1: COST OF CAPITAL – Damodaran INR approach
B2: Risk-free rate net of sovereign default spread · ERP = mature market + country risk premium · bottom-up beta · synthetic-rating cross-check
B4: A. Cost of equity
B5: India 10-year G-sec yield | C5: 0.0723 | F5: ICR ≥ | G5: Rating | H5: Spread | I5: Trading Economics, 7-Oct-2026 (two-year high after RBI repo hike to 5.50%)
B6: India sovereign default spread (Moody's Baa3) | C6: 0.0187 | F6: -99 | G6: Ca/CC | H6: 0.13 | I6: Damodaran country risk table, 5-Jan-2026
B7: Deduct default spread from G-sec? (1 = yes, Damodaran) | C7: 1 | F7: 0.8 | G7: Caa/CCC | H7: 0.08 | I7: Damodaran: INR risk-free rate = government bond yield − default spread
B8: INR risk-free rate | C8: =C5-C6*C7 -> 0.0536 | F8: 1.25 | G8: B3/B- | H8: 0.051
B9: Mature-market equity risk premium | C9: 0.0423 | F9: 1.5 | G9: B2/B | H9: 0.042 | I9: Damodaran implied ERP, Jan-2026
B10: India country risk premium | C10: 0.0285 | F10: 1.75 | G10: B1/B+ | H10: 0.035 | I10: Damodaran, Jan-2026 (default spread x relative equity volatility)
B11: Total equity risk premium – India | C11: =C9+C10 -> 0.0708 | F11: 2 | G11: Ba2/BB | H11: 0.024 | I11: Matches Damodaran's published India ERP 7.08%
F12: 2.25 | G12: Ba1/BB+ | H12: 0.02
B13: Bottom-up beta (Damodaran global industry betas) | C13: Unlevered β | D13: Weight | F13: 2.5 | G13: Baa2/BBB | H13: 0.0156
B14: R.E.I.T. (cash-corrected) | C14: 0.36 | D14: 0.5 | F14: 3 | G14: A3/A- | H14: 0.0121 | I14: Damodaran betas page (header: data as of Jan-2026); REIT 0.35 uncorrected. Weights: judgement (REIT-heavy, plus operating/development risk)
B15: Real Estate (Operations & Services), cash-corrected | C15: 0.51 | D15: 0.25 | F15: 4.25 | G15: A2/A | H15: 0.0107
B16: Real Estate (General/Diversified), cash-corrected | C16: 0.6 | D16: 0.25 | F16: 5.5 | G16: A1/A+ | H16: 0.0092
B17: Weighted unlevered beta | C17: =SUMPRODUCT(C14:C16,D14:D16) -> 0.4575 | F17: 6.5 | G17: Aa2/AA | H17: 0.007
B18: Target debt / (debt + equity) | C18: 0.33 | F18: 8.5 | G18: Aaa/AAA | H18: 0.0059 | I18: Management target: one-third debt / two-thirds equity for acquisitions; LTV cap 35%
B19: Implied target D/E | C19: =C18/(1-C18) -> 0.49253731 | F19: Approximate Damodaran large-firm table – refresh from ratings.xls before external use
B20: Marginal tax rate (re-levering) | C20: =Inputs!$C$42 -> 0.2517
B21: Re-levered equity beta | C21: =C17*(1+(1-C20)*C19) -> 0.62611879 | I21: Hamada: βL = βU x (1 + (1 − t) x D/E)
B22: Cost of equity (1): Damodaran (INR Rf + β x ERP) | C22: =C8+C21*C11 -> 0.097929211
B23: Cost of equity (2): G-sec + β x ERP (common practitioner) | C23: =C5+C21*C11 -> 0.11662921 | I23: Includes default spread in Rf – conservative upper bound
B24: Cost of equity (3): market-implied (DPU yield + growth) | C24: =Inputs!$C$17/Inputs!$C$10+0.04 -> 0.10812652 | I24: Annualised Q1 DPU / price + 4% stable growth – cross-check only
B25: Method selected (1, 2 or 3 = average of 1 and 2) | C25: 3 | I25: Average used: conflicts between Damodaran's and practitioner Rf conventions
B26: SELECTED COST OF EQUITY | C26: =CHOOSE(C25,C22,C23,AVERAGE(C22,C23)) -> 0.10727921
B28: B. Cost of debt
B29: Reported average interest rate (Q1 FY27) | C29: 0.073 | I29: Q1 FY27 earnings: 7.3%, ~90% floating, dual AAA (CRISIL/ICRA)
B30: Selected pre-tax cost of debt (marginal) | C30: 0.075 | I30: Peers' Q1 FY27 raises: Embassy 7.46%, Mindspace 7.42%, KRT 7.2%
B31: Implied spread over G-sec | C31: =C30-C5 -> 0.0027 | I31: AAA REIT paper trades close to G-sec given dual-AAA and lease-backed cash flows
B32: After-tax cost of debt | C32: =C30*(1-C20) -> 0.0561225
B33: Interest coverage FY27E (EBIT / interest) | C33: =Fin_Proj!I60 -> 1.9673762
B34: Synthetic rating (Damodaran-style lookup) | C34: =LOOKUP(C33,F6:F18,G6:G18) -> B1/B+ | I34: Cross-check only: REIT long-dated lease cash flows justify better than interest-cover-implied rating
B35: Synthetic spread | C35: =LOOKUP(C33,F6:F18,H6:H18) -> 0.035
B36: Synthetic cost of debt (G-sec + spread) | C36: =C5+C35 -> 0.1073
B38: C. Weighted average cost of capital
B39: Market capitalisation | C39: =Inputs!$C$12 -> 27286.483
B40: Pro-forma net debt | C40: =Inputs!$C$34 -> 14060.565
B41: Current market D / (D + E) | C41: =C40/(C39+C40) -> 0.34006212 | I41: Consolidated basis, ignores minorities
B42: Target D / (D + E) applied | C42: =C18 -> 0.33
B43: Equity weight | C43: =1-C42 -> 0.67
B44: WACC | C44: =C43*C26+C42*C32 -> 0.090397496 | I44: WACC = E/V x CoE + D/V x Kd x (1 − t)
B45: WACC at current market weights | C45: =(1-C41)*C26+C41*C32 -> 0.089882751 | I45: Cross-check

Sheet DCF_FCFF
B1: FCFF DISCOUNTED CASH FLOW – enterprise value → value per unit
B2: Mid-period discounting with stub period · Gordon-growth terminal value on normalised FCFF · bridge adjusts for net debt, partners' share and the NCP JV
B3: 1. Free cash flow to firm
B4: Rs crore | C4: Unit | I4: FY27E | J4: FY28E | K4: FY29E | L4: FY30E | M4: FY31E | N4: FY32E | O4: FY33E | P4: FY34E | Q4: FY35E | R4: FY36E
B5: Year index | I5: =Fin_Proj!I5 -> 1 | J5: =Fin_Proj!J5 -> 2 | K5: =Fin_Proj!K5 -> 3 | L5: =Fin_Proj!L5 -> 4 | M5: =Fin_Proj!M5 -> 5 | N5: =Fin_Proj!N5 -> 6 | O5: =Fin_Proj!O5 -> 7 | P5: =Fin_Proj!P5 -> 8 | ... R5: =Fin_Proj!R5 -> 10
B6: EBITDA | I6: =Fin_Proj!I29 -> 2776.0209 | J6: =Fin_Proj!J29 -> 3005.6346 | K6: =Fin_Proj!K29 -> 3200.1394 | L6: =Fin_Proj!L29 -> 3360.1464 | M6: =Fin_Proj!M29 -> 3528.1537 | N6: =Fin_Proj!N29 -> 3704.5614 | O6: =Fin_Proj!O29 -> 3889.7894 | P6: =Fin_Proj!P29 -> 4084.2789 | ... R6: =Fin_Proj!R29 -> 4502.9175
B7: Depreciation & amortisation | I7: =Fin_Proj!I31 -> 580 | J7: =Fin_Proj!J31 -> 589.17722 | K7: =Fin_Proj!K31 -> 602.43319 | L7: =Fin_Proj!L31 -> 608.45752 | M7: =Fin_Proj!M31 -> 614.5421 | N7: =Fin_Proj!N31 -> 620.68752 | O7: =Fin_Proj!O31 -> 626.8944 | P7: =Fin_Proj!P31 -> 633.16334 | ... R7: =Fin_Proj!R31 -> 645.88992
B8: EBIT | I8: =I6-I7 -> 2196.0209 | J8: =J6-J7 -> 2416.4574 | K8: =K6-K7 -> 2597.7062 | L8: =L6-L7 -> 2751.6889 | M8: =M6-M7 -> 2913.6116 | N8: =N6-N7 -> 3083.8739 | O8: =O6-O7 -> 3262.8951 | P8: =P6-P7 -> 3451.1156 | ... R8: =R6-R7 -> 3857.0276
B9: Tax rate on EBIT (P&L effective rate) | I9: =Fin_Proj!I13 -> 0.24 | J9: =Fin_Proj!J13 -> 0.25 | K9: =Fin_Proj!K13 -> 0.26 | L9: =Fin_Proj!L13 -> 0.2517 | M9: =Fin_Proj!M13 -> 0.2517 | N9: =Fin_Proj!N13 -> 0.2517 | O9: =Fin_Proj!O13 -> 0.2517 | P9: =Fin_Proj!P13 -> 0.2517 | ... R9: =Fin_Proj!R13 -> 0.2517
B10: Tax on EBIT | I10: =I8*I9 -> 527.04501 | J10: =J8*J9 -> 604.11436 | K10: =K8*K9 -> 675.40362 | L10: =L8*L9 -> 692.60008 | M10: =M8*M9 -> 733.35604 | N10: =N8*N9 -> 776.21105 | O10: =O8*O9 -> 821.27068 | P10: =P8*P9 -> 868.64579 | ... R10: =R8*R9 -> 970.81384
B11: NOPAT | I11: =I8-I10 -> 1668.9759 | J11: =J8-J10 -> 1812.3431 | K11: =K8-K10 -> 1922.3026 | L11: =L8-L10 -> 2059.0888 | M11: =M8-M10 -> 2180.2556 | N11: =N8-N10 -> 2307.6628 | O11: =O8-O10 -> 2441.6244 | P11: =P8-P10 -> 2582.4698 | ... R11: =R8-R10 -> 2886.2137
B12: + Depreciation & amortisation | I12: =I7 -> 580 | J12: =J7 -> 589.17722 | K12: =K7 -> 602.43319 | L12: =L7 -> 608.45752 | M12: =M7 -> 614.5421 | N12: =N7 -> 620.68752 | O12: =O7 -> 626.8944 | P12: =P7 -> 633.16334 | ... R12: =R7 -> 645.88992
B13: − Maintenance capex | I13: =-Fin_Proj!I65 -> -68.256 | J13: =-Fin_Proj!J65 -> -72.45612 | K13: =-Fin_Proj!K65 -> -77.420204 | L13: =-Fin_Proj!L65 -> -80.904114 | M13: =-Fin_Proj!M65 -> -84.544799 | N13: =-Fin_Proj!N65 -> -88.349315 | O13: =-Fin_Proj!O65 -> -92.325034 | P13: =-Fin_Proj!P65 -> -96.47966 | ... R13: =-Fin_Proj!R65 -> -105.3582
B14: − Growth capex (committed additions) | I14: =-Fin_Proj!I66 -> -146.25 | J14: =-Fin_Proj!J66 -> -357.5 | K14: =-Fin_Proj!K66 -> -211.25 | L14: =-Fin_Proj!L66 -> 0 | M14: =-Fin_Proj!M66 -> 0 | N14: =-Fin_Proj!N66 -> 0 | O14: =-Fin_Proj!O66 -> 0 | P14: =-Fin_Proj!P66 -> 0 | ... R14: =-Fin_Proj!R66 -> 0
B15: − Refurbishment capex | I15: =-Fin_Proj!I67 -> -150 | J15: =-Fin_Proj!J67 -> -150 | K15: =-Fin_Proj!K67 -> -150 | L15: =-Fin_Proj!L67 -> -100 | M15: =-Fin_Proj!M67 -> -100 | N15: =-Fin_Proj!N67 -> -100 | O15: =-Fin_Proj!O67 -> -100 | P15: =-Fin_Proj!P67 -> -100 | ... R15: =-Fin_Proj!R67 -> -100
B16: − Increase in net working capital | I16: =-Fin_Proj!I70 -> 48.724076 | J16: =-Fin_Proj!J70 -> 10.344606 | K16: =-Fin_Proj!K70 -> 10.427874 | L16: =-Fin_Proj!L70 -> 10.880475 | M16: =-Fin_Proj!M70 -> 11.424499 | N16: =-Fin_Proj!N70 -> 11.995724 | O16: =-Fin_Proj!O70 -> 12.59551 | P16: =-Fin_Proj!P70 -> 13.225286 | ... R16: =-Fin_Proj!R70 -> 14.580877
B17: Free cash flow to firm (FCFF) | I17: =SUM(I11:I16) -> 1933.1939 | J17: =SUM(J11:J16) -> 1831.9088 | K17: =SUM(K11:K16) -> 2096.4935 | L17: =SUM(L11:L16) -> 2497.5227 | M17: =SUM(M11:M16) -> 2621.6774 | N17: =SUM(N11:N16) -> 2751.9967 | O17: =SUM(O11:O16) -> 2888.7892 | P17: =SUM(P11:P16) -> 3032.3788 | ... R17: =SUM(R11:R16) -> 3341.3263
B18: Fraction of year after valuation date | I18: =IF(I5=1,Inputs!$C$9,1) -> 0.47123288 | J18: =IF(J5=1,Inputs!$C$9,1) -> 1 | K18: =IF(K5=1,Inputs!$C$9,1) -> 1 | L18: =IF(L5=1,Inputs!$C$9,1) -> 1 | M18: =IF(M5=1,Inputs!$C$9,1) -> 1 | N18: =IF(N5=1,Inputs!$C$9,1) -> 1 | O18: =IF(O5=1,Inputs!$C$9,1) -> 1 | P18: =IF(P5=1,Inputs!$C$9,1) -> 1 | ... R18: =IF(R5=1,Inputs!$C$9,1) -> 1
B19: FCFF counted in valuation | I19: =I17*I18 -> 910.98454 | J19: =J17*J18 -> 1831.9088 | K19: =K17*K18 -> 2096.4935 | L19: =L17*L18 -> 2497.5227 | M19: =M17*M18 -> 2621.6774 | N19: =N17*N18 -> 2751.9967 | O19: =O17*O18 -> 2888.7892 | P19: =P17*P18 -> 3032.3788 | ... R19: =R17*R18 -> 3341.3263
B20: Discount period (years, mid-period) | I20: =IF(I5=1,Inputs!$C$9/2,Inputs!$C$9+I5-1.5) -> 0.23561644 | J20: =IF(J5=1,Inputs!$C$9/2,Inputs!$C$9+J5-1.5) -> 0.97123288 | K20: =IF(K5=1,Inputs!$C$9/2,Inputs!$C$9+K5-1.5) -> 1.9712329 | L20: =IF(L5=1,Inputs!$C$9/2,Inputs!$C$9+L5-1.5) -> 2.9712329 | M20: =IF(M5=1,Inputs!$C$9/2,Inputs!$C$9+M5-1.5) -> 3.9712329 | N20: =IF(N5=1,Inputs!$C$9/2,Inputs!$C$9+N5-1.5) -> 4.9712329 | O20: =IF(O5=1,Inputs!$C$9/2,Inputs!$C$9+O5-1.5) -> 5.9712329 | P20: =IF(P5=1,Inputs!$C$9/2,Inputs!$C$9+P5-1.5) -> 6.9712329 | ... R20: =IF(R5=1,Inputs!$C$9/2,Inputs!$C$9+R5-1.5) -> 8.9712329
B21: Discount factor at WACC | I21: =1/(1+$C$25)^I20 -> 0.9798157 | J21: =1/(1+$C$25)^J20 -> 0.91938277 | K21: =1/(1+$C$25)^K20 -> 0.84316295 | L21: =1/(1+$C$25)^L20 -> 0.773262 | M21: =1/(1+$C$25)^M20 -> 0.70915607 | N21: =1/(1+$C$25)^N20 -> 0.65036473 | O21: =1/(1+$C$25)^O20 -> 0.59644738 | P21: =1/(1+$C$25)^P20 -> 0.54699995 | ... R21: =1/(1+$C$25)^R20 -> 0.46006331
B22: Present value of FCFF | I22: =I19*I21 -> 892.59695 | J22: =J19*J21 -> 1684.2254 | K22: =K19*K21 -> 1767.6856 | L22: =L19*L21 -> 1931.2394 | M22: =M19*M21 -> 1859.1784 | N22: =N19*N21 -> 1789.8016 | O22: =O19*O21 -> 1723.0108 | P22: =P19*P21 -> 1658.711 | ... R22: =R19*R21 -> 1537.2217
B24: 2. Terminal value and enterprise value
B25: WACC | C25: =WACC!$C$44 -> 0.090397496
B26: Terminal (stable) growth rate | C26: 0.04 | D26: ≈ RBI CPI target; below INR risk-free rate (Damodaran cap) – ASSUMPTION
B27: Terminal capex as % of EBITDA (normalised reinvestment) | C27: 0.08 | D27: Maintenance + leasing costs + refurbishment; D&A set equal to capex in perpetuity – ASSUMPTION
B28: Terminal tax rate | C28: =Inputs!$C$42 -> 0.2517
B29: Exit cap rate on forward NOI (cross-check) | C29: 0.075 | D29: Brookfield BKC deal: 7.4% on FY28E NOI, 8.1% on FY30E; valuers use 7.5–8.0% terminal
B30: TV method (1 = Gordon growth, 2 = exit cap, 3 = average) | C30: 1 | D30: Sensitivity tables are on Gordon-growth basis
B32: EBITDA in year N+1 | C32: =R6*(1+C26) -> 4683.0342
B33: Normalised capex in year N+1 | C33: =C27*C32 -> 374.64274
B34: Normalised FCFF in year N+1 | C34: =(C32-C33)*(1-C28) -> 3223.9693
B35: Terminal value – Gordon growth | C35: =C34/(C25-C26) -> 63970.824
B36: Terminal value – exit cap rate | C36: =C32/C29 -> 62440.456
B37: Implied exit cap rate of Gordon TV | C37: =C32/C35 -> 0.073205783 | D37: Compare with 7.5–8.0% valuer range
B38: Implied TV / EBITDA (x) | C38: =C35/C32 -> 13.660123
B39: Terminal value used | C39: =CHOOSE(C30,C35,C36,AVERAGE(C35,C36)) -> 63970.824
B40: Discount factor for TV (end of FY36) | C40: =1/(1+C25)^(Inputs!$C$9+9) -> 0.4405804
B41: PV of terminal value | C41: =C39*C40 -> 28184.291
B42: PV of explicit FCFF (FY27E stub – FY36E) | C42: =SUM(I22:R22) -> 16440.482
B43: ENTERPRISE VALUE (100% of consolidated operations) | C43: =C41+C42 -> 44624.773
B44: Terminal value as % of EV | C44: =C41/C43 -> 0.63158397
B46: 3. Bridge: enterprise value → value per unit (BAV: non-operating assets, minorities, associates)
B47: Enterprise value | C47: =C43 -> 44624.773
B48: − Pro-forma net debt | C48: =Inputs!$C$34 -> 14060.565 | D48: Inputs: Mar-26 borrowings, QIP, 360 ONE, BKC funding
B49: Equity value, 100% basis | C49: =C47-C48 -> 30564.208
B50: Partners' share of consolidated value (%) | C50: =Rev_Build!$D$75 -> 0.20341657 | D50: Rev_Build: revenue-weighted (1 − own%)
B51: − Partners' (minority) share at fair value | C51: =C49*C50 -> 6217.2663
B52: NCP NOI FY28E (100%) | C52: =Rev_Build!$Z$51*Inputs!$C$49 -> 667.64948
B53: NCP capitalisation rate | C53: 0.0775 | D53: ASSUMPTION – mature Delhi-NCR assets; between KRT/Embassy and G1/G2
B54: NCP enterprise value (100%) | C54: =C52/C53 -> 8614.832
B55: − NCP debt (100%) | C55: =Inputs!$C$35 -> 3400
B56: NCP equity (100%) | C56: =C54-C55 -> 5214.832
B57: + REIT share of NCP, after illiquidity discount | C57: =C56*Inputs!$C$36*(1-Inputs!$C$37) -> 2346.6744
B58: + BKC JV stake at cost | C58: =Inputs!$C$32 -> 850 | D58: Debt-funded: neutral to the bridge
B59: EQUITY VALUE TO UNITHOLDERS | C59: =C49-C51+C57+C58 -> 27543.616
B60: Units outstanding (crore) | C60: =Inputs!$C$11 -> 82.988087
B61: DCF VALUE PER UNIT (Rs) | C61: =C59/C60 -> 331.89843
B62: Upside / (downside) vs current price | C62: =C61/Inputs!$C$10-1 -> 0.0094234631
B64: 4. Implied multiples and value of growth (BAV Ch. 9–11)
B65: EV / EBITDA FY27E (x) | C65: =C43/I6 -> 16.075086
B66: EV / NOI FY28E (x) | C66: =C43/(Rev_Build!$Z$52*Inputs!$C$50) -> 13.896105
B67: Implied cap rate on FY28E NOI | C67: =Rev_Build!$Z$52*Inputs!$C$50/C43 -> 0.071962614
B68: Steady-state (no-growth) EV = FY27E NOPAT / WACC | C68: =I11/C25 -> 18462.634 | D68: No real growth, constant earnings
B69: Value of growth = EV − steady-state value | C69: =C43-C68 -> 26162.139
B70: Value of growth as % of EV | C70: =C69/C43 -> 0.58626941
B71: Average reinvestment rate FY27E–FY29E | C71: =(-SUM(I13:K16)-SUM(I12:K12))/SUM(I11:K11) -> -0.084753278 | D71: (capex − D&A + ΔNWC) / NOPAT; negative = D&A exceeds reinvestment
B72: Terminal growth sanity: g vs INR risk-free rate | C72: =C26-WACC!$C$8 -> -0.0136 | D72: Must be ≤ 0 (growth cannot exceed risk-free rate)
B74: 5. Sensitivity – value per unit (Rs): WACC (down) × terminal growth (across); Gordon-growth basis
B75: WACC ↓ / g → | C75: =$C$26+(-0.01) -> 0.03 | D75: =$C$26+(-0.005) -> 0.035 | E75: =$C$26+(0) -> 0.04 | F75: =$C$26+(0.005) -> 0.045 | G75: =$C$26+(0.01) -> 0.05
B76: =$C$25+(-0.01) -> 0.080397496 | C76: =(((SUMPRODUCT($I$19:$R$19*(1+$B76)^(-$I$20:$R$20))+($R$6*(1+C$75)*(1-$C$27)*(1-$C$28)/($B76-C$75))*(1+$B76)^(-(Inputs!$C$9+9)))-$C$48)*(1-$C$50)+$C$57+$C$58)/$C$60 -> 360.61827 | D76: =(((SUMPRODUCT($I$19:$R$19*(1+$B76)^(-$I$20:$R$20))+($R$6*(1+D$75)*(1-$C$27)*(1-$C$28)/($B76-D$75))*(1+$B76)^(-(Inputs!$C$9+9)))-$C$48)*(1-$C$50)+$C$57+$C$58)/$C$60 -> 394.39425 | E76: =(((SUMPRODUCT($I$19:$R$19*(1+$B76)^(-$I$20:$R$20))+($R$6*(1+E$75)*(1-$C$27)*(1-$C$28)/($B76-E$75))*(1+$B76)^(-(Inputs!$C$9+9)))-$C$48)*(1-$C$50)+$C$57+$C$58)/$C$60 -> 436.53114 | F76: =(((SUMPRODUCT($I$19:$R$19*(1+$B76)^(-$I$20:$R$20))+($R$6*(1+F$75)*(1-$C$27)*(1-$C$28)/($B76-F$75))*(1+$B76)^(-(Inputs!$C$9+9)))-$C$48)*(1-$C$50)+$C$57+$C$58)/$C$60 -> 490.57195 | G76: =(((SUMPRODUCT($I$19:$R$19*(1+$B76)^(-$I$20:$R$20))+($R$6*(1+G$75)*(1-$C$27)*(1-$C$28)/($B76-G$75))*(1+$B76)^(-(Inputs!$C$9+9)))-$C$48)*(1-$C$50)+$C$57+$C$58)/$C$60 -> 562.39081
B77: =$C$25+(-0.005) -> 0.085397496 | C77: =(((SUMPRODUCT($I$19:$R$19*(1+$B77)^(-$I$20:$R$20))+($R$6*(1+C$75)*(1-$C$27)*(1-$C$28)/($B77-C$75))*(1+$B77)^(-(Inputs!$C$9+9)))-$C$48)*(1-$C$50)+$C$57+$C$58)/$C$60 -> 319.34744 | D77: =(((SUMPRODUCT($I$19:$R$19*(1+$B77)^(-$I$20:$R$20))+($R$6*(1+D$75)*(1-$C$27)*(1-$C$28)/($B77-D$75))*(1+$B77)^(-(Inputs!$C$9+9)))-$C$48)*(1-$C$50)+$C$57+$C$58)/$C$60 -> 345.96467 | E77: =(((SUMPRODUCT($I$19:$R$19*(1+$B77)^(-$I$20:$R$20))+($R$6*(1+E$75)*(1-$C$27)*(1-$C$28)/($B77-E$75))*(1+$B77)^(-(Inputs!$C$9+9)))-$C$48)*(1-$C$50)+$C$57+$C$58)/$C$60 -> 378.44505 | F77: =(((SUMPRODUCT($I$19:$R$19*(1+$B77)^(-$I$20:$R$20))+($R$6*(1+F$75)*(1-$C$27)*(1-$C$28)/($B77-F$75))*(1+$B77)^(-(Inputs!$C$9+9)))-$C$48)*(1-$C$50)+$C$57+$C$58)/$C$60 -> 418.96562 | G77: =(((SUMPRODUCT($I$19:$R$19*(1+$B77)^(-$I$20:$R$20))+($R$6*(1+G$75)*(1-$C$27)*(1-$C$28)/($B77-G$75))*(1+$B77)^(-(Inputs!$C$9+9)))-$C$48)*(1-$C$50)+$C$57+$C$58)/$C$60 -> 470.9335
B78: =$C$25+(0) -> 0.090397496 | C78: =(((SUMPRODUCT($I$19:$R$19*(1+$B78)^(-$I$20:$R$20))+($R$6*(1+C$75)*(1-$C$27)*(1-$C$28)/($B78-C$75))*(1+$B78)^(-(Inputs!$C$9+9)))-$C$48)*(1-$C$50)+$C$57+$C$58)/$C$60 -> 284.9355 | D78: =(((SUMPRODUCT($I$19:$R$19*(1+$B78)^(-$I$20:$R$20))+($R$6*(1+D$75)*(1-$C$27)*(1-$C$28)/($B78-D$75))*(1+$B78)^(-(Inputs!$C$9+9)))-$C$48)*(1-$C$50)+$C$57+$C$58)/$C$60 -> 306.29761 | E78: =(((SUMPRODUCT($I$19:$R$19*(1+$B78)^(-$I$20:$R$20))+($R$6*(1+E$75)*(1-$C$27)*(1-$C$28)/($B78-E$75))*(1+$B78)^(-(Inputs!$C$9+9)))-$C$48)*(1-$C$50)+$C$57+$C$58)/$C$60 -> 331.89843 | F78: =(((SUMPRODUCT($I$19:$R$19*(1+$B78)^(-$I$20:$R$20))+($R$6*(1+F$75)*(1-$C$27)*(1-$C$28)/($B78-F$75))*(1+$B78)^(-(Inputs!$C$9+9)))-$C$48)*(1-$C$50)+$C$57+$C$58)/$C$60 -> 363.13852 | G78: =(((SUMPRODUCT($I$19:$R$19*(1+$B78)^(-$I$20:$R$20))+($R$6*(1+G$75)*(1-$C$27)*(1-$C$28)/($B78-G$75))*(1+$B78)^(-(Inputs!$C$9+9)))-$C$48)*(1-$C$50)+$C$57+$C$58)/$C$60 -> 402.11178
B79: =$C$25+(0.005) -> 0.095397496 | C79: =(((SUMPRODUCT($I$19:$R$19*(1+$B79)^(-$I$20:$R$20))+($R$6*(1+C$75)*(1-$C$27)*(1-$C$28)/($B79-C$75))*(1+$B79)^(-(Inputs!$C$9+9)))-$C$48)*(1-$C$50)+$C$57+$C$58)/$C$60 -> 255.80753 | D79: =(((SUMPRODUCT($I$19:$R$19*(1+$B79)^(-$I$20:$R$20))+($R$6*(1+D$75)*(1-$C$27)*(1-$C$28)/($B79-D$75))*(1+$B79)^(-(Inputs!$C$9+9)))-$C$48)*(1-$C$50)+$C$57+$C$58)/$C$60 -> 273.21523 | E79: =(((SUMPRODUCT($I$19:$R$19*(1+$B79)^(-$I$20:$R$20))+($R$6*(1+E$75)*(1-$C$27)*(1-$C$28)/($B79-E$75))*(1+$B79)^(-(Inputs!$C$9+9)))-$C$48)*(1-$C$50)+$C$57+$C$58)/$C$60 -> 293.76527 | F79: =(((SUMPRODUCT($I$19:$R$19*(1+$B79)^(-$I$20:$R$20))+($R$6*(1+F$75)*(1-$C$27)*(1-$C$28)/($B79-F$75))*(1+$B79)^(-(Inputs!$C$9+9)))-$C$48)*(1-$C$50)+$C$57+$C$58)/$C$60 -> 318.39289 | G79: =(((SUMPRODUCT($I$19:$R$19*(1+$B79)^(-$I$20:$R$20))+($R$6*(1+G$75)*(1-$C$27)*(1-$C$28)/($B79-G$75))*(1+$B79)^(-(Inputs!$C$9+9)))-$C$48)*(1-$C$50)+$C$57+$C$58)/$C$60 -> 348.4454
B80: =$C$25+(0.01) -> 0.1003975 | C80: =(((SUMPRODUCT($I$19:$R$19*(1+$B80)^(-$I$20:$R$20))+($R$6*(1+C$75)*(1-$C$27)*(1-$C$28)/($B80-C$75))*(1+$B80)^(-(Inputs!$C$9+9)))-$C$48)*(1-$C$50)+$C$57+$C$58)/$C$60 -> 230.83615 | D80: =(((SUMPRODUCT($I$19:$R$19*(1+$B80)^(-$I$20:$R$20))+($R$6*(1+D$75)*(1-$C$27)*(1-$C$28)/($B80-D$75))*(1+$B80)^(-(Inputs!$C$9+9)))-$C$48)*(1-$C$50)+$C$57+$C$58)/$C$60 -> 245.20587 | E80: =(((SUMPRODUCT($I$19:$R$19*(1+$B80)^(-$I$20:$R$20))+($R$6*(1+E$75)*(1-$C$27)*(1-$C$28)/($B80-E$75))*(1+$B80)^(-(Inputs!$C$9+9)))-$C$48)*(1-$C$50)+$C$57+$C$58)/$C$60 -> 261.95479 | F80: =(((SUMPRODUCT($I$19:$R$19*(1+$B80)^(-$I$20:$R$20))+($R$6*(1+F$75)*(1-$C$27)*(1-$C$28)/($B80-F$75))*(1+$B80)^(-(Inputs!$C$9+9)))-$C$48)*(1-$C$50)+$C$57+$C$58)/$C$60 -> 281.72711 | G80: =(((SUMPRODUCT($I$19:$R$19*(1+$B80)^(-$I$20:$R$20))+($R$6*(1+G$75)*(1-$C$27)*(1-$C$28)/($B80-G$75))*(1+$B80)^(-(Inputs!$C$9+9)))-$C$48)*(1-$C$50)+$C$57+$C$58)/$C$60 -> 305.42271
B82: 6. Sensitivity – value per unit (Rs): WACC (down) × normalised terminal capex % of EBITDA (across)
B83: WACC ↓ / capex % → | C83: 0.04 | D83: 0.06 | E83: 0.08 | F83: 0.1 | G83: 0.12
B84: =$C$25+(-0.01) -> 0.080397496 | C84: =(((SUMPRODUCT($I$19:$R$19*(1+$B84)^(-$I$20:$R$20))+($R$6*(1+$C$26)*(1-C$83)*(1-$C$28)/($B84-$C$26))*(1+$B84)^(-(Inputs!$C$9+9)))-$C$48)*(1-$C$50)+$C$57+$C$58)/$C$60 -> 452.54317 | D84: =(((SUMPRODUCT($I$19:$R$19*(1+$B84)^(-$I$20:$R$20))+($R$6*(1+$C$26)*(1-D$83)*(1-$C$28)/($B84-$C$26))*(1+$B84)^(-(Inputs!$C$9+9)))-$C$48)*(1-$C$50)+$C$57+$C$58)/$C$60 -> 444.53716 | E84: =(((SUMPRODUCT($I$19:$R$19*(1+$B84)^(-$I$20:$R$20))+($R$6*(1+$C$26)*(1-E$83)*(1-$C$28)/($B84-$C$26))*(1+$B84)^(-(Inputs!$C$9+9)))-$C$48)*(1-$C$50)+$C$57+$C$58)/$C$60 -> 436.53114 | F84: =(((SUMPRODUCT($I$19:$R$19*(1+$B84)^(-$I$20:$R$20))+($R$6*(1+$C$26)*(1-F$83)*(1-$C$28)/($B84-$C$26))*(1+$B84)^(-(Inputs!$C$9+9)))-$C$48)*(1-$C$50)+$C$57+$C$58)/$C$60 -> 428.52513 | G84: =(((SUMPRODUCT($I$19:$R$19*(1+$B84)^(-$I$20:$R$20))+($R$6*(1+$C$26)*(1-G$83)*(1-$C$28)/($B84-$C$26))*(1+$B84)^(-(Inputs!$C$9+9)))-$C$48)*(1-$C$50)+$C$57+$C$58)/$C$60 -> 420.51911
B85: =$C$25+(-0.005) -> 0.085397496 | C85: =(((SUMPRODUCT($I$19:$R$19*(1+$B85)^(-$I$20:$R$20))+($R$6*(1+$C$26)*(1-C$83)*(1-$C$28)/($B85-$C$26))*(1+$B85)^(-(Inputs!$C$9+9)))-$C$48)*(1-$C$50)+$C$57+$C$58)/$C$60 -> 392.08387 | D85: =(((SUMPRODUCT($I$19:$R$19*(1+$B85)^(-$I$20:$R$20))+($R$6*(1+$C$26)*(1-D$83)*(1-$C$28)/($B85-$C$26))*(1+$B85)^(-(Inputs!$C$9+9)))-$C$48)*(1-$C$50)+$C$57+$C$58)/$C$60 -> 385.26446 | E85: =(((SUMPRODUCT($I$19:$R$19*(1+$B85)^(-$I$20:$R$20))+($R$6*(1+$C$26)*(1-E$83)*(1-$C$28)/($B85-$C$26))*(1+$B85)^(-(Inputs!$C$9+9)))-$C$48)*(1-$C$50)+$C$57+$C$58)/$C$60 -> 378.44505 | F85: =(((SUMPRODUCT($I$19:$R$19*(1+$B85)^(-$I$20:$R$20))+($R$6*(1+$C$26)*(1-F$83)*(1-$C$28)/($B85-$C$26))*(1+$B85)^(-(Inputs!$C$9+9)))-$C$48)*(1-$C$50)+$C$57+$C$58)/$C$60 -> 371.62564 | G85: =(((SUMPRODUCT($I$19:$R$19*(1+$B85)^(-$I$20:$R$20))+($R$6*(1+$C$26)*(1-G$83)*(1-$C$28)/($B85-$C$26))*(1+$B85)^(-(Inputs!$C$9+9)))-$C$48)*(1-$C$50)+$C$57+$C$58)/$C$60 -> 364.80623
B86: =$C$25+(0) -> 0.090397496 | C86: =(((SUMPRODUCT($I$19:$R$19*(1+$B86)^(-$I$20:$R$20))+($R$6*(1+$C$26)*(1-C$83)*(1-$C$28)/($B86-$C$26))*(1+$B86)^(-(Inputs!$C$9+9)))-$C$48)*(1-$C$50)+$C$57+$C$58)/$C$60 -> 343.6608 | D86: =(((SUMPRODUCT($I$19:$R$19*(1+$B86)^(-$I$20:$R$20))+($R$6*(1+$C$26)*(1-D$83)*(1-$C$28)/($B86-$C$26))*(1+$B86)^(-(Inputs!$C$9+9)))-$C$48)*(1-$C$50)+$C$57+$C$58)/$C$60 -> 337.77962 | E86: =(((SUMPRODUCT($I$19:$R$19*(1+$B86)^(-$I$20:$R$20))+($R$6*(1+$C$26)*(1-E$83)*(1-$C$28)/($B86-$C$26))*(1+$B86)^(-(Inputs!$C$9+9)))-$C$48)*(1-$C$50)+$C$57+$C$58)/$C$60 -> 331.89843 | F86: =(((SUMPRODUCT($I$19:$R$19*(1+$B86)^(-$I$20:$R$20))+($R$6*(1+$C$26)*(1-F$83)*(1-$C$28)/($B86-$C$26))*(1+$B86)^(-(Inputs!$C$9+9)))-$C$48)*(1-$C$50)+$C$57+$C$58)/$C$60 -> 326.01725 | G86: =(((SUMPRODUCT($I$19:$R$19*(1+$B86)^(-$I$20:$R$20))+($R$6*(1+$C$26)*(1-G$83)*(1-$C$28)/($B86-$C$26))*(1+$B86)^(-(Inputs!$C$9+9)))-$C$48)*(1-$C$50)+$C$57+$C$58)/$C$60 -> 320.13607
B87: =$C$25+(0.005) -> 0.095397496 | C87: =(((SUMPRODUCT($I$19:$R$19*(1+$B87)^(-$I$20:$R$20))+($R$6*(1+$C$26)*(1-C$83)*(1-$C$28)/($B87-$C$26))*(1+$B87)^(-(Inputs!$C$9+9)))-$C$48)*(1-$C$50)+$C$57+$C$58)/$C$60 -> 304.01223 | D87: =(((SUMPRODUCT($I$19:$R$19*(1+$B87)^(-$I$20:$R$20))+($R$6*(1+$C$26)*(1-D$83)*(1-$C$28)/($B87-$C$26))*(1+$B87)^(-(Inputs!$C$9+9)))-$C$48)*(1-$C$50)+$C$57+$C$58)/$C$60 -> 298.88875 | E87: =(((SUMPRODUCT($I$19:$R$19*(1+$B87)^(-$I$20:$R$20))+($R$6*(1+$C$26)*(1-E$83)*(1-$C$28)/($B87-$C$26))*(1+$B87)^(-(Inputs!$C$9+9)))-$C$48)*(1-$C$50)+$C$57+$C$58)/$C$60 -> 293.76527 | F87: =(((SUMPRODUCT($I$19:$R$19*(1+$B87)^(-$I$20:$R$20))+($R$6*(1+$C$26)*(1-F$83)*(1-$C$28)/($B87-$C$26))*(1+$B87)^(-(Inputs!$C$9+9)))-$C$48)*(1-$C$50)+$C$57+$C$58)/$C$60 -> 288.64179 | G87: =(((SUMPRODUCT($I$19:$R$19*(1+$B87)^(-$I$20:$R$20))+($R$6*(1+$C$26)*(1-G$83)*(1-$C$28)/($B87-$C$26))*(1+$B87)^(-(Inputs!$C$9+9)))-$C$48)*(1-$C$50)+$C$57+$C$58)/$C$60 -> 283.5183
B88: =$C$25+(0.01) -> 0.1003975 | C88: =(((SUMPRODUCT($I$19:$R$19*(1+$B88)^(-$I$20:$R$20))+($R$6*(1+$C$26)*(1-C$83)*(1-$C$28)/($B88-$C$26))*(1+$B88)^(-(Inputs!$C$9+9)))-$C$48)*(1-$C$50)+$C$57+$C$58)/$C$60 -> 270.95668 | D88: =(((SUMPRODUCT($I$19:$R$19*(1+$B88)^(-$I$20:$R$20))+($R$6*(1+$C$26)*(1-D$83)*(1-$C$28)/($B88-$C$26))*(1+$B88)^(-(Inputs!$C$9+9)))-$C$48)*(1-$C$50)+$C$57+$C$58)/$C$60 -> 266.45573 | E88: =(((SUMPRODUCT($I$19:$R$19*(1+$B88)^(-$I$20:$R$20))+($R$6*(1+$C$26)*(1-E$83)*(1-$C$28)/($B88-$C$26))*(1+$B88)^(-(Inputs!$C$9+9)))-$C$48)*(1-$C$50)+$C$57+$C$58)/$C$60 -> 261.95479 | F88: =(((SUMPRODUCT($I$19:$R$19*(1+$B88)^(-$I$20:$R$20))+($R$6*(1+$C$26)*(1-F$83)*(1-$C$28)/($B88-$C$26))*(1+$B88)^(-(Inputs!$C$9+9)))-$C$48)*(1-$C$50)+$C$57+$C$58)/$C$60 -> 257.45384 | G88: =(((SUMPRODUCT($I$19:$R$19*(1+$B88)^(-$I$20:$R$20))+($R$6*(1+$C$26)*(1-G$83)*(1-$C$28)/($B88-$C$26))*(1+$B88)^(-(Inputs!$C$9+9)))-$C$48)*(1-$C$50)+$C$57+$C$58)/$C$60 -> 252.9529
B90: 7. Reverse DCF – what WACC does the current price imply? (g and cash flows held at base case)
B91: WACC | C91: Value / unit (Rs)
B92: 0.07 | C92: =(((SUMPRODUCT($I$19:$R$19*(1+$B92)^(-$I$20:$R$20))+($R$6*(1+$C$26)*(1-$C$27)*(1-$C$28)/($B92-$C$26))*(1+$B92)^(-(Inputs!$C$9+9)))-$C$48)*(1-$C$50)+$C$57+$C$58)/$C$60 -> 619.40468
B93: 0.075 | C93: =(((SUMPRODUCT($I$19:$R$19*(1+$B93)^(-$I$20:$R$20))+($R$6*(1+$C$26)*(1-$C$27)*(1-$C$28)/($B93-$C$26))*(1+$B93)^(-(Inputs!$C$9+9)))-$C$48)*(1-$C$50)+$C$57+$C$58)/$C$60 -> 517.88798
B94: 0.08 | C94: =(((SUMPRODUCT($I$19:$R$19*(1+$B94)^(-$I$20:$R$20))+($R$6*(1+$C$26)*(1-$C$27)*(1-$C$28)/($B94-$C$26))*(1+$B94)^(-(Inputs!$C$9+9)))-$C$48)*(1-$C$50)+$C$57+$C$58)/$C$60 -> 441.77287
B95: 0.085 | C95: =(((SUMPRODUCT($I$19:$R$19*(1+$B95)^(-$I$20:$R$20))+($R$6*(1+$C$26)*(1-$C$27)*(1-$C$28)/($B95-$C$26))*(1+$B95)^(-(Inputs!$C$9+9)))-$C$48)*(1-$C$50)+$C$57+$C$58)/$C$60 -> 382.58996
B96: 0.09 | C96: =(((SUMPRODUCT($I$19:$R$19*(1+$B96)^(-$I$20:$R$20))+($R$6*(1+$C$26)*(1-$C$27)*(1-$C$28)/($B96-$C$26))*(1+$B96)^(-(Inputs!$C$9+9)))-$C$48)*(1-$C$50)+$C$57+$C$58)/$C$60 -> 335.25776
B97: 0.095 | C97: =(((SUMPRODUCT($I$19:$R$19*(1+$B97)^(-$I$20:$R$20))+($R$6*(1+$C$26)*(1-$C$27)*(1-$C$28)/($B97-$C$26))*(1+$B97)^(-(Inputs!$C$9+9)))-$C$48)*(1-$C$50)+$C$57+$C$58)/$C$60 -> 296.54276
B98: 0.1 | C98: =(((SUMPRODUCT($I$19:$R$19*(1+$B98)^(-$I$20:$R$20))+($R$6*(1+$C$26)*(1-$C$27)*(1-$C$28)/($B98-$C$26))*(1+$B98)^(-(Inputs!$C$9+9)))-$C$48)*(1-$C$50)+$C$57+$C$58)/$C$60 -> 264.2894
B99: 0.105 | C99: =(((SUMPRODUCT($I$19:$R$19*(1+$B99)^(-$I$20:$R$20))+($R$6*(1+$C$26)*(1-$C$27)*(1-$C$28)/($B99-$C$26))*(1+$B99)^(-(Inputs!$C$9+9)))-$C$48)*(1-$C$50)+$C$57+$C$58)/$C$60 -> 237.00549
B100: 0.11 | C100: =(((SUMPRODUCT($I$19:$R$19*(1+$B100)^(-$I$20:$R$20))+($R$6*(1+$C$26)*(1-$C$27)*(1-$C$28)/($B100-$C$26))*(1+$B100)^(-(Inputs!$C$9+9)))-$C$48)*(1-$C$50)+$C$57+$C$58)/$C$60 -> 213.62523
B101: 0.115 | C101: =(((SUMPRODUCT($I$19:$R$19*(1+$B101)^(-$I$20:$R$20))+($R$6*(1+$C$26)*(1-$C$27)*(1-$C$28)/($B101-$C$26))*(1+$B101)^(-(Inputs!$C$9+9)))-$C$48)*(1-$C$50)+$C$57+$C$58)/$C$60 -> 193.36714
B102: 0.12 | C102: =(((SUMPRODUCT($I$19:$R$19*(1+$B102)^(-$I$20:$R$20))+($R$6*(1+$C$26)*(1-$C$27)*(1-$C$28)/($B102-$C$26))*(1+$B102)^(-(Inputs!$C$9+9)))-$C$48)*(1-$C$50)+$C$57+$C$58)/$C$60 -> 175.64517
B103: 0.125 | C103: =(((SUMPRODUCT($I$19:$R$19*(1+$B103)^(-$I$20:$R$20))+($R$6*(1+$C$26)*(1-$C$27)*(1-$C$28)/($B103-$C$26))*(1+$B103)^(-(Inputs!$C$9+9)))-$C$48)*(1-$C$50)+$C$57+$C$58)/$C$60 -> 160.01121
B104: 0.13 | C104: =(((SUMPRODUCT($I$19:$R$19*(1+$B104)^(-$I$20:$R$20))+($R$6*(1+$C$26)*(1-$C$27)*(1-$C$28)/($B104-$C$26))*(1+$B104)^(-(Inputs!$C$9+9)))-$C$48)*(1-$C$50)+$C$57+$C$58)/$C$60 -> 146.11679
B106: Market-implied WACC (linear interpolation at current price) | C106: =INDEX(B92:B104,MATCH(Inputs!$C$10,C92:C104,-1))+(INDEX(C92:C104,MATCH(Inputs!$C$10,C92:C104,-1))-Inputs!$C$10)/(INDEX(C92:C104,MATCH(Inputs!$C$10,C92:C104,-1))-INDEX(C92:C104,MATCH(Inputs!$C$10,C92:C104,-1)+1))*0.005 -> 0.090834012 | D106: Compare with model WACC in C25: a lower implied WACC means the market is pricing the REIT more richly than the model.

Sheet DDM_NDCF
B1: NDCF / DIVIDEND DISCOUNT MODEL– equity-level valuation per unit
B2: REITs distribute ≥90% of NDCF, so FCFE ≈ DPU · Two-stage DDM at cost of equity · anchored to Q1 FY27 distribution run-rate
B3: 1. Distribution forecast and present value
I4: FY27E | J4: FY28E | K4: FY29E | L4: FY30E | M4: FY31E | N4: FY32E | O4: FY33E | P4: FY34E | Q4: FY35E | R4: FY36E
B5: Distribution per unit (Rs) | I5: =Fin_Proj!I86 -> 22.6 | J5: =Fin_Proj!J86 -> 24.586689 | K5: =Fin_Proj!K86 -> 25.886529 | L5: =Fin_Proj!L86 -> 27.051181 | M5: =Fin_Proj!M86 -> 28.248721 | N5: =Fin_Proj!N86 -> 29.444849 | O5: =Fin_Proj!O86 -> 30.6368 | P5: =Fin_Proj!P86 -> 31.82155 | ... R5: =Fin_Proj!R86 -> 35.615167
B6: DPU still to be received after valuation date (Rs) | I6: =I5-Inputs!$C$16 -> 17 | J6: =J5 -> 24.586689 | K6: =K5 -> 25.886529 | L6: =L5 -> 27.051181 | M6: =M5 -> 28.248721 | N6: =N5 -> 29.444849 | O6: =O5 -> 30.6368 | P6: =P5 -> 31.82155 | Q6: =Q5 -> 33.671082 | R6: =R5 -> 35.615167
B7: Discount period (years, mid-period) | I7: =DCF_FCFF!I20 -> 0.23561644 | J7: =DCF_FCFF!J20 -> 0.97123288 | K7: =DCF_FCFF!K20 -> 1.9712329 | L7: =DCF_FCFF!L20 -> 2.9712329 | M7: =DCF_FCFF!M20 -> 3.9712329 | N7: =DCF_FCFF!N20 -> 4.9712329 | O7: =DCF_FCFF!O20 -> 5.9712329 | P7: =DCF_FCFF!P20 -> 6.9712329 | ... R7: =DCF_FCFF!R20 -> 8.9712329
B8: Discount factor at cost of equity | I8: =1/(1+$C$13)^I7 -> 0.97627527 | J8: =1/(1+$C$13)^J7 -> 0.90576598 | K8: =1/(1+$C$13)^K7 -> 0.81801046 | L8: =1/(1+$C$13)^L7 -> 0.73875718 | M8: =1/(1+$C$13)^M7 -> 0.66718238 | N8: =1/(1+$C$13)^N7 -> 0.60254213 | O8: =1/(1+$C$13)^O7 -> 0.54416459 | P8: =1/(1+$C$13)^P7 -> 0.49144297 | ... R8: =1/(1+$C$13)^R7 -> 0.40082872
B9: Present value (Rs/unit) | I9: =I6*I8 -> 16.59668 | J9: =J6*J8 -> 22.269786 | K9: =K6*K8 -> 21.175451 | L9: =L6*L8 -> 19.984254 | M9: =M6*M8 -> 18.847049 | N9: =N6*N8 -> 17.741762 | O9: =O6*O8 -> 16.671462 | P9: =P6*P8 -> 15.638477 | ... R9: =R6*R8 -> 14.275582
B11: 2. Valuation
B13: Cost of equity | C13: =WACC!$C$26 -> 0.10727921 | D13: From WACC sheet
B14: Stable growth in distributions | C14: 0.04 | D14: ASSUMPTION – equal to terminal growth in DCF (inflation-linked rent growth)
B15: Terminal value of distributions (end FY36E) | C15: =R5*(1+C14)/(C13-C14) -> 550.53817
B16: PV of terminal value (Rs/unit) | C16: =C15/(1+C13)^(Inputs!$C$9+9) -> 209.7093
B17: PV of explicit distributions (Rs/unit) | C17: =SUM(I9:R9) -> 178.14472
B18: DDM VALUE PER UNIT (Rs) | C18: =C16+C17 -> 387.85402
B19: Upside / (downside) vs current price | C19: =C18/Inputs!$C$10-1 -> 0.17960468
B20: Terminal value as % of value | C20: =C16/C18 -> 0.54069133
B21: Cross-check: Gordon on annualised run-rate DPU | C21: =Inputs!$C$17*(1+C14)/(C13-C14) -> 346.25852 | D21: Single-stage
B22: Implied distribution yield at DDM value | C22: =Fin_Proj!I86/C18 -> 0.058269346
B23: FCFE check: equity-funded capex (debt-funded in base case) | C23: =0 -> 0 | D23: Growth capex is debt-funded, so FCFE ≈ NDCF ≈ DPU
B25: 3. Sensitivity – DDM value per unit (Rs): cost of equity (down) × stable growth (across)
B26: CoE ↓ / g → | C26: =$C$14+(-0.01) -> 0.03 | D26: =$C$14+(-0.005) -> 0.035 | E26: =$C$14+(0) -> 0.04 | F26: =$C$14+(0.005) -> 0.045 | G26: =$C$14+(0.01) -> 0.05
B27: =$C$13+(-0.01) -> 0.097279211 | C27: =SUMPRODUCT($I$6:$R$6*(1+$B27)^(-$I$7:$R$7))+$R$5*(1+C$26)/($B27-C$26)*(1+$B27)^(-(Inputs!$C$9+9)) -> 411.42348 | D27: =SUMPRODUCT($I$6:$R$6*(1+$B27)^(-$I$7:$R$7))+$R$5*(1+D$26)/($B27-D$26)*(1+$B27)^(-(Inputs!$C$9+9)) -> 430.78079 | E27: =SUMPRODUCT($I$6:$R$6*(1+$B27)^(-$I$7:$R$7))+$R$5*(1+E$26)/($B27-E$26)*(1+$B27)^(-(Inputs!$C$9+9)) -> 453.51757 | F27: =SUMPRODUCT($I$6:$R$6*(1+$B27)^(-$I$7:$R$7))+$R$5*(1+F$26)/($B27-F$26)*(1+$B27)^(-(Inputs!$C$9+9)) -> 480.60345 | G27: =SUMPRODUCT($I$6:$R$6*(1+$B27)^(-$I$7:$R$7))+$R$5*(1+G$26)/($B27-G$26)*(1+$B27)^(-(Inputs!$C$9+9)) -> 513.41825
B28: =$C$13+(-0.005) -> 0.10227921 | C28: =SUMPRODUCT($I$6:$R$6*(1+$B28)^(-$I$7:$R$7))+$R$5*(1+C$26)/($B28-C$26)*(1+$B28)^(-(Inputs!$C$9+9)) -> 383.35731 | D28: =SUMPRODUCT($I$6:$R$6*(1+$B28)^(-$I$7:$R$7))+$R$5*(1+D$26)/($B28-D$26)*(1+$B28)^(-(Inputs!$C$9+9)) -> 399.40633 | E28: =SUMPRODUCT($I$6:$R$6*(1+$B28)^(-$I$7:$R$7))+$R$5*(1+E$26)/($B28-E$26)*(1+$B28)^(-(Inputs!$C$9+9)) -> 418.0323 | F28: =SUMPRODUCT($I$6:$R$6*(1+$B28)^(-$I$7:$R$7))+$R$5*(1+F$26)/($B28-F$26)*(1+$B28)^(-(Inputs!$C$9+9)) -> 439.91006 | G28: =SUMPRODUCT($I$6:$R$6*(1+$B28)^(-$I$7:$R$7))+$R$5*(1+G$26)/($B28-G$26)*(1+$B28)^(-(Inputs!$C$9+9)) -> 465.9726
B29: =$C$13+(0) -> 0.10727921 | C29: =SUMPRODUCT($I$6:$R$6*(1+$B29)^(-$I$7:$R$7))+$R$5*(1+C$26)/($B29-C$26)*(1+$B29)^(-(Inputs!$C$9+9)) -> 358.96194 | D29: =SUMPRODUCT($I$6:$R$6*(1+$B29)^(-$I$7:$R$7))+$R$5*(1+D$26)/($B29-D$26)*(1+$B29)^(-(Inputs!$C$9+9)) -> 372.40866 | E29: =SUMPRODUCT($I$6:$R$6*(1+$B29)^(-$I$7:$R$7))+$R$5*(1+E$26)/($B29-E$26)*(1+$B29)^(-(Inputs!$C$9+9)) -> 387.85402 | F29: =SUMPRODUCT($I$6:$R$6*(1+$B29)^(-$I$7:$R$7))+$R$5*(1+F$26)/($B29-F$26)*(1+$B29)^(-(Inputs!$C$9+9)) -> 405.7794 | G29: =SUMPRODUCT($I$6:$R$6*(1+$B29)^(-$I$7:$R$7))+$R$5*(1+G$26)/($B29-G$26)*(1+$B29)^(-(Inputs!$C$9+9)) -> 426.83426
B30: =$C$13+(0.005) -> 0.11227921 | C30: =SUMPRODUCT($I$6:$R$6*(1+$B30)^(-$I$7:$R$7))+$R$5*(1+C$26)/($B30-C$26)*(1+$B30)^(-(Inputs!$C$9+9)) -> 337.56571 | D30: =SUMPRODUCT($I$6:$R$6*(1+$B30)^(-$I$7:$R$7))+$R$5*(1+D$26)/($B30-D$26)*(1+$B30)^(-(Inputs!$C$9+9)) -> 348.93581 | E30: =SUMPRODUCT($I$6:$R$6*(1+$B30)^(-$I$7:$R$7))+$R$5*(1+E$26)/($B30-E$26)*(1+$B30)^(-(Inputs!$C$9+9)) -> 361.87898 | F30: =SUMPRODUCT($I$6:$R$6*(1+$B30)^(-$I$7:$R$7))+$R$5*(1+F$26)/($B30-F$26)*(1+$B30)^(-(Inputs!$C$9+9)) -> 376.74596 | G30: =SUMPRODUCT($I$6:$R$6*(1+$B30)^(-$I$7:$R$7))+$R$5*(1+G$26)/($B30-G$26)*(1+$B30)^(-(Inputs!$C$9+9)) -> 394.00009
B31: =$C$13+(0.01) -> 0.11727921 | C31: =SUMPRODUCT($I$6:$R$6*(1+$B31)^(-$I$7:$R$7))+$R$5*(1+C$26)/($B31-C$26)*(1+$B31)^(-(Inputs!$C$9+9)) -> 318.65104 | D31: =SUMPRODUCT($I$6:$R$6*(1+$B31)^(-$I$7:$R$7))+$R$5*(1+D$26)/($B31-D$26)*(1+$B31)^(-(Inputs!$C$9+9)) -> 328.34307 | E31: =SUMPRODUCT($I$6:$R$6*(1+$B31)^(-$I$7:$R$7))+$R$5*(1+E$26)/($B31-E$26)*(1+$B31)^(-(Inputs!$C$9+9)) -> 339.28927 | F31: =SUMPRODUCT($I$6:$R$6*(1+$B31)^(-$I$7:$R$7))+$R$5*(1+F$26)/($B31-F$26)*(1+$B31)^(-(Inputs!$C$9+9)) -> 351.74989 | G31: =SUMPRODUCT($I$6:$R$6*(1+$B31)^(-$I$7:$R$7))+$R$5*(1+G$26)/($B31-G$26)*(1+$B31)^(-(Inputs!$C$9+9)) -> 366.06259

Sheet Relative
B1: RELATIVE VALUATION – peer REIT multiples : equity multiples (P/NAV, yield) and value multiple (EV/NOI)
B2: Peer prices: late-Sep-2026 closes · Fundamentals: Q1 FY27 results / FY26 NAV · Net debt for Mindspace and KRT derived from reported LTV (see notes)
B6: REIT | C6: Price (Rs) | D6: Units (cr) | E6: NAV/unit (Rs) | F6: Q1 FY27 NOI (Rs cr) | G6: Annualised NOI | H6: Net debt (Rs cr) | I6: Q1 DPU (Rs) | J6: Market cap (Rs cr) | K6: EV (Rs cr) | L6: EV / NOI (x) | M6: P / NAV (x) | N6: DPU yield | O6: Source / note
B7: Embassy Office Parks REIT | C7: 438 | D7: 94.79 | E7: 491.62 | F7: 1020.48 | G7: =F7*4 -> 4081.92 | H7: 21879 | I7: 6.31 | J7: =C7*D7 -> 41518.02 | K7: =J7+H7 -> 63397.02 | L7: =K7/G7 -> 15.531177 | M7: =C7/E7 -> 0.89093202 | N7: =I7*4/C7 -> 0.057625571 | O7: Embassy Q1 FY27 release (30-Jul-26): net debt Rs 21,879 cr; NAV FY26 annual report; units = NAV equity Rs 46,600 cr / NAV per unit
B8: Mindspace Business Parks REIT | C8: 508 | D8: 66.2 | E8: 527 | F8: 788 | G8: =F8*4 -> 3152 | H8: 15411 | I8: 6.67 | J8: =C8*D8 -> 33629.6 | K8: =J8+H8 -> 49040.6 | L8: =K8/G8 -> 15.558566 | M8: =C8/E8 -> 0.96394687 | N8: =I8*4/C8 -> 0.052519685 | O8: Q1 FY27 (5-Aug-26); units = Rs 441.55 cr distribution / DPU; net debt DERIVED = 29.7% LTV x GAV Rs 51,890 cr
B9: Knowledge Realty Trust | C9: 113 | D9: 443.43 | E9: 123.61 | F9: 1111.7 | G9: =F9*4 -> 4446.8 | H9: 12031 | I9: 1.695 | J9: =C9*D9 -> 50107.59 | K9: =J9+H9 -> 62138.59 | L9: =K9/G9 -> 13.973777 | M9: =C9/E9 -> 0.91416552 | N9: =I9*4/C9 -> 0.06 | O9: Q1 FY27 (28-Jul-26); NAV 31-Mar-26; units = Rs 751.6 cr / DPU; net debt DERIVED from 18% LTV and NAV equity
B11: Mean | L11: =AVERAGE(L7:L9) -> 15.021173 | M11: =AVERAGE(M7:M9) -> 0.9230148 | N11: =AVERAGE(N7:N9) -> 0.056715085
B12: Median | L12: =MEDIAN(L7:L9) -> 15.531177 | M12: =MEDIAN(M7:M9) -> 0.91416552 | N12: =MEDIAN(N7:N9) -> 0.057625571
B13: Minimum | L13: =MIN(L7:L9) -> 13.973777 | M13: =MIN(M7:M9) -> 0.89093202 | N13: =MIN(N7:N9) -> 0.052519685
B14: Maximum | L14: =MAX(L7:L9) -> 15.558566 | M14: =MAX(M7:M9) -> 0.96394687 | N14: =MAX(N7:N9) -> 0.06
B16: Brookfield India REIT (model basis) | C16: =Inputs!$C$10 -> 328.8 | D16: =Inputs!$C$11 -> 82.988087 | E16: =NAV_Asset!$G$34 -> 379.85862 | F16: 756.56 | G16: =F16*4 -> 3026.24 | H16: =Inputs!$C$34 -> 14060.565 | I16: =Inputs!$C$16 -> 5.6 | J16: =C16*D16 -> 27286.483 | K16: =(J16-DCF_FCFF!C57-DCF_FCFF!C58)/(1-DCF_FCFF!C50)+H16 -> 44301.978 | L16: =K16/G16 -> 14.639281 | M16: =C16/E16 -> 0.8655852 | N16: =I16*4/C16 -> 0.068126521 | O16: Market-implied consolidated EV (100% basis) obtained by reversing the DCF bridge (partners' share, NCP stake); NOI = Q1 FY27 consolidated Rs 756.56 cr x 4
B17: BIRET premium / (discount) to peer median | L17: =L16/L12-1 -> -0.057426138 | M17: =M16/M12-1 -> -0.053141713 | N17: =N16/N12-1 -> 0.18222726
B19: Implied value per unit (Rs) for Brookfield India REIT
B20: Method | C20: Low (peer min) | D20: Median | E20: High (peer max) | F20: Basis
B21: P / NAV x pro-forma NAV | C21: =$E$16*M13 -> 338.42821 | D21: =$E$16*M12 -> 347.25365 | E21: =$E$16*M14 -> 366.16353 | F21: Peer P/NAV (low=min, high=max) x NAV Rs
B22: EV / NOI x consolidated NOI | C22: =(((L13*$G$16)-DCF_FCFF!$C$48)*(1-DCF_FCFF!$C$50)+DCF_FCFF!$C$57+DCF_FCFF!$C$58)/DCF_FCFF!$C$60 -> 309.46831 | D22: =(((L12*$G$16)-DCF_FCFF!$C$48)*(1-DCF_FCFF!$C$50)+DCF_FCFF!$C$57+DCF_FCFF!$C$58)/DCF_FCFF!$C$60 -> 354.70794 | E22: =(((L14*$G$16)-DCF_FCFF!$C$48)*(1-DCF_FCFF!$C$50)+DCF_FCFF!$C$57+DCF_FCFF!$C$58)/DCF_FCFF!$C$60 -> 355.50355 | F22: Peer EV/NOI → EV → same bridge as DCF
B23: Distribution yield (DPU run-rate ÷ peer yield) | C23: =Inputs!$C$17/N14 -> 373.33333 | D23: =Inputs!$C$17/N12 -> 388.71632 | E23: =Inputs!$C$17/N13 -> 426.50675 | F23: Low = highest peer yield
B24: RELATIVE VALUE (average of the three methods) | C24: =AVERAGE(C21:C23) -> 340.40995 | D24: =AVERAGE(D21:D23) -> 363.55931 | E24: =AVERAGE(E21:E23) -> 382.72461
B25: Upside / (downside) vs current price | D25: =D24/Inputs!$C$10-1 -> 0.10571565
B27: Justified multiples from fundamentals (Damodaran: multiples are driven by growth, risk and reinvestment)
B28: Justified EV / EBITDA FY27E from DCF (x) | C28: =DCF_FCFF!C65 -> 16.075086
B29: Justified terminal EV / EBITDA = 1 − capex% x (1 − t) / (WACC − g) | C29: =DCF_FCFF!C38 -> 13.660123
B30: Peer median EV / NOI (market) | C30: =L12 -> 15.531177
B31: BIRET trades at a higher yield than peers: smaller scale, ~90% floating-rate debt, IT/GCC tenant concentration – offset by ~15% embedded DPU growth guidance.

Sheet NAV_Asset
B1: ASSET-BASED VALUATION – NAV by capitalising asset NOI (BAV: asset-based / liquidation vs going-concern)
B2: Forward (FY28E) NOI from Rev_Build x NOI margin ÷ cap rate · same bridge as DCF · compared with reported NAV
B4: 1. Asset-level gross asset value (Rs crore)
B6: Asset | C6: REIT own % | D6: FY28E revenue | E6: FY28E NOI | F6: Cap rate | G6: GAV – Base | H6: GAV – cap −25bp | I6: GAV – cap +25bp | J6: GAV – Stress
B7: Cap-rate shift | G7: 0 | H7: -0.0025 | I7: 0.0025 | J7: 0.01
B8: Transaction / disposal cost (% of GAV) | G8: 0 | H8: 0 | I8: 0 | J8: 0.03
B9: Illiquidity discount on JV stakes | G9: 0 | H9: 0 | I9: 0 | J9: =Inputs!$C$37 -> 0.1
B10: Ecoworld, Bangalore | C10: =Rev_Build!C40 -> 0.87 | D10: =Rev_Build!Z40 -> 1085.6228 | E10: =D10*Inputs!$C$50 -> 841.35767 | F10: 0.0725 | G10: =$E10/($F10+G$7) -> 11604.933 | H10: =$E10/($F10+H$7) -> 12019.395 | I10: =$E10/($F10+I$7) -> 11218.102 | J10: =$E10/($F10+J$7) -> 10198.275 | L10: Cap rates (ASSUMPTION): Bengaluru/Mumbai 7.25%, Gurugram/Noida 7.75%, Kolkata 8.25%; BKC deal priced at 7.4% on FY28E NOI
B11: Downtown Powai, Mumbai | C11: =Rev_Build!C41 -> 0.5 | D11: =Rev_Build!Z41 -> 915.40662 | E11: =D11*Inputs!$C$50 -> 709.44013 | F11: 0.0725 | G11: =$E11/($F11+G$7) -> 9785.3811 | H11: =$E11/($F11+H$7) -> 10134.859 | I11: =$E11/($F11+I$7) -> 9459.2018 | J11: =$E11/($F11+J$7) -> 8599.2743
B12: G1, Gurugram | C12: =Rev_Build!C42 -> 0.5 | D12: =Rev_Build!Z42 -> 488.0985 | E12: =D12*Inputs!$C$50 -> 378.27634 | F12: 0.0775 | G12: =$E12/($F12+G$7) -> 4880.985 | H12: =$E12/($F12+H$7) -> 5043.6845 | I12: =$E12/($F12+I$7) -> 4728.4542 | J12: =$E12/($F12+J$7) -> 4323.1582
B13: G2, Gurugram | C13: =Rev_Build!C43 -> 1 | D13: =Rev_Build!Z43 -> 600.08281 | E13: =D13*Inputs!$C$50 -> 465.06418 | F13: 0.0775 | G13: =$E13/($F13+G$7) -> 6000.8281 | H13: =$E13/($F13+H$7) -> 6200.8557 | I13: =$E13/($F13+I$7) -> 5813.3023 | J13: =$E13/($F13+J$7) -> 5315.0192
B14: N1, Noida | C14: =Rev_Build!C44 -> 1 | D14: =Rev_Build!Z44 -> 296.52931 | E14: =D14*Inputs!$C$50 -> 229.81022 | F14: 0.0775 | G14: =$E14/($F14+G$7) -> 2965.2931 | H14: =$E14/($F14+H$7) -> 3064.1362 | I14: =$E14/($F14+I$7) -> 2872.6277 | J14: =$E14/($F14+J$7) -> 2626.4025
B15: N2, Noida | C15: =Rev_Build!C45 -> 1 | D15: =Rev_Build!Z45 -> 470.00588 | E15: =D15*Inputs!$C$50 -> 364.25456 | F15: 0.0775 | G15: =$E15/($F15+G$7) -> 4700.0588 | H15: =$E15/($F15+H$7) -> 4856.7275 | I15: =$E15/($F15+I$7) -> 4553.182 | J15: =$E15/($F15+J$7) -> 4162.9093
B16: K1, Kolkata | C16: =Rev_Build!C46 -> 1 | D16: =Rev_Build!Z46 -> 287.88669 | E16: =D16*Inputs!$C$50 -> 223.11218 | F16: 0.0825 | G16: =$E16/($F16+G$7) -> 2704.3901 | H16: =$E16/($F16+H$7) -> 2788.9023 | I16: =$E16/($F16+I$7) -> 2624.8492 | J16: =$E16/($F16+J$7) -> 2412.0236
B17: Under-construction area at cost (0.6 msf, 50% complete) | G17: =600*Inputs!$C$45*0.5/10000 -> 195 | H17: =600*Inputs!$C$45*0.5/10000 -> 195 | I17: =600*Inputs!$C$45*0.5/10000 -> 195 | J17: =600*Inputs!$C$45*0.5/10000 -> 195 | L17: ASSUMPTION – 600k sf under construction (Q1 FY27 release) at cost; 4.0 msf potential valued at Rs 300/sf (kept low; optionality valued in Real_Options)
B18: Future development potential (4.0 msf) – land/entitlement value | G18: =4000*300/10000 -> 120 | H18: =4000*300/10000 -> 120 | I18: =4000*300/10000 -> 120 | J18: =4000*300/10000 -> 120
B19: Gross asset value – consolidated operations | D19: =SUM(D10:D16) -> 4143.6326 | E19: =SUM(E10:E16) -> 3211.3153 | G19: =SUM(G10:G18)*(1-G8) -> 42956.87 | H19: =SUM(H10:H18)*(1-H8) -> 44423.561 | I19: =SUM(I10:I18)*(1-I8) -> 41584.719 | J19: =SUM(J10:J18)*(1-J8) -> 36813.5
B21: 2. North Commercial Portfolio (equity-accounted JV, 100% basis)
B22: NCP NOI FY28E | G22: =Rev_Build!$Z$51*Inputs!$C$49 -> 667.64948 | H22: =Rev_Build!$Z$51*Inputs!$C$49 -> 667.64948 | I22: =Rev_Build!$Z$51*Inputs!$C$49 -> 667.64948 | J22: =Rev_Build!$Z$51*Inputs!$C$49 -> 667.64948
B23: NCP enterprise value | G23: =G22/(DCF_FCFF!$C$53+G$7)*(1-G$8) -> 8614.832 | H23: =H22/(DCF_FCFF!$C$53+H$7)*(1-H$8) -> 8901.9931 | I23: =I22/(DCF_FCFF!$C$53+I$7)*(1-I$8) -> 8345.6185 | J23: =J22/(DCF_FCFF!$C$53+J$7)*(1-J$8) -> 7401.3714
B25: 3. NAV bridge (Rs crore)
B26: Gross asset value – consolidated | G26: =G19 -> 42956.87 | H26: =H19 -> 44423.561 | I26: =I19 -> 41584.719 | J26: =J19 -> 36813.5
B27: − Pro-forma net debt | G27: =Inputs!$C$34 -> 14060.565 | H27: =Inputs!$C$34 -> 14060.565 | I27: =Inputs!$C$34 -> 14060.565 | J27: =Inputs!$C$34 -> 14060.565
B28: Equity value, 100% basis | G28: =G26-G27 -> 28896.305 | H28: =H26-H27 -> 30362.996 | I28: =I26-I27 -> 27524.155 | J28: =J26-J27 -> 22752.935
B29: − Partners' share (value-weighted, base-case weights) | G29: =G28*SUMPRODUCT(1-$C$10:$C$16,$G$10:$G$16)/SUM($G$10:$G$16) -> 5991.671 | H29: =H28*SUMPRODUCT(1-$C$10:$C$16,$G$10:$G$16)/SUM($G$10:$G$16) -> 6295.7905 | I29: =I28*SUMPRODUCT(1-$C$10:$C$16,$G$10:$G$16)/SUM($G$10:$G$16) -> 5707.1546 | J29: =J28*SUMPRODUCT(1-$C$10:$C$16,$G$10:$G$16)/SUM($G$10:$G$16) -> 4717.8386
B30: + REIT share of NCP equity (after illiquidity discount) | G30: =(G23-Inputs!$C$35)*Inputs!$C$36*(1-G9) -> 2607.416 | H30: =(H23-Inputs!$C$35)*Inputs!$C$36*(1-H9) -> 2750.9965 | I30: =(I23-Inputs!$C$35)*Inputs!$C$36*(1-I9) -> 2472.8093 | J30: =(J23-Inputs!$C$35)*Inputs!$C$36*(1-J9) -> 1800.6171
B31: + BKC JV stake at cost | G31: =Inputs!$C$32 -> 850 | H31: =Inputs!$C$32 -> 850 | I31: =Inputs!$C$32 -> 850 | J31: =Inputs!$C$32 -> 850
B32: NAV to unitholders | G32: =G28-G29+G30+G31 -> 26362.05 | H32: =H28-H29+H30+H31 -> 27668.202 | I32: =I28-I29+I30+I31 -> 25139.809 | J32: =J28-J29+J30+J31 -> 20685.714
B33: NAV per unit (Rs) | G33: =G32/Inputs!$C$11 -> 317.66065 | H33: =H32/Inputs!$C$11 -> 333.39968 | I33: =I32/Inputs!$C$11 -> 302.93275 | J33: =J32/Inputs!$C$11 -> 249.26124 | L33: Base = going-concern; Stress = +100bp cap rate, 3% disposal cost, JV illiquidity discount (liquidation-style view)
B34: Reported NAV per unit, pro-forma for April-26 QIP (Rs) | G34: =(Inputs!$C$13*(Inputs!$C$11-Inputs!$C$26/Inputs!$C$19)+Inputs!$C$28)/Inputs!$C$11 -> 379.85862 | L34: (Reported NAV x pre-QIP units + net QIP proceeds) ÷ post-QIP units; reported NAV Rs 386.66 at 31-Mar-26
B35: Model NAV vs reported (%) | G35: =G33/$G$34-1 -> -0.16373978 | H35: =H33/$G$34-1 -> -0.12230587 | I35: =I33/$G$34-1 -> -0.20251185 | J35: =J33/$G$34-1 -> -0.34380522
B36: Price / NAV (x) | G36: =Inputs!$C$10/G33 -> 1.0350668 | H36: =Inputs!$C$10/H33 -> 0.9862037 | I36: =Inputs!$C$10/I33 -> 1.0853894 | J36: =Inputs!$C$10/J33 -> 1.319098
B37: Implied blended cap rate – consolidated assets | G37: =E19/SUM(G10:G16) -> 0.07530897
B38: Replacement-cost cross-check: all-in cost Rs/sq ft | G38: 9000 | L38: ASSUMPTION – all-in land + construction cost of comparable Grade-A campus; shows value created over replacement cost
B39: GAV / replacement cost (x) | G39: =SUM(G10:G16)/(Rev_Build!D33*G38/10000) -> 1.6659583

Sheet EVA
B1: ECONOMIC VALUE ADDED & VALUE ENHANCEMENT (BAV Ch. 31–32)
B2: EVA = NOPAT − WACC x opening invested capital · EV = IC₀ + PV(EVA) reconciles to the DCF · value-enhancement levers quantified
B3: 1. Invested capital at book (Ind-AS cost model) – FY26 estimated
B4: Shareholders' funds FY25 | C4: 14029.92 | D4: User model 'Balance Sheet'!F12
B5: Minority interest FY25 | C5: 1980.695 | D5: 'Balance Sheet'!F13
B6: Total debt FY25 | C6: 9058.525 | D6: 'Balance Sheet'!F61
B7: Cash FY25 | C7: 665.744 | D7: 'Balance Sheet'!F50
B8: Invested capital FY25 (equity + MI + debt − cash) | C8: =C4+C5+C6-C7 -> 24403.396
B9: + Ecoworld acquisition consideration (Dec-2025) | C9: 7006.302 | D9: Brookfield FY26 results: Arliga Ecoworld acquired for Rs 7,006.3 cr
B10: + FY26 capex − FY26 depreciation (estimate) | C10: =100-Fin_Proj!H31 -> -369.402 | D10: ASSUMPTION – capex Rs 100 cr
B11: Invested capital FY26E (opening for FY27E) | C11: =C8+C9+C10 -> 31040.296
B13: 2. EVA by year
I14: FY27E | J14: FY28E | K14: FY29E | L14: FY30E | M14: FY31E | N14: FY32E | O14: FY33E | P14: FY34E | Q14: FY35E | R14: FY36E
B15: NOPAT | I15: =DCF_FCFF!I11 -> 1668.9759 | J15: =DCF_FCFF!J11 -> 1812.3431 | K15: =DCF_FCFF!K11 -> 1922.3026 | L15: =DCF_FCFF!L11 -> 2059.0888 | M15: =DCF_FCFF!M11 -> 2180.2556 | N15: =DCF_FCFF!N11 -> 2307.6628 | O15: =DCF_FCFF!O11 -> 2441.6244 | P15: =DCF_FCFF!P11 -> 2582.4698 | ... R15: =DCF_FCFF!R11 -> 2886.2137
B16: Net reinvestment (capex + ΔNWC − D&A) | I16: =DCF_FCFF!I11-DCF_FCFF!I17 -> -264.21808 | J16: =DCF_FCFF!J11-DCF_FCFF!J17 -> -19.565701 | K16: =DCF_FCFF!K11-DCF_FCFF!K17 -> -174.19086 | L16: =DCF_FCFF!L11-DCF_FCFF!L17 -> -438.43389 | M16: =DCF_FCFF!M11-DCF_FCFF!M17 -> -441.4218 | N16: =DCF_FCFF!N11-DCF_FCFF!N17 -> -444.33393 | O16: =DCF_FCFF!O11-DCF_FCFF!O17 -> -447.16487 | P16: =DCF_FCFF!P11-DCF_FCFF!P17 -> -449.90897 | ... R16: =DCF_FCFF!R11-DCF_FCFF!R17 -> -455.1126
B17: Opening invested capital | I17: =$C$11 -> 31040.296 | J17: =I18 -> 30776.078 | K17: =J18 -> 30756.512 | L17: =K18 -> 30582.321 | M17: =L18 -> 30143.887 | N17: =M18 -> 29702.466 | O17: =N18 -> 29258.132 | P17: =O18 -> 28810.967 | Q17: =P18 -> 28361.058 | R17: =Q18 -> 27908.498
B18: Closing invested capital | I18: =I17+I16 -> 30776.078 | J18: =J17+J16 -> 30756.512 | K18: =K17+K16 -> 30582.321 | L18: =L17+L16 -> 30143.887 | M18: =M17+M16 -> 29702.466 | N18: =N17+N16 -> 29258.132 | O18: =O17+O16 -> 28810.967 | P18: =P17+P16 -> 28361.058 | ... R18: =R17+R16 -> 27453.385
B19: ROIC on book capital | I19: =I15/I17 -> 0.053768039 | J19: =J15/J17 -> 0.058888045 | K19: =K15/K17 -> 0.062500669 | L19: =L15/L17 -> 0.067329381 | M19: =M15/M17 -> 0.072328281 | N19: =N15/N17 -> 0.077692634 | O19: =O15/O17 -> 0.083451137 | P19: =P15/P17 -> 0.089634957 | ... R19: =R15/R17 -> 0.10341702
B20: WACC | I20: =WACC!$C$44 -> 0.090397496 | J20: =WACC!$C$44 -> 0.090397496 | K20: =WACC!$C$44 -> 0.090397496 | L20: =WACC!$C$44 -> 0.090397496 | M20: =WACC!$C$44 -> 0.090397496 | N20: =WACC!$C$44 -> 0.090397496 | O20: =WACC!$C$44 -> 0.090397496 | P20: =WACC!$C$44 -> 0.090397496 | ... R20: =WACC!$C$44 -> 0.090397496
B21: ROIC − WACC spread | I21: =I19-I20 -> -0.036629457 | J21: =J19-J20 -> -0.031509451 | K21: =K19-K20 -> -0.027896827 | L21: =L19-L20 -> -0.023068115 | M21: =M19-M20 -> -0.018069215 | N21: =N19-N20 -> -0.012704862 | O21: =O19-O20 -> -0.0069463589 | P21: =P19-P20 -> -0.00076253872 | ... R21: =R19-R20 -> 0.013019527
B22: EVA = NOPAT − WACC x opening IC | I22: =I15-I20*I17 -> -1136.9892 | J22: =J15-J20*J17 -> -969.73731 | K22: =K15-K20*K17 -> -858.0091 | L22: =L15-L20*L17 -> -705.47651 | M22: =M15-M20*M17 -> -544.6764 | N22: =N15-N20*N17 -> -377.36572 | O22: =O15-O20*O17 -> -203.23748 | P22: =P15-P20*P17 -> -21.969478 | ... R22: =R15-R20*R17 -> 363.35544
B23: Discount factor (year-end, from 31-Mar-26) | I23: =1/(1+I20)^DCF_FCFF!I5 -> 0.91709675 | J23: =1/(1+J20)^DCF_FCFF!J5 -> 0.84106645 | K23: =1/(1+K20)^DCF_FCFF!K5 -> 0.77133931 | L23: =1/(1+L20)^DCF_FCFF!L5 -> 0.70739277 | M23: =1/(1+M20)^DCF_FCFF!M5 -> 0.64874761 | N23: =1/(1+N20)^DCF_FCFF!N5 -> 0.59496433 | O23: =1/(1+O20)^DCF_FCFF!O5 -> 0.54563985 | P23: =1/(1+P20)^DCF_FCFF!P5 -> 0.50040453 | ... R23: =1/(1+R20)^DCF_FCFF!R5 -> 0.42087346
B24: PV of EVA | I24: =I22*I23 -> -1042.7291 | J24: =J22*J23 -> -815.61352 | K24: =K22*K23 -> -661.81614 | L24: =L22*L23 -> -499.04898 | M24: =M22*M23 -> -353.35751 | N24: =N22*N23 -> -224.51914 | O24: =O22*O23 -> -110.89447 | P24: =P22*P23 -> -10.993626 | ... R24: =R22*R23 -> 152.92666
B25: FCFF, full year (DCF row 17) | I25: =DCF_FCFF!I17 -> 1933.1939 | J25: =DCF_FCFF!J17 -> 1831.9088 | K25: =DCF_FCFF!K17 -> 2096.4935 | L25: =DCF_FCFF!L17 -> 2497.5227 | M25: =DCF_FCFF!M17 -> 2621.6774 | N25: =DCF_FCFF!N17 -> 2751.9967 | O25: =DCF_FCFF!O17 -> 2888.7892 | P25: =DCF_FCFF!P17 -> 3032.3788 | ... R25: =DCF_FCFF!R17 -> 3341.3263
B26: PV of FCFF (year-end convention) | I26: =I25*I23 -> 1772.9259 | J26: =J25*J23 -> 1540.757 | K26: =K25*K23 -> 1617.1078 | L26: =L25*L23 -> 1766.7295 | M26: =M25*M23 -> 1700.8069 | N26: =N25*N23 -> 1637.3399 | O26: =O25*O23 -> 1576.2385 | P26: =P25*P23 -> 1517.4161 | ... R26: =R25*R23 -> 1406.2756
B28: 3. EVA valuation vs DCF (as at 31-Mar-2026, year-end convention, full-year flows)
B29: Opening invested capital (IC₀) | C29: =C11 -> 31040.296
B30: + PV of EVA, FY27E–FY36E | C30: =SUM(I24:R24) -> -3489.5088
B31: Terminal value of FCFF at FY36 (Gordon, from DCF) | C31: =DCF_FCFF!C35 -> 63970.824
B32: − Closing invested capital FY36E | C32: =R18 -> 27453.385
B33: PV of terminal EVA = (TV − IC_N) discounted | C33: =(C31-C32)*R23 -> 15369.221
B34: EVA-based enterprise value | C34: =C29+C30+C33 -> 42920.008
B35: DCF enterprise value, same convention | C35: =SUM(I26:R26)+C31*R23 -> 42920.008
B36: Difference (should be ~0) | C36: =C34-C35 -> 0
B37: Market value added (EV − book IC₀) | C37: =C34-C29 -> 11879.712
B38: Average ROIC on book capital FY27E–FY36E | C38: =AVERAGE(I19:R19) -> 0.076528814 | D38: Book ROIC is depressed by Ind-AS cost model: Ecoworld enters at acquisition cost but legacy assets sit far below fair value (book value/unit Rs 231 vs NAV Rs 387).
B39: Average spread vs WACC | C39: =AVERAGE(I21:R21) -> -0.013868682
B41: 4. Value-enhancement levers (BAV: operating, financing and investment levers)
B42: Lever | C42: Δ EV (Rs cr) | D42: Δ value / unit (Rs) | E42: Basis
B43: +1pp portfolio occupancy (90% flow-through) | C43: =Rev_Build!$Z$69*0.01/Rev_Build!$Q$67*0.9*(1-Inputs!$C$42)/(DCF_FCFF!C25-DCF_FCFF!C26) -> 618.23473 | D43: =C43*(1-DCF_FCFF!$C$50)/Inputs!$C$11 -> 5.934292 | E43: FY29E revenue x 1pp/occupancy, taxed, capitalised at WACC − g
B44: −100bp operating-expense ratio | C44: =Rev_Build!$Z$69*0.01*(1-Inputs!$C$42)/(DCF_FCFF!C25-DCF_FCFF!C26) -> 646.21144 | D44: =C44*(1-DCF_FCFF!$C$50)/Inputs!$C$11 -> 6.202834 | E44: Margin gain on FY29E revenue, capitalised
B45: −50bp WACC | C45: =(SUMPRODUCT(DCF_FCFF!$I$19:$R$19*(1+(DCF_FCFF!$C$25-0.005))^(-DCF_FCFF!$I$20:$R$20))+(DCF_FCFF!$R$6*(1+DCF_FCFF!$C$26)*(1-DCF_FCFF!$C$27)*(1-DCF_FCFF!$C$28)/((DCF_FCFF!$C$25-0.005)-DCF_FCFF!$C$26))*(1+(DCF_FCFF!$C$25-0.005))^(-(Inputs!$C$9+9)))-DCF_FCFF!C43 -> 4849.2277 | D45: =C45*(1-DCF_FCFF!$C$50)/Inputs!$C$11 -> 46.546614 | E45: Closed-form re-valuation of the DCF
B46: Acquire Rs 1,000 cr at 7.4% cap, g = terminal | C46: =1000*((0.074*(1-Inputs!$C$42)+DCF_FCFF!C26)-DCF_FCFF!C25)/(DCF_FCFF!C25-DCF_FCFF!C26) -> 98.74903 | D46: =C46*(1-DCF_FCFF!$C$50)/Inputs!$C$11 -> 0.94786907 | E46: NPV = A x (IRR − WACC)/(WACC − g); thin spread → discipline matters
B48: 5. Capital-structure lever – WACC at different debt ratios (CoE re-levered, Kd steps up above 30% D/V)
B49: D/V | C49: Re-levered β | D49: Cost of equity | E49: Pre-tax Kd | F49: WACC
B50: 0.1 | C50: =WACC!$C$17*(1+(1-Inputs!$C$42)*B50/(1-B50)) -> 0.49553858 | D50: =(WACC!$C$8+WACC!$C$5)/2+C50*WACC!$C$11 -> 0.098034132 | E50: =WACC!$C$30+0.0025*MAX(0,(B50-0.3)/0.05) -> 0.075 | F50: =(1-B50)*D50+B50*E50*(1-Inputs!$C$42) -> 0.093842969
B51: 0.2 | C51: =WACC!$C$17*(1+(1-Inputs!$C$42)*B51/(1-B51)) -> 0.54308681 | D51: =(WACC!$C$8+WACC!$C$5)/2+C51*WACC!$C$11 -> 0.10140055 | E51: =WACC!$C$30+0.0025*MAX(0,(B51-0.3)/0.05) -> 0.075 | F51: =(1-B51)*D51+B51*E51*(1-Inputs!$C$42) -> 0.092344937
B52: 0.3 | C52: =WACC!$C$17*(1+(1-Inputs!$C$42)*B52/(1-B52)) -> 0.60422025 | D52: =(WACC!$C$8+WACC!$C$5)/2+C52*WACC!$C$11 -> 0.10572879 | E52: =WACC!$C$30+0.0025*MAX(0,(B52-0.3)/0.05) -> 0.075 | F52: =(1-B52)*D52+B52*E52*(1-Inputs!$C$42) -> 0.090846906
B53: 0.33 | C53: =WACC!$C$17*(1+(1-Inputs!$C$42)*B53/(1-B53)) -> 0.62611879 | D53: =(WACC!$C$8+WACC!$C$5)/2+C53*WACC!$C$11 -> 0.10727921 | E53: =WACC!$C$30+0.0025*MAX(0,(B53-0.3)/0.05) -> 0.0765 | F53: =(1-B53)*D53+B53*E53*(1-Inputs!$C$42) -> 0.090767905
B54: 0.35 | C54: =WACC!$C$17*(1+(1-Inputs!$C$42)*B54/(1-B54)) -> 0.64184083 | D54: =(WACC!$C$8+WACC!$C$5)/2+C54*WACC!$C$11 -> 0.10839233 | E54: =WACC!$C$30+0.0025*MAX(0,(B54-0.3)/0.05) -> 0.0775 | F54: =(1-B54)*D54+B54*E54*(1-Inputs!$C$42) -> 0.090752652
B55: 0.4 | C55: =WACC!$C$17*(1+(1-Inputs!$C$42)*B55/(1-B55)) -> 0.6857315 | D55: =(WACC!$C$8+WACC!$C$5)/2+C55*WACC!$C$11 -> 0.11149979 | E55: =WACC!$C$30+0.0025*MAX(0,(B55-0.3)/0.05) -> 0.08 | F55: =(1-B55)*D55+B55*E55*(1-Inputs!$C$42) -> 0.090845474
B56: 0.5 | C56: =WACC!$C$17*(1+(1-Inputs!$C$42)*B56/(1-B56)) -> 0.79984725 | D56: =(WACC!$C$8+WACC!$C$5)/2+C56*WACC!$C$11 -> 0.11957919 | E56: =WACC!$C$30+0.0025*MAX(0,(B56-0.3)/0.05) -> 0.085 | F56: =(1-B56)*D56+B56*E56*(1-Inputs!$C$42) -> 0.091592343
B57: Minimum WACC sits near the target ratio; leverage beyond ~35% LTV raises Kd and equity risk faster than the tax shield helps.

Sheet Scenario_DT
B1: SCENARIO ANALYSIS & DECISION TREES
B2: Three scenarios valued with the same compact FCFF engine as the Monte Carlo · probability-weighted value · two decision trees
B4: 1. Scenario definitions and valuation (shocks applied to the base case)
B5: Scenario | C5: Probability | D5: Δ occupancy (pp, FY28+) | E5: Δ revenue growth FY30+ | F5: Δ EBITDA margin | G5: Δ WACC | H5: Δ terminal g | I5: FY27E | J5: FY28E | K5: FY29E | L5: FY30E | M5: FY31E | N5: FY32E | O5: FY33E | P5: FY34E | Q5: FY35E | R5: FY36E | S5: PV of TV | T5: Enterprise value | U5: Value / unit (Rs)
B6: Bear – softer leasing, rates stay high | C6: 0.25 | D6: -0.03 | E6: -0.01 | F6: -0.015 | G6: 0.0075 | H6: -0.005 | I6: =((Scenario_DT!I$11*(IF(Scenario_DT!I$18=1,1,1+$D6/Scenario_DT!$C$19)*(1+$E6)^MAX(0,Scenario_DT!I$18-3))*(Scenario_DT!I$12+$F6)-Scenario_DT!I$13)*(1-Scenario_DT!I$14)+Scenario_DT!I$13-Scenario_DT!I$15)*Scenario_DT!I$16 -> 889.83615 | J6: =((Scenario_DT!J$11*(IF(Scenario_DT!J$18=1,1,1+$D6/Scenario_DT!$C$19)*(1+$E6)^MAX(0,Scenario_DT!J$18-3))*(Scenario_DT!J$12+$F6)-Scenario_DT!J$13)*(1-Scenario_DT!J$14)+Scenario_DT!J$13-Scenario_DT!J$15)*Scenario_DT!J$16 -> 1714.8917 | K6: =((Scenario_DT!K$11*(IF(Scenario_DT!K$18=1,1,1+$D6/Scenario_DT!$C$19)*(1+$E6)^MAX(0,Scenario_DT!K$18-3))*(Scenario_DT!K$12+$F6)-Scenario_DT!K$13)*(1-Scenario_DT!K$14)+Scenario_DT!K$13-Scenario_DT!K$15)*Scenario_DT!K$16 -> 1974.2054 | L6: =((Scenario_DT!L$11*(IF(Scenario_DT!L$18=1,1,1+$D6/Scenario_DT!$C$19)*(1+$E6)^MAX(0,Scenario_DT!L$18-3))*(Scenario_DT!L$12+$F6)-Scenario_DT!L$13)*(1-Scenario_DT!L$14)+Scenario_DT!L$13-Scenario_DT!L$15)*Scenario_DT!L$16 -> 2343.8345 | M6: =((Scenario_DT!M$11*(IF(Scenario_DT!M$18=1,1,1+$D6/Scenario_DT!$C$19)*(1+$E6)^MAX(0,Scenario_DT!M$18-3))*(Scenario_DT!M$12+$F6)-Scenario_DT!M$13)*(1-Scenario_DT!M$14)+Scenario_DT!M$13-Scenario_DT!M$15)*Scenario_DT!M$16 -> 2435.5173 | N6: =((Scenario_DT!N$11*(IF(Scenario_DT!N$18=1,1,1+$D6/Scenario_DT!$C$19)*(1+$E6)^MAX(0,Scenario_DT!N$18-3))*(Scenario_DT!N$12+$F6)-Scenario_DT!N$13)*(1-Scenario_DT!N$14)+Scenario_DT!N$13-Scenario_DT!N$15)*Scenario_DT!N$16 -> 2530.7621 | O6: =((Scenario_DT!O$11*(IF(Scenario_DT!O$18=1,1,1+$D6/Scenario_DT!$C$19)*(1+$E6)^MAX(0,Scenario_DT!O$18-3))*(Scenario_DT!O$12+$F6)-Scenario_DT!O$13)*(1-Scenario_DT!O$14)+Scenario_DT!O$13-Scenario_DT!O$15)*Scenario_DT!O$16 -> 2629.7086 | P6: =((Scenario_DT!P$11*(IF(Scenario_DT!P$18=1,1,1+$D6/Scenario_DT!$C$19)*(1+$E6)^MAX(0,Scenario_DT!P$18-3))*(Scenario_DT!P$12+$F6)-Scenario_DT!P$13)*(1-Scenario_DT!P$14)+Scenario_DT!P$13-Scenario_DT!P$15)*Scenario_DT!P$16 -> 2732.5018 | ... R6: =((Scenario_DT!R$11*(IF(Scenario_DT!R$18=1,1,1+$D6/Scenario_DT!$C$19)*(1+$E6)^MAX(0,Scenario_DT!R$18-3))*(Scenario_DT!R$12+$F6)-Scenario_DT!R$13)*(1-Scenario_DT!R$14)+Scenario_DT!R$13-Scenario_DT!R$15)*Scenario_DT!R$16 -> 2950.2375 | S6: =(Scenario_DT!$R$11*(1+$D6/Scenario_DT!$C$19)*(1+$E6)^7*(Scenario_DT!$R$12+$F6)*(1+MIN(DCF_FCFF!$C$26+$H6,(DCF_FCFF!$C$25+$G6)-0.02))*(1-DCF_FCFF!$C$27)*(1-DCF_FCFF!$C$28)/((DCF_FCFF!$C$25+$G6)-MIN(DCF_FCFF!$C$26+$H6,(DCF_FCFF!$C$25+$G6)-0.02)))*(1+(DCF_FCFF!$C$25+$G6))^(-(Inputs!$C$9+9)) -> 18617.189 | T6: =SUMPRODUCT(I6:R6*(1+(DCF_FCFF!$C$25+$G6))^(-$I$17:$R$17))+S6 -> 33298.944 | U6: =((T6-DCF_FCFF!$C$48)*(1-DCF_FCFF!$C$50)+DCF_FCFF!$C$57+DCF_FCFF!$C$58)/DCF_FCFF!$C$60 -> 223.18443
B7: Base | C7: 0.5 | D7: 0 | E7: 0 | F7: 0 | G7: 0 | H7: 0 | I7: =((Scenario_DT!I$11*(IF(Scenario_DT!I$18=1,1,1+$D7/Scenario_DT!$C$19)*(1+$E7)^MAX(0,Scenario_DT!I$18-3))*(Scenario_DT!I$12+$F7)-Scenario_DT!I$13)*(1-Scenario_DT!I$14)+Scenario_DT!I$13-Scenario_DT!I$15)*Scenario_DT!I$16 -> 910.98454 | J7: =((Scenario_DT!J$11*(IF(Scenario_DT!J$18=1,1,1+$D7/Scenario_DT!$C$19)*(1+$E7)^MAX(0,Scenario_DT!J$18-3))*(Scenario_DT!J$12+$F7)-Scenario_DT!J$13)*(1-Scenario_DT!J$14)+Scenario_DT!J$13-Scenario_DT!J$15)*Scenario_DT!J$16 -> 1831.9088 | K7: =((Scenario_DT!K$11*(IF(Scenario_DT!K$18=1,1,1+$D7/Scenario_DT!$C$19)*(1+$E7)^MAX(0,Scenario_DT!K$18-3))*(Scenario_DT!K$12+$F7)-Scenario_DT!K$13)*(1-Scenario_DT!K$14)+Scenario_DT!K$13-Scenario_DT!K$15)*Scenario_DT!K$16 -> 2096.4935 | L7: =((Scenario_DT!L$11*(IF(Scenario_DT!L$18=1,1,1+$D7/Scenario_DT!$C$19)*(1+$E7)^MAX(0,Scenario_DT!L$18-3))*(Scenario_DT!L$12+$F7)-Scenario_DT!L$13)*(1-Scenario_DT!L$14)+Scenario_DT!L$13-Scenario_DT!L$15)*Scenario_DT!L$16 -> 2497.5227 | M7: =((Scenario_DT!M$11*(IF(Scenario_DT!M$18=1,1,1+$D7/Scenario_DT!$C$19)*(1+$E7)^MAX(0,Scenario_DT!M$18-3))*(Scenario_DT!M$12+$F7)-Scenario_DT!M$13)*(1-Scenario_DT!M$14)+Scenario_DT!M$13-Scenario_DT!M$15)*Scenario_DT!M$16 -> 2621.6774 | N7: =((Scenario_DT!N$11*(IF(Scenario_DT!N$18=1,1,1+$D7/Scenario_DT!$C$19)*(1+$E7)^MAX(0,Scenario_DT!N$18-3))*(Scenario_DT!N$12+$F7)-Scenario_DT!N$13)*(1-Scenario_DT!N$14)+Scenario_DT!N$13-Scenario_DT!N$15)*Scenario_DT!N$16 -> 2751.9967 | O7: =((Scenario_DT!O$11*(IF(Scenario_DT!O$18=1,1,1+$D7/Scenario_DT!$C$19)*(1+$E7)^MAX(0,Scenario_DT!O$18-3))*(Scenario_DT!O$12+$F7)-Scenario_DT!O$13)*(1-Scenario_DT!O$14)+Scenario_DT!O$13-Scenario_DT!O$15)*Scenario_DT!O$16 -> 2888.7892 | P7: =((Scenario_DT!P$11*(IF(Scenario_DT!P$18=1,1,1+$D7/Scenario_DT!$C$19)*(1+$E7)^MAX(0,Scenario_DT!P$18-3))*(Scenario_DT!P$12+$F7)-Scenario_DT!P$13)*(1-Scenario_DT!P$14)+Scenario_DT!P$13-Scenario_DT!P$15)*Scenario_DT!P$16 -> 3032.3788 | ... R7: =((Scenario_DT!R$11*(IF(Scenario_DT!R$18=1,1,1+$D7/Scenario_DT!$C$19)*(1+$E7)^MAX(0,Scenario_DT!R$18-3))*(Scenario_DT!R$12+$F7)-Scenario_DT!R$13)*(1-Scenario_DT!R$14)+Scenario_DT!R$13-Scenario_DT!R$15)*Scenario_DT!R$16 -> 3341.3263 | S7: =(Scenario_DT!$R$11*(1+$D7/Scenario_DT!$C$19)*(1+$E7)^7*(Scenario_DT!$R$12+$F7)*(1+MIN(DCF_FCFF!$C$26+$H7,(DCF_FCFF!$C$25+$G7)-0.02))*(1-DCF_FCFF!$C$27)*(1-DCF_FCFF!$C$28)/((DCF_FCFF!$C$25+$G7)-MIN(DCF_FCFF!$C$26+$H7,(DCF_FCFF!$C$25+$G7)-0.02)))*(1+(DCF_FCFF!$C$25+$G7))^(-(Inputs!$C$9+9)) -> 28184.291 | T7: =SUMPRODUCT(I7:R7*(1+(DCF_FCFF!$C$25+$G7))^(-$I$17:$R$17))+S7 -> 44624.773 | U7: =((T7-DCF_FCFF!$C$48)*(1-DCF_FCFF!$C$50)+DCF_FCFF!$C$57+DCF_FCFF!$C$58)/DCF_FCFF!$C$60 -> 331.89843
B8: Bull – GCC demand, rate cuts, tax-regime savings | C8: 0.25 | D8: 0.02 | E8: 0.0075 | F8: 0.01 | G8: -0.005 | H8: 0.005 | I8: =((Scenario_DT!I$11*(IF(Scenario_DT!I$18=1,1,1+$D8/Scenario_DT!$C$19)*(1+$E8)^MAX(0,Scenario_DT!I$18-3))*(Scenario_DT!I$12+$F8)-Scenario_DT!I$13)*(1-Scenario_DT!I$14)+Scenario_DT!I$13-Scenario_DT!I$15)*Scenario_DT!I$16 -> 925.08346 | J8: =((Scenario_DT!J$11*(IF(Scenario_DT!J$18=1,1,1+$D8/Scenario_DT!$C$19)*(1+$E8)^MAX(0,Scenario_DT!J$18-3))*(Scenario_DT!J$12+$F8)-Scenario_DT!J$13)*(1-Scenario_DT!J$14)+Scenario_DT!J$13-Scenario_DT!J$15)*Scenario_DT!J$16 -> 1911.5719 | K8: =((Scenario_DT!K$11*(IF(Scenario_DT!K$18=1,1,1+$D8/Scenario_DT!$C$19)*(1+$E8)^MAX(0,Scenario_DT!K$18-3))*(Scenario_DT!K$12+$F8)-Scenario_DT!K$13)*(1-Scenario_DT!K$14)+Scenario_DT!K$13-Scenario_DT!K$15)*Scenario_DT!K$16 -> 2179.7306 | L8: =((Scenario_DT!L$11*(IF(Scenario_DT!L$18=1,1,1+$D8/Scenario_DT!$C$19)*(1+$E8)^MAX(0,Scenario_DT!L$18-3))*(Scenario_DT!L$12+$F8)-Scenario_DT!L$13)*(1-Scenario_DT!L$14)+Scenario_DT!L$13-Scenario_DT!L$15)*Scenario_DT!L$16 -> 2605.4228 | M8: =((Scenario_DT!M$11*(IF(Scenario_DT!M$18=1,1,1+$D8/Scenario_DT!$C$19)*(1+$E8)^MAX(0,Scenario_DT!M$18-3))*(Scenario_DT!M$12+$F8)-Scenario_DT!M$13)*(1-Scenario_DT!M$14)+Scenario_DT!M$13-Scenario_DT!M$15)*Scenario_DT!M$16 -> 2755.6231 | N8: =((Scenario_DT!N$11*(IF(Scenario_DT!N$18=1,1,1+$D8/Scenario_DT!$C$19)*(1+$E8)^MAX(0,Scenario_DT!N$18-3))*(Scenario_DT!N$12+$F8)-Scenario_DT!N$13)*(1-Scenario_DT!N$14)+Scenario_DT!N$13-Scenario_DT!N$15)*Scenario_DT!N$16 -> 2914.4855 | O8: =((Scenario_DT!O$11*(IF(Scenario_DT!O$18=1,1,1+$D8/Scenario_DT!$C$19)*(1+$E8)^MAX(0,Scenario_DT!O$18-3))*(Scenario_DT!O$12+$F8)-Scenario_DT!O$13)*(1-Scenario_DT!O$14)+Scenario_DT!O$13-Scenario_DT!O$15)*Scenario_DT!O$16 -> 3082.5125 | P8: =((Scenario_DT!P$11*(IF(Scenario_DT!P$18=1,1,1+$D8/Scenario_DT!$C$19)*(1+$E8)^MAX(0,Scenario_DT!P$18-3))*(Scenario_DT!P$12+$F8)-Scenario_DT!P$13)*(1-Scenario_DT!P$14)+Scenario_DT!P$13-Scenario_DT!P$15)*Scenario_DT!P$16 -> 3260.2357 | ... R8: =((Scenario_DT!R$11*(IF(Scenario_DT!R$18=1,1,1+$D8/Scenario_DT!$C$19)*(1+$E8)^MAX(0,Scenario_DT!R$18-3))*(Scenario_DT!R$12+$F8)-Scenario_DT!R$13)*(1-Scenario_DT!R$14)+Scenario_DT!R$13-Scenario_DT!R$15)*Scenario_DT!R$16 -> 3647.0535 | S8: =(Scenario_DT!$R$11*(1+$D8/Scenario_DT!$C$19)*(1+$E8)^7*(Scenario_DT!$R$12+$F8)*(1+MIN(DCF_FCFF!$C$26+$H8,(DCF_FCFF!$C$25+$G8)-0.02))*(1-DCF_FCFF!$C$27)*(1-DCF_FCFF!$C$28)/((DCF_FCFF!$C$25+$G8)-MIN(DCF_FCFF!$C$26+$H8,(DCF_FCFF!$C$25+$G8)-0.02)))*(1+(DCF_FCFF!$C$25+$G8))^(-(Inputs!$C$9+9)) -> 40250.179 | T8: =SUMPRODUCT(I8:R8*(1+(DCF_FCFF!$C$25+$G8))^(-$I$17:$R$17))+S8 -> 58023.3 | U8: =((T8-DCF_FCFF!$C$48)*(1-DCF_FCFF!$C$50)+DCF_FCFF!$C$57+DCF_FCFF!$C$58)/DCF_FCFF!$C$60 -> 460.50779
B10: Base-case arrays used by the engine (linked)
B11: Revenue | I11: =Fin_Proj!I24 -> 3936.7405 | J11: =Fin_Proj!J24 -> 4143.6326 | K11: =Fin_Proj!K24 -> 4352.1901 | L11: =Fin_Proj!L24 -> 4569.7996 | M11: =Fin_Proj!M24 -> 4798.2896 | N11: =Fin_Proj!N24 -> 5038.2041 | O11: =Fin_Proj!O24 -> 5290.1143 | P11: =Fin_Proj!P24 -> 5554.62 | ... R11: =Fin_Proj!R24 -> 6123.9685
B12: EBITDA margin | I12: =Fin_Proj!I30 -> 0.70515719 | J12: =Fin_Proj!J30 -> 0.72536224 | K12: =Fin_Proj!K30 -> 0.73529403 | L12: =Fin_Proj!L30 -> 0.73529403 | M12: =Fin_Proj!M30 -> 0.73529403 | N12: =Fin_Proj!N30 -> 0.73529403 | O12: =Fin_Proj!O30 -> 0.73529403 | P12: =Fin_Proj!P30 -> 0.73529403 | ... R12: =Fin_Proj!R30 -> 0.73529403
B13: Depreciation | I13: =Fin_Proj!I31 -> 580 | J13: =Fin_Proj!J31 -> 589.17722 | K13: =Fin_Proj!K31 -> 602.43319 | L13: =Fin_Proj!L31 -> 608.45752 | M13: =Fin_Proj!M31 -> 614.5421 | N13: =Fin_Proj!N31 -> 620.68752 | O13: =Fin_Proj!O31 -> 626.8944 | P13: =Fin_Proj!P31 -> 633.16334 | ... R13: =Fin_Proj!R31 -> 645.88992
B14: Tax rate | I14: =Fin_Proj!I13 -> 0.24 | J14: =Fin_Proj!J13 -> 0.25 | K14: =Fin_Proj!K13 -> 0.26 | L14: =Fin_Proj!L13 -> 0.2517 | M14: =Fin_Proj!M13 -> 0.2517 | N14: =Fin_Proj!N13 -> 0.2517 | O14: =Fin_Proj!O13 -> 0.2517 | P14: =Fin_Proj!P13 -> 0.2517 | ... R14: =Fin_Proj!R13 -> 0.2517
B15: Capex + increase in NWC | I15: =Fin_Proj!I68+Fin_Proj!I70 -> 315.78192 | J15: =Fin_Proj!J68+Fin_Proj!J70 -> 569.61151 | K15: =Fin_Proj!K68+Fin_Proj!K70 -> 428.24233 | L15: =Fin_Proj!L68+Fin_Proj!L70 -> 170.02364 | M15: =Fin_Proj!M68+Fin_Proj!M70 -> 173.1203 | N15: =Fin_Proj!N68+Fin_Proj!N70 -> 176.35359 | O15: =Fin_Proj!O68+Fin_Proj!O70 -> 179.72952 | P15: =Fin_Proj!P68+Fin_Proj!P70 -> 183.25437 | ... R15: =Fin_Proj!R68+Fin_Proj!R70 -> 190.77732
B16: Fraction of year counted | I16: =DCF_FCFF!I18 -> 0.47123288 | J16: =DCF_FCFF!J18 -> 1 | K16: =DCF_FCFF!K18 -> 1 | L16: =DCF_FCFF!L18 -> 1 | M16: =DCF_FCFF!M18 -> 1 | N16: =DCF_FCFF!N18 -> 1 | O16: =DCF_FCFF!O18 -> 1 | P16: =DCF_FCFF!P18 -> 1 | ... R16: =DCF_FCFF!R18 -> 1
B17: Discount period | I17: =DCF_FCFF!I20 -> 0.23561644 | J17: =DCF_FCFF!J20 -> 0.97123288 | K17: =DCF_FCFF!K20 -> 1.9712329 | L17: =DCF_FCFF!L20 -> 2.9712329 | M17: =DCF_FCFF!M20 -> 3.9712329 | N17: =DCF_FCFF!N20 -> 4.9712329 | O17: =DCF_FCFF!O20 -> 5.9712329 | P17: =DCF_FCFF!P20 -> 6.9712329 | ... R17: =DCF_FCFF!R20 -> 8.9712329
B18: Year index | I18: =DCF_FCFF!I5 -> 1 | J18: =DCF_FCFF!J5 -> 2 | K18: =DCF_FCFF!K5 -> 3 | L18: =DCF_FCFF!L5 -> 4 | M18: =DCF_FCFF!M5 -> 5 | N18: =DCF_FCFF!N5 -> 6 | O18: =DCF_FCFF!O5 -> 7 | P18: =DCF_FCFF!P5 -> 8 | ... R18: =DCF_FCFF!R5 -> 10
B19: Portfolio occupancy FY29E (base for occupancy shock) | C19: =Rev_Build!$Q$67 -> 0.94072732
B21: Probability-weighted value per unit (Rs) | U21: =SUMPRODUCT(C6:C8,U6:U8) -> 336.87227
B22: Check: probabilities sum to 100% | U22: =SUM(C6:C8) -> 1
B23: Expected upside vs current price | U23: =U21/Inputs!$C$10-1 -> 0.024550708
B24: Standard deviation of scenario values | U24: =SQRT(SUMPRODUCT(C6:C8,(U6:U8-U21)^2)) -> 84.05377
B26: 2. Decision tree A – hedge the floating-rate debt? (90% of debt is floating; RBI hiked 25bp on 7-Oct-2026)
B27: Average gross debt FY28E (Rs cr) | C27: =Fin_Proj!J54 -> 15284.783
B28: Floating-rate share of debt | C28: 0.9
B29: Share of floating debt fixed under hedge | C29: 0.5
B30: Hedge premium over floating (p.a.) | C30: 0.004
B31: Cost of equity | C31: =WACC!$C$26 -> 0.10727921
B32: Stable growth (DDM) | C32: =DDM_NDCF!C14 -> 0.04
B34: Rate state (12-month move) | C34: Probability | D34: Δ rate | E34: Stay floating: Δ interest (Rs cr) | F34: Hedge: Δ interest (Rs cr) | G34: Stay: value / unit (Rs) | H34: Hedge: value / unit (Rs)
B35: Further hikes | C35: 0.35 | D35: 0.01 | E35: =$C$27*$C$28*D35 -> 137.56305 | F35: =$C$27*$C$28*((1-$C$29)*D35+$C$29*$C$30) -> 96.294132 | G35: =-E35*(1-Inputs!$C$56)*(1-Inputs!$C$42*Fin_Proj!$J$14)/Inputs!$C$11/($C$31-$C$32) -> -18.833816 | H35: =-F35*(1-Inputs!$C$56)*(1-Inputs!$C$42*Fin_Proj!$J$14)/Inputs!$C$11/($C$31-$C$32) -> -13.183671
B36: Rates flat | C36: 0.45 | D36: 0 | E36: =$C$27*$C$28*D36 -> 0 | F36: =$C$27*$C$28*((1-$C$29)*D36+$C$29*$C$30) -> 27.512609 | G36: =-E36*(1-Inputs!$C$56)*(1-Inputs!$C$42*Fin_Proj!$J$14)/Inputs!$C$11/($C$31-$C$32) -> 0 | H36: =-F36*(1-Inputs!$C$56)*(1-Inputs!$C$42*Fin_Proj!$J$14)/Inputs!$C$11/($C$31-$C$32) -> -3.7667632
B37: Cuts | C37: 0.2 | D37: -0.01 | E37: =$C$27*$C$28*D37 -> -137.56305 | F37: =$C$27*$C$28*((1-$C$29)*D37+$C$29*$C$30) -> -41.268914 | G37: =-E37*(1-Inputs!$C$56)*(1-Inputs!$C$42*Fin_Proj!$J$14)/Inputs!$C$11/($C$31-$C$32) -> 18.833816 | H37: =-F37*(1-Inputs!$C$56)*(1-Inputs!$C$42*Fin_Proj!$J$14)/Inputs!$C$11/($C$31-$C$32) -> 5.6501447
B38: Expected value per unit (Rs) | G38: =SUMPRODUCT($C$35:$C$37,G35:G37) -> -2.8250724 | H38: =SUMPRODUCT($C$35:$C$37,H35:H37) -> -5.1792993
B39: Preferred branch | G39: =IF(H38>G38,"Hedge (fix part of floating debt)","Stay floating") -> Stay floating
B40: Hedging pays only if the hike probability is high enough to outweigh the premium; flat-rate state shows the pure cost of insurance.
B42: 3. Decision tree B – deploy the Rs 4,300 cr 'dry powder' (35% LTV headroom after BKC)?
B43: Deployable capital (Rs cr) | C43: 4300 | D43: Mgmt: ~Rs 43 bn dry powder at 35% LTV (Q1 FY27 call)
B44: Transaction costs (% of price) | C44: 0.01
B45: Cash yield forgone / earned on idle cash | C45: 0.06
B47: Acquisition outcome (value ÷ price paid) | C47: Probability | D47: Value / price | E47: Acquire: Δ value (Rs cr)
B48: Priced below fair value (sponsor discount, lease-up) | C48: 0.3 | D48: 1.06 | E48: =$C$43*(D48-1-$C$44) -> 215
B49: Fairly priced | C49: 0.5 | D49: 1.02 | E49: =$C$43*(D49-1-$C$44) -> 43
B50: Overpaid / lease-up misses | C50: 0.2 | D50: 0.95 | E50: =$C$43*(D50-1-$C$44) -> -258
B52: Decision branch | C52: Expected Δ value (Rs cr) | D52: Value / unit (Rs)
B53: Acquire | C53: =SUMPRODUCT(C48:C50,E48:E50) -> 34.4 | D53: =C53*(1-DCF_FCFF!$C$50)/Inputs!$C$11 -> 0.33019764
B54: Prepay debt | C54: =C43*(WACC!$C$30-C45)*(1-Inputs!$C$42)/WACC!$C$26 -> 449.90404 | D54: =C54*(1-DCF_FCFF!$C$50)/Inputs!$C$11 -> 4.3185247
B55: Hold cash | C55: 0 | D55: =C55*(1-DCF_FCFF!$C$50)/Inputs!$C$11 -> 0
B56: Preferred branch | C56: =INDEX(B53:B55,MATCH(MAX(D53:D55),D53:D55,0)) -> Prepay debt
B57: Acquisitions only add value when bought at a discount to intrinsic value – the 3.6% discount achieved on BKC is the real source of accretion.

Sheet Monte_Carlo
B1: MONTE CARLO SIMULATION – 500 trials of the compact FCFF engine (BAV: simulations)
B2: Uniform draws are stored as inputs (seed 42) so results are reproducible; replace columns C:G with =RAND() and paste values to resample
B4: 1. Distribution assumptions (standard deviations of shocks)
B5: Occupancy shock, FY28+ (pp) | C5: 0.02
B6: Revenue growth shock FY30+ (p.a.) | C6: 0.008
B7: EBITDA margin shock | C7: 0.012
B8: WACC shock | C8: 0.006
B9: Terminal growth shock | C9: 0.004
B10: Correlation: occupancy ↔ revenue growth | C10: 0.5
B12: 2. Results (value per unit, Rs)
B13: Mean | C13: =AVERAGE($AD$32:$AD$531) -> 342.99344
B14: Median | C14: =MEDIAN($AD$32:$AD$531) -> 338.01146
B15: Standard deviation | C15: =STDEV($AD$32:$AD$531) -> 64.018733
B16: 5th percentile | C16: =PERCENTILE($AD$32:$AD$531,0.05) -> 249.31772
B17: 10th percentile | C17: =PERCENTILE($AD$32:$AD$531,0.1) -> 266.63161
B18: 25th percentile | C18: =PERCENTILE($AD$32:$AD$531,0.25) -> 298.02315
B19: 75th percentile | C19: =PERCENTILE($AD$32:$AD$531,0.75) -> 379.10064
B20: 90th percentile | C20: =PERCENTILE($AD$32:$AD$531,0.9) -> 428.73443
B21: 95th percentile | C21: =PERCENTILE($AD$32:$AD$531,0.95) -> 452.00575
B22: Probability value > current price | C22: =COUNTIF($AD$32:$AD$531,">"&Inputs!$C$10)/COUNT($AD$32:$AD$531) -> 0.548
B23: Probability value > reported NAV | C23: =COUNTIF($AD$32:$AD$531,">"&Inputs!$C$13)/COUNT($AD$32:$AD$531) -> 0.226
B24: Trials | C24: =COUNT($AD$32:$AD$531) -> 500
B26: Check: zero-shock row vs DCF value | C26: =AD31-DCF_FCFF!$C$61 -> 0
B29: 3. Simulation table
B30: Trial | C30: U1 occ | D30: U2 growth | E30: U3 margin | F30: U4 WACC | G30: U5 g | H30: z1 | I30: z2 | J30: z3 | K30: z4 | L30: z5 | M30: Δ occ | N30: Δ growth | O30: Δ margin | P30: Δ WACC | Q30: Δ g | R30: FCFF FY27E | S30: FCFF FY28E | T30: FCFF FY29E | U30: FCFF FY30E | V30: FCFF FY31E | W30: FCFF FY32E | X30: FCFF FY33E | Y30: FCFF FY34E | Z30: FCFF FY35E | AA30: FCFF FY36E | AB30: PV of TV | AC30: EV (Rs cr) | AD30: Value / unit | AF30: Histogram bin (Rs/unit) | AG30: Trials
B31: Base (zero shock) | C31: 0.5 | D31: 0.5 | E31: 0.5 | F31: 0.5 | G31: 0.5 | H31: =NORMSINV(C31) -> 0 | I31: =NORMSINV(D31) -> 0 | J31: =NORMSINV(E31) -> 0 | K31: =NORMSINV(F31) -> 0 | L31: =NORMSINV(G31) -> 0 | M31: =H31*$C$5 -> 0 | N31: =($C$10*H31+SQRT(1-$C$10^2)*I31)*$C$6 -> 0 | O31: =J31*$C$7 -> 0 | P31: =K31*$C$8 -> 0 | Q31: =L31*$C$9 -> 0 | R31: =((Scenario_DT!I$11*(IF(Scenario_DT!I$18=1,1,1+$M31/Scenario_DT!$C$19)*(1+$N31)^MAX(0,Scenario_DT!I$18-3))*(Scenario_DT!I$12+$O31)-Scenario_DT!I$13)*(1-Scenario_DT!I$14)+Scenario_DT!I$13-Scenario_DT!I$15)*Scenario_DT!I$16 -> 910.98454 | S31: =((Scenario_DT!J$11*(IF(Scenario_DT!J$18=1,1,1+$M31/Scenario_DT!$C$19)*(1+$N31)^MAX(0,Scenario_DT!J$18-3))*(Scenario_DT!J$12+$O31)-Scenario_DT!J$13)*(1-Scenario_DT!J$14)+Scenario_DT!J$13-Scenario_DT!J$15)*Scenario_DT!J$16 -> 1831.9088 | T31: =((Scenario_DT!K$11*(IF(Scenario_DT!K$18=1,1,1+$M31/Scenario_DT!$C$19)*(1+$N31)^MAX(0,Scenario_DT!K$18-3))*(Scenario_DT!K$12+$O31)-Scenario_DT!K$13)*(1-Scenario_DT!K$14)+Scenario_DT!K$13-Scenario_DT!K$15)*Scenario_DT!K$16 -> 2096.4935 | U31: =((Scenario_DT!L$11*(IF(Scenario_DT!L$18=1,1,1+$M31/Scenario_DT!$C$19)*(1+$N31)^MAX(0,Scenario_DT!L$18-3))*(Scenario_DT!L$12+$O31)-Scenario_DT!L$13)*(1-Scenario_DT!L$14)+Scenario_DT!L$13-Scenario_DT!L$15)*Scenario_DT!L$16 -> 2497.5227 | V31: =((Scenario_DT!M$11*(IF(Scenario_DT!M$18=1,1,1+$M31/Scenario_DT!$C$19)*(1+$N31)^MAX(0,Scenario_DT!M$18-3))*(Scenario_DT!M$12+$O31)-Scenario_DT!M$13)*(1-Scenario_DT!M$14)+Scenario_DT!M$13-Scenario_DT!M$15)*Scenario_DT!M$16 -> 2621.6774 | W31: =((Scenario_DT!N$11*(IF(Scenario_DT!N$18=1,1,1+$M31/Scenario_DT!$C$19)*(1+$N31)^MAX(0,Scenario_DT!N$18-3))*(Scenario_DT!N$12+$O31)-Scenario_DT!N$13)*(1-Scenario_DT!N$14)+Scenario_DT!N$13-Scenario_DT!N$15)*Scenario_DT!N$16 -> 2751.9967 | X31: =((Scenario_DT!O$11*(IF(Scenario_DT!O$18=1,1,1+$M31/Scenario_DT!$C$19)*(1+$N31)^MAX(0,Scenario_DT!O$18-3))*(Scenario_DT!O$12+$O31)-Scenario_DT!O$13)*(1-Scenario_DT!O$14)+Scenario_DT!O$13-Scenario_DT!O$15)*Scenario_DT!O$16 -> 2888.7892 | Y31: =((Scenario_DT!P$11*(IF(Scenario_DT!P$18=1,1,1+$M31/Scenario_DT!$C$19)*(1+$N31)^MAX(0,Scenario_DT!P$18-3))*(Scenario_DT!P$12+$O31)-Scenario_DT!P$13)*(1-Scenario_DT!P$14)+Scenario_DT!P$13-Scenario_DT!P$15)*Scenario_DT!P$16 -> 3032.3788 | ... AA31: =((Scenario_DT!R$11*(IF(Scenario_DT!R$18=1,1,1+$M31/Scenario_DT!$C$19)*(1+$N31)^MAX(0,Scenario_DT!R$18-3))*(Scenario_DT!R$12+$O31)-Scenario_DT!R$13)*(1-Scenario_DT!R$14)+Scenario_DT!R$13-Scenario_DT!R$15)*Scenario_DT!R$16 -> 3341.3263 | AB31: =(Scenario_DT!$R$11*(1+$M31/Scenario_DT!$C$19)*(1+$N31)^7*(Scenario_DT!$R$12+$O31)*(1+MIN(DCF_FCFF!$C$26+$Q31,(DCF_FCFF!$C$25+$P31)-0.02))*(1-DCF_FCFF!$C$27)*(1-DCF_FCFF!$C$28)/((DCF_FCFF!$C$25+$P31)-MIN(DCF_FCFF!$C$26+$Q31,(DCF_FCFF!$C$25+$P31)-0.02)))*(1+(DCF_FCFF!$C$25+$P31))^(-(Inputs!$C$9+9)) -> 28184.291 | AC31: =SUMPRODUCT(R31:AA31*(1+(DCF_FCFF!$C$25+$P31))^(-Scenario_DT!$I$17:$R$17))+AB31 -> 44624.773 | AD31: =((AC31-DCF_FCFF!$C$48)*(1-DCF_FCFF!$C$50)+DCF_FCFF!$C$57+DCF_FCFF!$C$58)/DCF_FCFF!$C$60 -> 331.89843 | AF31: 100 | AG31: =COUNTIFS($AD$32:$AD$531,">="&AF31,$AD$32:$AD$531,"<"&AF31+25) -> 0
B32: 1 | C32: 0.77395605 | D32: 0.43887844 | E32: 0.85859792 | F32: 0.69736803 | G32: 0.094177348 | H32: =NORMSINV(C32) -> 0.75193873 | I32: =NORMSINV(D32) -> -0.15381339 | J32: =NORMSINV(E32) -> 1.0740413 | K32: =NORMSINV(F32) -> 0.5168456 | L32: =NORMSINV(G32) -> -1.315462 | M32: =H32*$C$5 -> 0.015038775 | N32: =($C$10*H32+SQRT(1-$C$10^2)*I32)*$C$6 -> 0.0019421045 | O32: =J32*$C$7 -> 0.012888496 | P32: =K32*$C$8 -> 0.0031010736 | Q32: =L32*$C$9 -> -0.0052618478 | R32: =((Scenario_DT!I$11*(IF(Scenario_DT!I$18=1,1,1+$M32/Scenario_DT!$C$19)*(1+$N32)^MAX(0,Scenario_DT!I$18-3))*(Scenario_DT!I$12+$O32)-Scenario_DT!I$13)*(1-Scenario_DT!I$14)+Scenario_DT!I$13-Scenario_DT!I$15)*Scenario_DT!I$16 -> 929.15593 | S32: =((Scenario_DT!J$11*(IF(Scenario_DT!J$18=1,1,1+$M32/Scenario_DT!$C$19)*(1+$N32)^MAX(0,Scenario_DT!J$18-3))*(Scenario_DT!J$12+$O32)-Scenario_DT!J$13)*(1-Scenario_DT!J$14)+Scenario_DT!J$13-Scenario_DT!J$15)*Scenario_DT!J$16 -> 1908.6398 | T32: =((Scenario_DT!K$11*(IF(Scenario_DT!K$18=1,1,1+$M32/Scenario_DT!$C$19)*(1+$N32)^MAX(0,Scenario_DT!K$18-3))*(Scenario_DT!K$12+$O32)-Scenario_DT!K$13)*(1-Scenario_DT!K$14)+Scenario_DT!K$13-Scenario_DT!K$15)*Scenario_DT!K$16 -> 2176.5233 | U32: =((Scenario_DT!L$11*(IF(Scenario_DT!L$18=1,1,1+$M32/Scenario_DT!$C$19)*(1+$N32)^MAX(0,Scenario_DT!L$18-3))*(Scenario_DT!L$12+$O32)-Scenario_DT!L$13)*(1-Scenario_DT!L$14)+Scenario_DT!L$13-Scenario_DT!L$15)*Scenario_DT!L$16 -> 2587.5447 | V32: =((Scenario_DT!M$11*(IF(Scenario_DT!M$18=1,1,1+$M32/Scenario_DT!$C$19)*(1+$N32)^MAX(0,Scenario_DT!M$18-3))*(Scenario_DT!M$12+$O32)-Scenario_DT!M$13)*(1-Scenario_DT!M$14)+Scenario_DT!M$13-Scenario_DT!M$15)*Scenario_DT!M$16 -> 2721.5115 | W32: =((Scenario_DT!N$11*(IF(Scenario_DT!N$18=1,1,1+$M32/Scenario_DT!$C$19)*(1+$N32)^MAX(0,Scenario_DT!N$18-3))*(Scenario_DT!N$12+$O32)-Scenario_DT!N$13)*(1-Scenario_DT!N$14)+Scenario_DT!N$13-Scenario_DT!N$15)*Scenario_DT!N$16 -> 2862.4099 | X32: =((Scenario_DT!O$11*(IF(Scenario_DT!O$18=1,1,1+$M32/Scenario_DT!$C$19)*(1+$N32)^MAX(0,Scenario_DT!O$18-3))*(Scenario_DT!O$12+$O32)-Scenario_DT!O$13)*(1-Scenario_DT!O$14)+Scenario_DT!O$13-Scenario_DT!O$15)*Scenario_DT!O$16 -> 3010.6012 | Y32: =((Scenario_DT!P$11*(IF(Scenario_DT!P$18=1,1,1+$M32/Scenario_DT!$C$19)*(1+$N32)^MAX(0,Scenario_DT!P$18-3))*(Scenario_DT!P$12+$O32)-Scenario_DT!P$13)*(1-Scenario_DT!P$14)+Scenario_DT!P$13-Scenario_DT!P$15)*Scenario_DT!P$16 -> 3166.4653 | ... AA32: =((Scenario_DT!R$11*(IF(Scenario_DT!R$18=1,1,1+$M32/Scenario_DT!$C$19)*(1+$N32)^MAX(0,Scenario_DT!R$18-3))*(Scenario_DT!R$12+$O32)-Scenario_DT!R$13)*(1-Scenario_DT!R$14)+Scenario_DT!R$13-Scenario_DT!R$15)*Scenario_DT!R$16 -> 3502.8322 | AB32: =(Scenario_DT!$R$11*(1+$M32/Scenario_DT!$C$19)*(1+$N32)^7*(Scenario_DT!$R$12+$O32)*(1+MIN(DCF_FCFF!$C$26+$Q32,(DCF_FCFF!$C$25+$P32)-0.02))*(1-DCF_FCFF!$C$27)*(1-DCF_FCFF!$C$28)/((DCF_FCFF!$C$25+$P32)-MIN(DCF_FCFF!$C$26+$Q32,(DCF_FCFF!$C$25+$P32)-0.02)))*(1+(DCF_FCFF!$C$25+$P32))^(-(Inputs!$C$9+9)) -> 24534.631 | AC32: =SUMPRODUCT(R32:AA32*(1+(DCF_FCFF!$C$25+$P32))^(-Scenario_DT!$I$17:$R$17))+AB32 -> 41415.027 | AD32: =((AC32-DCF_FCFF!$C$48)*(1-DCF_FCFF!$C$50)+DCF_FCFF!$C$57+DCF_FCFF!$C$58)/DCF_FCFF!$C$60 -> 301.08883 | AF32: 125 | AG32: =COUNTIFS($AD$32:$AD$531,">="&AF32,$AD$32:$AD$531,"<"&AF32+25) -> 0
B33: 2 | C33: 0.97562235 | D33: 0.7611397 | E33: 0.78606431 | F33: 0.12811363 | G33: 0.45038594 | H33: =NORMSINV(C33) -> 1.9707254 | I33: =NORMSINV(D33) -> 0.70997346 | J33: =NORMSINV(E33) -> 0.79283941 | K33: =NORMSINV(F33) -> -1.1353534 | L33: =NORMSINV(G33) -> -0.12468634 | M33: =H33*$C$5 -> 0.039414507 | N33: =($C$10*H33+SQRT(1-$C$10^2)*I33)*$C$6 -> 0.012801742 | O33: =J33*$C$7 -> 0.009514073 | P33: =K33*$C$8 -> -0.0068121206 | Q33: =L33*$C$9 -> -0.00049874534 | R33: =((Scenario_DT!I$11*(IF(Scenario_DT!I$18=1,1,1+$M33/Scenario_DT!$C$19)*(1+$N33)^MAX(0,Scenario_DT!I$18-3))*(Scenario_DT!I$12+$O33)-Scenario_DT!I$13)*(1-Scenario_DT!I$14)+Scenario_DT!I$13-Scenario_DT!I$15)*Scenario_DT!I$16 -> 924.39836 | S33: =((Scenario_DT!J$11*(IF(Scenario_DT!J$18=1,1,1+$M33/Scenario_DT!$C$19)*(1+$N33)^MAX(0,Scenario_DT!J$18-3))*(Scenario_DT!J$12+$O33)-Scenario_DT!J$13)*(1-Scenario_DT!J$14)+Scenario_DT!J$13-Scenario_DT!J$15)*Scenario_DT!J$16 -> 1957.162 | T33: =((Scenario_DT!K$11*(IF(Scenario_DT!K$18=1,1,1+$M33/Scenario_DT!$C$19)*(1+$N33)^MAX(0,Scenario_DT!K$18-3))*(Scenario_DT!K$12+$O33)-Scenario_DT!K$13)*(1-Scenario_DT!K$14)+Scenario_DT!K$13-Scenario_DT!K$15)*Scenario_DT!K$16 -> 2227.6371 | U33: =((Scenario_DT!L$11*(IF(Scenario_DT!L$18=1,1,1+$M33/Scenario_DT!$C$19)*(1+$N33)^MAX(0,Scenario_DT!L$18-3))*(Scenario_DT!L$12+$O33)-Scenario_DT!L$13)*(1-Scenario_DT!L$14)+Scenario_DT!L$13-Scenario_DT!L$15)*Scenario_DT!L$16 -> 2670.7392 | V33: =((Scenario_DT!M$11*(IF(Scenario_DT!M$18=1,1,1+$M33/Scenario_DT!$C$19)*(1+$N33)^MAX(0,Scenario_DT!M$18-3))*(Scenario_DT!M$12+$O33)-Scenario_DT!M$13)*(1-Scenario_DT!M$14)+Scenario_DT!M$13-Scenario_DT!M$15)*Scenario_DT!M$16 -> 2839.6811 | W33: =((Scenario_DT!N$11*(IF(Scenario_DT!N$18=1,1,1+$M33/Scenario_DT!$C$19)*(1+$N33)^MAX(0,Scenario_DT!N$18-3))*(Scenario_DT!N$12+$O33)-Scenario_DT!N$13)*(1-Scenario_DT!N$14)+Scenario_DT!N$13-Scenario_DT!N$15)*Scenario_DT!N$16 -> 3019.3191 | X33: =((Scenario_DT!O$11*(IF(Scenario_DT!O$18=1,1,1+$M33/Scenario_DT!$C$19)*(1+$N33)^MAX(0,Scenario_DT!O$18-3))*(Scenario_DT!O$12+$O33)-Scenario_DT!O$13)*(1-Scenario_DT!O$14)+Scenario_DT!O$13-Scenario_DT!O$15)*Scenario_DT!O$16 -> 3210.3334 | Y33: =((Scenario_DT!P$11*(IF(Scenario_DT!P$18=1,1,1+$M33/Scenario_DT!$C$19)*(1+$N33)^MAX(0,Scenario_DT!P$18-3))*(Scenario_DT!P$12+$O33)-Scenario_DT!P$13)*(1-Scenario_DT!P$14)+Scenario_DT!P$13-Scenario_DT!P$15)*Scenario_DT!P$16 -> 3413.4478 | ... AA33: =((Scenario_DT!R$11*(IF(Scenario_DT!R$18=1,1,1+$M33/Scenario_DT!$C$19)*(1+$N33)^MAX(0,Scenario_DT!R$18-3))*(Scenario_DT!R$12+$O33)-Scenario_DT!R$13)*(1-Scenario_DT!R$14)+Scenario_DT!R$13-Scenario_DT!R$15)*Scenario_DT!R$16 -> 3859.1046 | AB33: =(Scenario_DT!$R$11*(1+$M33/Scenario_DT!$C$19)*(1+$N33)^7*(Scenario_DT!$R$12+$O33)*(1+MIN(DCF_FCFF!$C$26+$Q33,(DCF_FCFF!$C$25+$P33)-0.02))*(1-DCF_FCFF!$C$27)*(1-DCF_FCFF!$C$28)/((DCF_FCFF!$C$25+$P33)-MIN(DCF_FCFF!$C$26+$Q33,(DCF_FCFF!$C$25+$P33)-0.02)))*(1+(DCF_FCFF!$C$25+$P33))^(-(Inputs!$C$9+9)) -> 39426.037 | AC33: =SUMPRODUCT(R33:AA33*(1+(DCF_FCFF!$C$25+$P33))^(-Scenario_DT!$I$17:$R$17))+AB33 -> 57969.84 | AD33: =((AC33-DCF_FCFF!$C$48)*(1-DCF_FCFF!$C$50)+DCF_FCFF!$C$57+DCF_FCFF!$C$58)/DCF_FCFF!$C$60 -> 459.99465 | AF33: 150 | AG33: =COUNTIFS($AD$32:$AD$531,">="&AF33,$AD$32:$AD$531,"<"&AF33+25) -> 0
B34: 3 | C34: 0.37079802 | D34: 0.92676499 | E34: 0.64386512 | F34: 0.82276161 | G34: 0.4434142 | H34: =NORMSINV(C34) -> -0.3297405 | I34: =NORMSINV(D34) -> 1.4521136 | J34: =NORMSINV(E34) -> 0.36880945 | K34: =NORMSINV(F34) -> 0.92594075 | L34: =NORMSINV(G34) -> -0.14231855 | M34: =H34*$C$5 -> -0.00659481 | N34: =($C$10*H34+SQRT(1-$C$10^2)*I34)*$C$6 -> 0.0087415761 | O34: =J34*$C$7 -> 0.0044257134 | P34: =K34*$C$8 -> 0.0055556445 | Q34: =L34*$C$9 -> -0.00056927419 | R34: =((Scenario_DT!I$11*(IF(Scenario_DT!I$18=1,1,1+$M34/Scenario_DT!$C$19)*(1+$N34)^MAX(0,Scenario_DT!I$18-3))*(Scenario_DT!I$12+$O34)-Scenario_DT!I$13)*(1-Scenario_DT!I$14)+Scenario_DT!I$13-Scenario_DT!I$15)*Scenario_DT!I$16 -> 917.22432 | S34: =((Scenario_DT!J$11*(IF(Scenario_DT!J$18=1,1,1+$M34/Scenario_DT!$C$19)*(1+$N34)^MAX(0,Scenario_DT!J$18-3))*(Scenario_DT!J$12+$O34)-Scenario_DT!J$13)*(1-Scenario_DT!J$14)+Scenario_DT!J$13-Scenario_DT!J$15)*Scenario_DT!J$16 -> 1829.7634 | T34: =((Scenario_DT!K$11*(IF(Scenario_DT!K$18=1,1,1+$M34/Scenario_DT!$C$19)*(1+$N34)^MAX(0,Scenario_DT!K$18-3))*(Scenario_DT!K$12+$O34)-Scenario_DT!K$13)*(1-Scenario_DT!K$14)+Scenario_DT!K$13-Scenario_DT!K$15)*Scenario_DT!K$16 -> 2094.0459 | U34: =((Scenario_DT!L$11*(IF(Scenario_DT!L$18=1,1,1+$M34/Scenario_DT!$C$19)*(1+$N34)^MAX(0,Scenario_DT!L$18-3))*(Scenario_DT!L$12+$O34)-Scenario_DT!L$13)*(1-Scenario_DT!L$14)+Scenario_DT!L$13-Scenario_DT!L$15)*Scenario_DT!L$16 -> 2516.881 | V34: =((Scenario_DT!M$11*(IF(Scenario_DT!M$18=1,1,1+$M34/Scenario_DT!$C$19)*(1+$N34)^MAX(0,Scenario_DT!M$18-3))*(Scenario_DT!M$12+$O34)-Scenario_DT!M$13)*(1-Scenario_DT!M$14)+Scenario_DT!M$13-Scenario_DT!M$15)*Scenario_DT!M$16 -> 2665.2601 | W34: =((Scenario_DT!N$11*(IF(Scenario_DT!N$18=1,1,1+$M34/Scenario_DT!$C$19)*(1+$N34)^MAX(0,Scenario_DT!N$18-3))*(Scenario_DT!N$12+$O34)-Scenario_DT!N$13)*(1-Scenario_DT!N$14)+Scenario_DT!N$13-Scenario_DT!N$15)*Scenario_DT!N$16 -> 2822.3913 | X34: =((Scenario_DT!O$11*(IF(Scenario_DT!O$18=1,1,1+$M34/Scenario_DT!$C$19)*(1+$N34)^MAX(0,Scenario_DT!O$18-3))*(Scenario_DT!O$12+$O34)-Scenario_DT!O$13)*(1-Scenario_DT!O$14)+Scenario_DT!O$13-Scenario_DT!O$15)*Scenario_DT!O$16 -> 2988.794 | Y34: =((Scenario_DT!P$11*(IF(Scenario_DT!P$18=1,1,1+$M34/Scenario_DT!$C$19)*(1+$N34)^MAX(0,Scenario_DT!P$18-3))*(Scenario_DT!P$12+$O34)-Scenario_DT!P$13)*(1-Scenario_DT!P$14)+Scenario_DT!P$13-Scenario_DT!P$15)*Scenario_DT!P$16 -> 3165.0183 | ... AA34: =((Scenario_DT!R$11*(IF(Scenario_DT!R$18=1,1,1+$M34/Scenario_DT!$C$19)*(1+$N34)^MAX(0,Scenario_DT!R$18-3))*(Scenario_DT!R$12+$O34)-Scenario_DT!R$13)*(1-Scenario_DT!R$14)+Scenario_DT!R$13-Scenario_DT!R$15)*Scenario_DT!R$16 -> 3549.2968 | AB34: =(Scenario_DT!$R$11*(1+$M34/Scenario_DT!$C$19)*(1+$N34)^7*(Scenario_DT!$R$12+$O34)*(1+MIN(DCF_FCFF!$C$26+$Q34,(DCF_FCFF!$C$25+$P34)-0.02))*(1-DCF_FCFF!$C$27)*(1-DCF_FCFF!$C$28)/((DCF_FCFF!$C$25+$P34)-MIN(DCF_FCFF!$C$26+$Q34,(DCF_FCFF!$C$25+$P34)-0.02)))*(1+(DCF_FCFF!$C$25+$P34))^(-(Inputs!$C$9+9)) -> 25413.448 | AC34: =SUMPRODUCT(R34:AA34*(1+(DCF_FCFF!$C$25+$P34))^(-Scenario_DT!$I$17:$R$17))+AB34 -> 41867.335 | AD34: =((AC34-DCF_FCFF!$C$48)*(1-DCF_FCFF!$C$50)+DCF_FCFF!$C$57+DCF_FCFF!$C$58)/DCF_FCFF!$C$60 -> 305.43043 | AF34: 175 | AG34: =COUNTIFS($AD$32:$AD$531,">="&AF34,$AD$32:$AD$531,"<"&AF34+25) -> 1
B35: 4 | C35: 0.22723872 | D35: 0.55458479 | E35: 0.063817256 | F35: 0.82763117 | G35: 0.6316644 | H35: =NORMSINV(C35) -> -0.74797134 | I35: =NORMSINV(D35) -> 0.1372535 | J35: =NORMSINV(E35) -> -1.5234966 | K35: =NORMSINV(F35) -> 0.9448457 | L35: =NORMSINV(G35) -> 0.33626479 | M35: =H35*$C$5 -> -0.014959427 | N35: =($C$10*H35+SQRT(1-$C$10^2)*I35)*$C$6 -> -0.0020409652 | O35: =J35*$C$7 -> -0.018281959 | P35: =K35*$C$8 -> 0.0056690742 | Q35: =L35*$C$9 -> 0.0013450591 | R35: =((Scenario_DT!I$11*(IF(Scenario_DT!I$18=1,1,1+$M35/Scenario_DT!$C$19)*(1+$N35)^MAX(0,Scenario_DT!I$18-3))*(Scenario_DT!I$12+$O35)-Scenario_DT!I$13)*(1-Scenario_DT!I$14)+Scenario_DT!I$13-Scenario_DT!I$15)*Scenario_DT!I$16 -> 885.20894 | S35: =((Scenario_DT!J$11*(IF(Scenario_DT!J$18=1,1,1+$M35/Scenario_DT!$C$19)*(1+$N35)^MAX(0,Scenario_DT!J$18-3))*(Scenario_DT!J$12+$O35)-Scenario_DT!J$13)*(1-Scenario_DT!J$14)+Scenario_DT!J$13-Scenario_DT!J$15)*Scenario_DT!J$16 -> 1740.1503 | T35: =((Scenario_DT!K$11*(IF(Scenario_DT!K$18=1,1,1+$M35/Scenario_DT!$C$19)*(1+$N35)^MAX(0,Scenario_DT!K$18-3))*(Scenario_DT!K$12+$O35)-Scenario_DT!K$13)*(1-Scenario_DT!K$14)+Scenario_DT!K$13-Scenario_DT!K$15)*Scenario_DT!K$16 -> 2000.893 | U35: =((Scenario_DT!L$11*(IF(Scenario_DT!L$18=1,1,1+$M35/Scenario_DT!$C$19)*(1+$N35)^MAX(0,Scenario_DT!L$18-3))*(Scenario_DT!L$12+$O35)-Scenario_DT!L$13)*(1-Scenario_DT!L$14)+Scenario_DT!L$13-Scenario_DT!L$15)*Scenario_DT!L$16 -> 2391.0916 | V35: =((Scenario_DT!M$11*(IF(Scenario_DT!M$18=1,1,1+$M35/Scenario_DT!$C$19)*(1+$N35)^MAX(0,Scenario_DT!M$18-3))*(Scenario_DT!M$12+$O35)-Scenario_DT!M$13)*(1-Scenario_DT!M$14)+Scenario_DT!M$13-Scenario_DT!M$15)*Scenario_DT!M$16 -> 2504.7645 | W35: =((Scenario_DT!N$11*(IF(Scenario_DT!N$18=1,1,1+$M35/Scenario_DT!$C$19)*(1+$N35)^MAX(0,Scenario_DT!N$18-3))*(Scenario_DT!N$12+$O35)-Scenario_DT!N$13)*(1-Scenario_DT!N$14)+Scenario_DT!N$13-Scenario_DT!N$15)*Scenario_DT!N$16 -> 2623.8309 | X35: =((Scenario_DT!O$11*(IF(Scenario_DT!O$18=1,1,1+$M35/Scenario_DT!$C$19)*(1+$N35)^MAX(0,Scenario_DT!O$18-3))*(Scenario_DT!O$12+$O35)-Scenario_DT!O$13)*(1-Scenario_DT!O$14)+Scenario_DT!O$13-Scenario_DT!O$15)*Scenario_DT!O$16 -> 2748.5491 | Y35: =((Scenario_DT!P$11*(IF(Scenario_DT!P$18=1,1,1+$M35/Scenario_DT!$C$19)*(1+$N35)^MAX(0,Scenario_DT!P$18-3))*(Scenario_DT!P$12+$O35)-Scenario_DT!P$13)*(1-Scenario_DT!P$14)+Scenario_DT!P$13-Scenario_DT!P$15)*Scenario_DT!P$16 -> 2879.1894 | ... AA35: =((Scenario_DT!R$11*(IF(Scenario_DT!R$18=1,1,1+$M35/Scenario_DT!$C$19)*(1+$N35)^MAX(0,Scenario_DT!R$18-3))*(Scenario_DT!R$12+$O35)-Scenario_DT!R$13)*(1-Scenario_DT!R$14)+Scenario_DT!R$13-Scenario_DT!R$15)*Scenario_DT!R$16 -> 3159.3837 | AB35: =(Scenario_DT!$R$11*(1+$M35/Scenario_DT!$C$19)*(1+$N35)^7*(Scenario_DT!$R$12+$O35)*(1+MIN(DCF_FCFF!$C$26+$Q35,(DCF_FCFF!$C$25+$P35)-0.02))*(1-DCF_FCFF!$C$27)*(1-DCF_FCFF!$C$28)/((DCF_FCFF!$C$25+$P35)-MIN(DCF_FCFF!$C$26+$Q35,(DCF_FCFF!$C$25+$P35)-0.02)))*(1+(DCF_FCFF!$C$25+$P35))^(-(Inputs!$C$9+9)) -> 23408.957 | AC35: =SUMPRODUCT(R35:AA35*(1+(DCF_FCFF!$C$25+$P35))^(-Scenario_DT!$I$17:$R$17))+AB35 -> 38708.301 | AD35: =((AC35-DCF_FCFF!$C$48)*(1-DCF_FCFF!$C$50)+DCF_FCFF!$C$57+DCF_FCFF!$C$58)/DCF_FCFF!$C$60 -> 275.10759 | AF35: 200 | AG35: =COUNTIFS($AD$32:$AD$531,">="&AF35,$AD$32:$AD$531,"<"&AF35+25) -> 3
B36: 5 | C36: 0.75808774 | D36: 0.35452597 | E36: 0.97069802 | F36: 0.89312112 | G36: 0.7783835 | H36: =NORMSINV(C36) -> 0.70016459 | I36: =NORMSINV(D36) -> -0.37312967 | J36: =NORMSINV(E36) -> 1.8911528 | K36: =NORMSINV(F36) -> 1.2432988 | L36: =NORMSINV(G36) -> 0.76674523 | M36: =H36*$C$5 -> 0.014003292 | N36: =($C$10*H36+SQRT(1-$C$10^2)*I36)*$C$6 -> 0.00021554018 | O36: =J36*$C$7 -> 0.022693833 | P36: =K36*$C$8 -> 0.0074597926 | Q36: =L36*$C$9 -> 0.0030669809 | R36: =((Scenario_DT!I$11*(IF(Scenario_DT!I$18=1,1,1+$M36/Scenario_DT!$C$19)*(1+$N36)^MAX(0,Scenario_DT!I$18-3))*(Scenario_DT!I$12+$O36)-Scenario_DT!I$13)*(1-Scenario_DT!I$14)+Scenario_DT!I$13-Scenario_DT!I$15)*Scenario_DT!I$16 -> 942.9804 | S36: =((Scenario_DT!J$11*(IF(Scenario_DT!J$18=1,1,1+$M36/Scenario_DT!$C$19)*(1+$N36)^MAX(0,Scenario_DT!J$18-3))*(Scenario_DT!J$12+$O36)-Scenario_DT!J$13)*(1-Scenario_DT!J$14)+Scenario_DT!J$13-Scenario_DT!J$15)*Scenario_DT!J$16 -> 1937.0403 | T36: =((Scenario_DT!K$11*(IF(Scenario_DT!K$18=1,1,1+$M36/Scenario_DT!$C$19)*(1+$N36)^MAX(0,Scenario_DT!K$18-3))*(Scenario_DT!K$12+$O36)-Scenario_DT!K$13)*(1-Scenario_DT!K$14)+Scenario_DT!K$13-Scenario_DT!K$15)*Scenario_DT!K$16 -> 2205.9203 | U36: =((Scenario_DT!L$11*(IF(Scenario_DT!L$18=1,1,1+$M36/Scenario_DT!$C$19)*(1+$N36)^MAX(0,Scenario_DT!L$18-3))*(Scenario_DT!L$12+$O36)-Scenario_DT!L$13)*(1-Scenario_DT!L$14)+Scenario_DT!L$13-Scenario_DT!L$15)*Scenario_DT!L$16 -> 2614.2765 | V36: =((Scenario_DT!M$11*(IF(Scenario_DT!M$18=1,1,1+$M36/Scenario_DT!$C$19)*(1+$N36)^MAX(0,Scenario_DT!M$18-3))*(Scenario_DT!M$12+$O36)-Scenario_DT!M$13)*(1-Scenario_DT!M$14)+Scenario_DT!M$13-Scenario_DT!M$15)*Scenario_DT!M$16 -> 2744.8644 | W36: =((Scenario_DT!N$11*(IF(Scenario_DT!N$18=1,1,1+$M36/Scenario_DT!$C$19)*(1+$N36)^MAX(0,Scenario_DT!N$18-3))*(Scenario_DT!N$12+$O36)-Scenario_DT!N$13)*(1-Scenario_DT!N$14)+Scenario_DT!N$13-Scenario_DT!N$15)*Scenario_DT!N$16 -> 2881.9685 | X36: =((Scenario_DT!O$11*(IF(Scenario_DT!O$18=1,1,1+$M36/Scenario_DT!$C$19)*(1+$N36)^MAX(0,Scenario_DT!O$18-3))*(Scenario_DT!O$12+$O36)-Scenario_DT!O$13)*(1-Scenario_DT!O$14)+Scenario_DT!O$13-Scenario_DT!O$15)*Scenario_DT!O$16 -> 3025.9164 | Y36: =((Scenario_DT!P$11*(IF(Scenario_DT!P$18=1,1,1+$M36/Scenario_DT!$C$19)*(1+$N36)^MAX(0,Scenario_DT!P$18-3))*(Scenario_DT!P$12+$O36)-Scenario_DT!P$13)*(1-Scenario_DT!P$14)+Scenario_DT!P$13-Scenario_DT!P$15)*Scenario_DT!P$16 -> 3177.0521 | ... AA36: =((Scenario_DT!R$11*(IF(Scenario_DT!R$18=1,1,1+$M36/Scenario_DT!$C$19)*(1+$N36)^MAX(0,Scenario_DT!R$18-3))*(Scenario_DT!R$12+$O36)-Scenario_DT!R$13)*(1-Scenario_DT!R$14)+Scenario_DT!R$13-Scenario_DT!R$15)*Scenario_DT!R$16 -> 3502.3501 | AB36: =(Scenario_DT!$R$11*(1+$M36/Scenario_DT!$C$19)*(1+$N36)^7*(Scenario_DT!$R$12+$O36)*(1+MIN(DCF_FCFF!$C$26+$Q36,(DCF_FCFF!$C$25+$P36)-0.02))*(1-DCF_FCFF!$C$27)*(1-DCF_FCFF!$C$28)/((DCF_FCFF!$C$25+$P36)-MIN(DCF_FCFF!$C$26+$Q36,(DCF_FCFF!$C$25+$P36)-0.02)))*(1+(DCF_FCFF!$C$25+$P36))^(-(Inputs!$C$9+9)) -> 25539.944 | AC36: =SUMPRODUCT(R36:AA36*(1+(DCF_FCFF!$C$25+$P36))^(-Scenario_DT!$I$17:$R$17))+AB36 -> 42244.579 | AD36: =((AC36-DCF_FCFF!$C$48)*(1-DCF_FCFF!$C$50)+DCF_FCFF!$C$57+DCF_FCFF!$C$58)/DCF_FCFF!$C$60 -> 309.05151 | AF36: 225 | AG36: =COUNTIFS($AD$32:$AD$531,">="&AF36,$AD$32:$AD$531,"<"&AF36+25) -> 22
B37: 6 | C37: 0.19463871 | D37: 0.466721 | E37: 0.043803766 | F37: 0.15428949 | G37: 0.68304895 | H37: =NORMSINV(C37) -> -0.86092851 | I37: =NORMSINV(D37) -> -0.083515054 | J37: =NORMSINV(E37) -> -1.7081553 | K37: =NORMSINV(F37) -> -1.0182083 | L37: =NORMSINV(G37) -> 0.47624184 | M37: =H37*$C$5 -> -0.01721857 | N37: =($C$10*H37+SQRT(1-$C$10^2)*I37)*$C$6 -> -0.0040223233 | O37: =J37*$C$7 -> -0.020497864 | P37: =K37*$C$8 -> -0.0061092497 | Q37: =L37*$C$9 -> 0.0019049674 | R37: =((Scenario_DT!I$11*(IF(Scenario_DT!I$18=1,1,1+$M37/Scenario_DT!$C$19)*(1+$N37)^MAX(0,Scenario_DT!I$18-3))*(Scenario_DT!I$12+$O37)-Scenario_DT!I$13)*(1-Scenario_DT!I$14)+Scenario_DT!I$13-Scenario_DT!I$15)*Scenario_DT!I$16 -> 882.08476 | S37: =((Scenario_DT!J$11*(IF(Scenario_DT!J$18=1,1,1+$M37/Scenario_DT!$C$19)*(1+$N37)^MAX(0,Scenario_DT!J$18-3))*(Scenario_DT!J$12+$O37)-Scenario_DT!J$13)*(1-Scenario_DT!J$14)+Scenario_DT!J$13-Scenario_DT!J$15)*Scenario_DT!J$16 -> 1728.1129 | T37: =((Scenario_DT!K$11*(IF(Scenario_DT!K$18=1,1,1+$M37/Scenario_DT!$C$19)*(1+$N37)^MAX(0,Scenario_DT!K$18-3))*(Scenario_DT!K$12+$O37)-Scenario_DT!K$13)*(1-Scenario_DT!K$14)+Scenario_DT!K$13-Scenario_DT!K$15)*Scenario_DT!K$16 -> 1988.3414 | U37: =((Scenario_DT!L$11*(IF(Scenario_DT!L$18=1,1,1+$M37/Scenario_DT!$C$19)*(1+$N37)^MAX(0,Scenario_DT!L$18-3))*(Scenario_DT!L$12+$O37)-Scenario_DT!L$13)*(1-Scenario_DT!L$14)+Scenario_DT!L$13-Scenario_DT!L$15)*Scenario_DT!L$16 -> 2373.0375 | V37: =((Scenario_DT!M$11*(IF(Scenario_DT!M$18=1,1,1+$M37/Scenario_DT!$C$19)*(1+$N37)^MAX(0,Scenario_DT!M$18-3))*(Scenario_DT!M$12+$O37)-Scenario_DT!M$13)*(1-Scenario_DT!M$14)+Scenario_DT!M$13-Scenario_DT!M$15)*Scenario_DT!M$16 -> 2480.8743 | W37: =((Scenario_DT!N$11*(IF(Scenario_DT!N$18=1,1,1+$M37/Scenario_DT!$C$19)*(1+$N37)^MAX(0,Scenario_DT!N$18-3))*(Scenario_DT!N$12+$O37)-Scenario_DT!N$13)*(1-Scenario_DT!N$14)+Scenario_DT!N$13-Scenario_DT!N$15)*Scenario_DT!N$16 -> 2593.5978 | X37: =((Scenario_DT!O$11*(IF(Scenario_DT!O$18=1,1,1+$M37/Scenario_DT!$C$19)*(1+$N37)^MAX(0,Scenario_DT!O$18-3))*(Scenario_DT!O$12+$O37)-Scenario_DT!O$13)*(1-Scenario_DT!O$14)+Scenario_DT!O$13-Scenario_DT!O$15)*Scenario_DT!O$16 -> 2711.4315 | Y37: =((Scenario_DT!P$11*(IF(Scenario_DT!P$18=1,1,1+$M37/Scenario_DT!$C$19)*(1+$N37)^MAX(0,Scenario_DT!P$18-3))*(Scenario_DT!P$12+$O37)-Scenario_DT!P$13)*(1-Scenario_DT!P$14)+Scenario_DT!P$13-Scenario_DT!P$15)*Scenario_DT!P$16 -> 2834.6089 | ... AA37: =((Scenario_DT!R$11*(IF(Scenario_DT!R$18=1,1,1+$M37/Scenario_DT!$C$19)*(1+$N37)^MAX(0,Scenario_DT!R$18-3))*(Scenario_DT!R$12+$O37)-Scenario_DT!R$13)*(1-Scenario_DT!R$14)+Scenario_DT!R$13-Scenario_DT!R$15)*Scenario_DT!R$16 -> 3097.9834 | AB37: =(Scenario_DT!$R$11*(1+$M37/Scenario_DT!$C$19)*(1+$N37)^7*(Scenario_DT!$R$12+$O37)*(1+MIN(DCF_FCFF!$C$26+$Q37,(DCF_FCFF!$C$25+$P37)-0.02))*(1-DCF_FCFF!$C$27)*(1-DCF_FCFF!$C$28)/((DCF_FCFF!$C$25+$P37)-MIN(DCF_FCFF!$C$26+$Q37,(DCF_FCFF!$C$25+$P37)-0.02)))*(1+(DCF_FCFF!$C$25+$P37))^(-(Inputs!$C$9+9)) -> 32852.821 | AC37: =SUMPRODUCT(R37:AA37*(1+(DCF_FCFF!$C$25+$P37))^(-Scenario_DT!$I$17:$R$17))+AB37 -> 48748.856 | AD37: =((AC37-DCF_FCFF!$C$48)*(1-DCF_FCFF!$C$50)+DCF_FCFF!$C$57+DCF_FCFF!$C$58)/DCF_FCFF!$C$60 -> 371.48456 | AF37: 250 | AG37: =COUNTIFS($AD$32:$AD$531,">="&AF37,$AD$32:$AD$531,"<"&AF37+25) -> 39
B38: 7 | C38: 0.74476216 | D38: 0.96750973 | E38: 0.32582536 | F38: 0.37045971 | G38: 0.46955581 | H38: =NORMSINV(C38) -> 0.65809718 | I38: =NORMSINV(D38) -> 1.845392 | J38: =NORMSINV(E38) -> -0.45147017 | K38: =NORMSINV(F38) -> -0.33063605 | L38: =NORMSINV(G38) -> -0.076386484 | M38: =H38*$C$5 -> 0.013161944 | N38: =($C$10*H38+SQRT(1-$C$10^2)*I38)*$C$6 -> 0.01541764 | O38: =J38*$C$7 -> -0.0054176421 | P38: =K38*$C$8 -> -0.0019838163 | Q38: =L38*$C$9 -> -0.00030554594 | R38: =((Scenario_DT!I$11*(IF(Scenario_DT!I$18=1,1,1+$M38/Scenario_DT!$C$19)*(1+$N38)^MAX(0,Scenario_DT!I$18-3))*(Scenario_DT!I$12+$O38)-Scenario_DT!I$13)*(1-Scenario_DT!I$14)+Scenario_DT!I$13-Scenario_DT!I$15)*Scenario_DT!I$16 -> 903.34625 | S38: =((Scenario_DT!J$11*(IF(Scenario_DT!J$18=1,1,1+$M38/Scenario_DT!$C$19)*(1+$N38)^MAX(0,Scenario_DT!J$18-3))*(Scenario_DT!J$12+$O38)-Scenario_DT!J$13)*(1-Scenario_DT!J$14)+Scenario_DT!J$13-Scenario_DT!J$15)*Scenario_DT!J$16 -> 1846.3761 | T38: =((Scenario_DT!K$11*(IF(Scenario_DT!K$18=1,1,1+$M38/Scenario_DT!$C$19)*(1+$N38)^MAX(0,Scenario_DT!K$18-3))*(Scenario_DT!K$12+$O38)-Scenario_DT!K$13)*(1-Scenario_DT!K$14)+Scenario_DT!K$13-Scenario_DT!K$15)*Scenario_DT!K$16 -> 2111.9339 | U38: =((Scenario_DT!L$11*(IF(Scenario_DT!L$18=1,1,1+$M38/Scenario_DT!$C$19)*(1+$N38)^MAX(0,Scenario_DT!L$18-3))*(Scenario_DT!L$12+$O38)-Scenario_DT!L$13)*(1-Scenario_DT!L$14)+Scenario_DT!L$13-Scenario_DT!L$15)*Scenario_DT!L$16 -> 2552.9358 | V38: =((Scenario_DT!M$11*(IF(Scenario_DT!M$18=1,1,1+$M38/Scenario_DT!$C$19)*(1+$N38)^MAX(0,Scenario_DT!M$18-3))*(Scenario_DT!M$12+$O38)-Scenario_DT!M$13)*(1-Scenario_DT!M$14)+Scenario_DT!M$13-Scenario_DT!M$15)*Scenario_DT!M$16 -> 2721.4626 | W38: =((Scenario_DT!N$11*(IF(Scenario_DT!N$18=1,1,1+$M38/Scenario_DT!$C$19)*(1+$N38)^MAX(0,Scenario_DT!N$18-3))*(Scenario_DT!N$12+$O38)-Scenario_DT!N$13)*(1-Scenario_DT!N$14)+Scenario_DT!N$13-Scenario_DT!N$15)*Scenario_DT!N$16 -> 2901.1262 | X38: =((Scenario_DT!O$11*(IF(Scenario_DT!O$18=1,1,1+$M38/Scenario_DT!$C$19)*(1+$N38)^MAX(0,Scenario_DT!O$18-3))*(Scenario_DT!O$12+$O38)-Scenario_DT!O$13)*(1-Scenario_DT!O$14)+Scenario_DT!O$13-Scenario_DT!O$15)*Scenario_DT!O$16 -> 3092.6659 | Y38: =((Scenario_DT!P$11*(IF(Scenario_DT!P$18=1,1,1+$M38/Scenario_DT!$C$19)*(1+$N38)^MAX(0,Scenario_DT!P$18-3))*(Scenario_DT!P$12+$O38)-Scenario_DT!P$13)*(1-Scenario_DT!P$14)+Scenario_DT!P$13-Scenario_DT!P$15)*Scenario_DT!P$16 -> 3296.8701 | ... AA38: =((Scenario_DT!R$11*(IF(Scenario_DT!R$18=1,1,1+$M38/Scenario_DT!$C$19)*(1+$N38)^MAX(0,Scenario_DT!R$18-3))*(Scenario_DT!R$12+$O38)-Scenario_DT!R$13)*(1-Scenario_DT!R$14)+Scenario_DT!R$13-Scenario_DT!R$15)*Scenario_DT!R$16 -> 3746.6905 | AB38: =(Scenario_DT!$R$11*(1+$M38/Scenario_DT!$C$19)*(1+$N38)^7*(Scenario_DT!$R$12+$O38)*(1+MIN(DCF_FCFF!$C$26+$Q38,(DCF_FCFF!$C$25+$P38)-0.02))*(1-DCF_FCFF!$C$27)*(1-DCF_FCFF!$C$28)/((DCF_FCFF!$C$25+$P38)-MIN(DCF_FCFF!$C$26+$Q38,(DCF_FCFF!$C$25+$P38)-0.02)))*(1+(DCF_FCFF!$C$25+$P38))^(-(Inputs!$C$9+9)) -> 33221.088 | AC38: =SUMPRODUCT(R38:AA38*(1+(DCF_FCFF!$C$25+$P38))^(-Scenario_DT!$I$17:$R$17))+AB38 -> 50659.103 | AD38: =((AC38-DCF_FCFF!$C$48)*(1-DCF_FCFF!$C$50)+DCF_FCFF!$C$57+DCF_FCFF!$C$58)/DCF_FCFF!$C$60 -> 389.82057 | AF38: 275 | AG38: =COUNTIFS($AD$32:$AD$531,">="&AF38,$AD$32:$AD$531,"<"&AF38+25) -> 65
B39: 8 | C39: 0.18947136 | D39: 0.12992151 | E39: 0.47570493 | F39: 0.22690935 | G39: 0.66981399 | H39: =NORMSINV(C39) -> -0.87984604 | I39: =NORMSINV(D39) -> -1.1267623 | J39: =NORMSINV(E39) -> -0.06093641 | K39: =NORMSINV(F39) -> -0.74906389 | L39: =NORMSINV(G39) -> 0.43939961 | M39: =H39*$C$5 -> -0.017596921 | N39: =($C$10*H39+SQRT(1-$C$10^2)*I39)*$C$6 -> -0.011325822 | O39: =J39*$C$7 -> -0.00073123692 | P39: =K39*$C$8 -> -0.0044943833 | Q39: =L39*$C$9 -> 0.0017575984 | R39: =((Scenario_DT!I$11*(IF(Scenario_DT!I$18=1,1,1+$M39/Scenario_DT!$C$19)*(1+$N39)^MAX(0,Scenario_DT!I$18-3))*(Scenario_DT!I$12+$O39)-Scenario_DT!I$13)*(1-Scenario_DT!I$14)+Scenario_DT!I$13-Scenario_DT!I$15)*Scenario_DT!I$16 -> 909.95357 | S39: =((Scenario_DT!J$11*(IF(Scenario_DT!J$18=1,1,1+$M39/Scenario_DT!$C$19)*(1+$N39)^MAX(0,Scenario_DT!J$18-3))*(Scenario_DT!J$12+$O39)-Scenario_DT!J$13)*(1-Scenario_DT!J$14)+Scenario_DT!J$13-Scenario_DT!J$15)*Scenario_DT!J$16 -> 1787.512 | T39: =((Scenario_DT!K$11*(IF(Scenario_DT!K$18=1,1,1+$M39/Scenario_DT!$C$19)*(1+$N39)^MAX(0,Scenario_DT!K$18-3))*(Scenario_DT!K$12+$O39)-Scenario_DT!K$13)*(1-Scenario_DT!K$14)+Scenario_DT!K$13-Scenario_DT!K$15)*Scenario_DT!K$16 -> 2049.8856 | U39: =((Scenario_DT!L$11*(IF(Scenario_DT!L$18=1,1,1+$M39/Scenario_DT!$C$19)*(1+$N39)^MAX(0,Scenario_DT!L$18-3))*(Scenario_DT!L$12+$O39)-Scenario_DT!L$13)*(1-Scenario_DT!L$14)+Scenario_DT!L$13-Scenario_DT!L$15)*Scenario_DT!L$16 -> 2420.1183 | V39: =((Scenario_DT!M$11*(IF(Scenario_DT!M$18=1,1,1+$M39/Scenario_DT!$C$19)*(1+$N39)^MAX(0,Scenario_DT!M$18-3))*(Scenario_DT!M$12+$O39)-Scenario_DT!M$13)*(1-Scenario_DT!M$14)+Scenario_DT!M$13-Scenario_DT!M$15)*Scenario_DT!M$16 -> 2511.4218 | W39: =((Scenario_DT!N$11*(IF(Scenario_DT!N$18=1,1,1+$M39/Scenario_DT!$C$19)*(1+$N39)^MAX(0,Scenario_DT!N$18-3))*(Scenario_DT!N$12+$O39)-Scenario_DT!N$13)*(1-Scenario_DT!N$14)+Scenario_DT!N$13-Scenario_DT!N$15)*Scenario_DT!N$16 -> 2606.143 | X39: =((Scenario_DT!O$11*(IF(Scenario_DT!O$18=1,1,1+$M39/Scenario_DT!$C$19)*(1+$N39)^MAX(0,Scenario_DT!O$18-3))*(Scenario_DT!O$12+$O39)-Scenario_DT!O$13)*(1-Scenario_DT!O$14)+Scenario_DT!O$13-Scenario_DT!O$15)*Scenario_DT!O$16 -> 2704.4109 | Y39: =((Scenario_DT!P$11*(IF(Scenario_DT!P$18=1,1,1+$M39/Scenario_DT!$C$19)*(1+$N39)^MAX(0,Scenario_DT!P$18-3))*(Scenario_DT!P$12+$O39)-Scenario_DT!P$13)*(1-Scenario_DT!P$14)+Scenario_DT!P$13-Scenario_DT!P$15)*Scenario_DT!P$16 -> 2806.3594 | ... AA39: =((Scenario_DT!R$11*(IF(Scenario_DT!R$18=1,1,1+$M39/Scenario_DT!$C$19)*(1+$N39)^MAX(0,Scenario_DT!R$18-3))*(Scenario_DT!R$12+$O39)-Scenario_DT!R$13)*(1-Scenario_DT!R$14)+Scenario_DT!R$13-Scenario_DT!R$15)*Scenario_DT!R$16 -> 3021.8593 | AB39: =(Scenario_DT!$R$11*(1+$M39/Scenario_DT!$C$19)*(1+$N39)^7*(Scenario_DT!$R$12+$O39)*(1+MIN(DCF_FCFF!$C$26+$Q39,(DCF_FCFF!$C$25+$P39)-0.02))*(1-DCF_FCFF!$C$27)*(1-DCF_FCFF!$C$28)/((DCF_FCFF!$C$25+$P39)-MIN(DCF_FCFF!$C$26+$Q39,(DCF_FCFF!$C$25+$P39)-0.02)))*(1+(DCF_FCFF!$C$25+$P39))^(-(Inputs!$C$9+9)) -> 30338.321 | AC39: =SUMPRODUCT(R39:AA39*(1+(DCF_FCFF!$C$25+$P39))^(-Scenario_DT!$I$17:$R$17))+AB39 -> 46244.084 | AD39: =((AC39-DCF_FCFF!$C$48)*(1-DCF_FCFF!$C$50)+DCF_FCFF!$C$57+DCF_FCFF!$C$58)/DCF_FCFF!$C$60 -> 347.44183 | AF39: 300 | AG39: =COUNTIFS($AD$32:$AD$531,">="&AF39,$AD$32:$AD$531,"<"&AF39+25) -> 84
B40: 9 | C40: 0.43715192 | D40: 0.8326782 | E40: 0.7002651 | F40: 0.31236664 | G40: 0.8322598 | H40: =NORMSINV(C40) -> -0.15819412 | I40: =NORMSINV(D40) -> 0.96480277 | J40: =NORMSINV(E40) -> 0.52516313 | K40: =NORMSINV(F40) -> -0.48915314 | L40: =NORMSINV(G40) -> 0.96313377 | M40: =H40*$C$5 -> -0.0031638824 | N40: =($C$10*H40+SQRT(1-$C$10^2)*I40)*$C$6 -> 0.0060515732 | O40: =J40*$C$7 -> 0.0063019575 | P40: =K40*$C$8 -> -0.0029349188 | Q40: =L40*$C$9 -> 0.0038525351 | R40: =((Scenario_DT!I$11*(IF(Scenario_DT!I$18=1,1,1+$M40/Scenario_DT!$C$19)*(1+$N40)^MAX(0,Scenario_DT!I$18-3))*(Scenario_DT!I$12+$O40)-Scenario_DT!I$13)*(1-Scenario_DT!I$14)+Scenario_DT!I$13-Scenario_DT!I$15)*Scenario_DT!I$16 -> 919.86962 | S40: =((Scenario_DT!J$11*(IF(Scenario_DT!J$18=1,1,1+$M40/Scenario_DT!$C$19)*(1+$N40)^MAX(0,Scenario_DT!J$18-3))*(Scenario_DT!J$12+$O40)-Scenario_DT!J$13)*(1-Scenario_DT!J$14)+Scenario_DT!J$13-Scenario_DT!J$15)*Scenario_DT!J$16 -> 1843.8462 | T40: =((Scenario_DT!K$11*(IF(Scenario_DT!K$18=1,1,1+$M40/Scenario_DT!$C$19)*(1+$N40)^MAX(0,Scenario_DT!K$18-3))*(Scenario_DT!K$12+$O40)-Scenario_DT!K$13)*(1-Scenario_DT!K$14)+Scenario_DT!K$13-Scenario_DT!K$15)*Scenario_DT!K$16 -> 2108.7569 | U40: =((Scenario_DT!L$11*(IF(Scenario_DT!L$18=1,1,1+$M40/Scenario_DT!$C$19)*(1+$N40)^MAX(0,Scenario_DT!L$18-3))*(Scenario_DT!L$12+$O40)-Scenario_DT!L$13)*(1-Scenario_DT!L$14)+Scenario_DT!L$13-Scenario_DT!L$15)*Scenario_DT!L$16 -> 2525.8386 | V40: =((Scenario_DT!M$11*(IF(Scenario_DT!M$18=1,1,1+$M40/Scenario_DT!$C$19)*(1+$N40)^MAX(0,Scenario_DT!M$18-3))*(Scenario_DT!M$12+$O40)-Scenario_DT!M$13)*(1-Scenario_DT!M$14)+Scenario_DT!M$13-Scenario_DT!M$15)*Scenario_DT!M$16 -> 2667.5659 | W40: =((Scenario_DT!N$11*(IF(Scenario_DT!N$18=1,1,1+$M40/Scenario_DT!$C$19)*(1+$N40)^MAX(0,Scenario_DT!N$18-3))*(Scenario_DT!N$12+$O40)-Scenario_DT!N$13)*(1-Scenario_DT!N$14)+Scenario_DT!N$13-Scenario_DT!N$15)*Scenario_DT!N$16 -> 2817.247 | X40: =((Scenario_DT!O$11*(IF(Scenario_DT!O$18=1,1,1+$M40/Scenario_DT!$C$19)*(1+$N40)^MAX(0,Scenario_DT!O$18-3))*(Scenario_DT!O$12+$O40)-Scenario_DT!O$13)*(1-Scenario_DT!O$14)+Scenario_DT!O$13-Scenario_DT!O$15)*Scenario_DT!O$16 -> 2975.3311 | Y40: =((Scenario_DT!P$11*(IF(Scenario_DT!P$18=1,1,1+$M40/Scenario_DT!$C$19)*(1+$N40)^MAX(0,Scenario_DT!P$18-3))*(Scenario_DT!P$12+$O40)-Scenario_DT!P$13)*(1-Scenario_DT!P$14)+Scenario_DT!P$13-Scenario_DT!P$15)*Scenario_DT!P$16 -> 3142.2928 | ... AA40: =((Scenario_DT!R$11*(IF(Scenario_DT!R$18=1,1,1+$M40/Scenario_DT!$C$19)*(1+$N40)^MAX(0,Scenario_DT!R$18-3))*(Scenario_DT!R$12+$O40)-Scenario_DT!R$13)*(1-Scenario_DT!R$14)+Scenario_DT!R$13-Scenario_DT!R$15)*Scenario_DT!R$16 -> 3504.883 | AB40: =(Scenario_DT!$R$11*(1+$M40/Scenario_DT!$C$19)*(1+$N40)^7*(Scenario_DT!$R$12+$O40)*(1+MIN(DCF_FCFF!$C$26+$Q40,(DCF_FCFF!$C$25+$P40)-0.02))*(1-DCF_FCFF!$C$27)*(1-DCF_FCFF!$C$28)/((DCF_FCFF!$C$25+$P40)-MIN(DCF_FCFF!$C$26+$Q40,(DCF_FCFF!$C$25+$P40)-0.02)))*(1+(DCF_FCFF!$C$25+$P40))^(-(Inputs!$C$9+9)) -> 35164.678 | AC40: =SUMPRODUCT(R40:AA40*(1+(DCF_FCFF!$C$25+$P40))^(-Scenario_DT!$I$17:$R$17))+AB40 -> 52199.303 | AD40: =((AC40-DCF_FCFF!$C$48)*(1-DCF_FCFF!$C$50)+DCF_FCFF!$C$57+DCF_FCFF!$C$58)/DCF_FCFF!$C$60 -> 404.60459 | AF40: 325 | AG40: =COUNTIFS($AD$32:$AD$531,">="&AF40,$AD$32:$AD$531,"<"&AF40+25) -> 73
B41: 10 | C41: 0.80476436 | D41: 0.38747838 | E41: 0.2883281 | F41: 0.6824955 | G41: 0.13975248 | H41: =NORMSINV(C41) -> 0.858763 | I41: =NORMSINV(D41) -> -0.28589733 | J41: =NORMSINV(E41) -> -0.55827559 | K41: =NORMSINV(F41) -> 0.47468853 | L41: =NORMSINV(G41) -> -1.0814321 | M41: =H41*$C$5 -> 0.01717526 | N41: =($C$10*H41+SQRT(1-$C$10^2)*I41)*$C$6 -> 0.0014542972 | O41: =J41*$C$7 -> -0.0066993071 | P41: =K41*$C$8 -> 0.0028481312 | Q41: =L41*$C$9 -> -0.0043257282 | R41: =((Scenario_DT!I$11*(IF(Scenario_DT!I$18=1,1,1+$M41/Scenario_DT!$C$19)*(1+$N41)^MAX(0,Scenario_DT!I$18-3))*(Scenario_DT!I$12+$O41)-Scenario_DT!I$13)*(1-Scenario_DT!I$14)+Scenario_DT!I$13-Scenario_DT!I$15)*Scenario_DT!I$16 -> 901.53924 | S41: =((Scenario_DT!J$11*(IF(Scenario_DT!J$18=1,1,1+$M41/Scenario_DT!$C$19)*(1+$N41)^MAX(0,Scenario_DT!J$18-3))*(Scenario_DT!J$12+$O41)-Scenario_DT!J$13)*(1-Scenario_DT!J$14)+Scenario_DT!J$13-Scenario_DT!J$15)*Scenario_DT!J$16 -> 1851.8654 | T41: =((Scenario_DT!K$11*(IF(Scenario_DT!K$18=1,1,1+$M41/Scenario_DT!$C$19)*(1+$N41)^MAX(0,Scenario_DT!K$18-3))*(Scenario_DT!K$12+$O41)-Scenario_DT!K$13)*(1-Scenario_DT!K$14)+Scenario_DT!K$13-Scenario_DT!K$15)*Scenario_DT!K$16 -> 2117.7591 | U41: =((Scenario_DT!L$11*(IF(Scenario_DT!L$18=1,1,1+$M41/Scenario_DT!$C$19)*(1+$N41)^MAX(0,Scenario_DT!L$18-3))*(Scenario_DT!L$12+$O41)-Scenario_DT!L$13)*(1-Scenario_DT!L$14)+Scenario_DT!L$13-Scenario_DT!L$15)*Scenario_DT!L$16 -> 2523.7915 | V41: =((Scenario_DT!M$11*(IF(Scenario_DT!M$18=1,1,1+$M41/Scenario_DT!$C$19)*(1+$N41)^MAX(0,Scenario_DT!M$18-3))*(Scenario_DT!M$12+$O41)-Scenario_DT!M$13)*(1-Scenario_DT!M$14)+Scenario_DT!M$13-Scenario_DT!M$15)*Scenario_DT!M$16 -> 2653.1393 | W41: =((Scenario_DT!N$11*(IF(Scenario_DT!N$18=1,1,1+$M41/Scenario_DT!$C$19)*(1+$N41)^MAX(0,Scenario_DT!N$18-3))*(Scenario_DT!N$12+$O41)-Scenario_DT!N$13)*(1-Scenario_DT!N$14)+Scenario_DT!N$13-Scenario_DT!N$15)*Scenario_DT!N$16 -> 2789.1113 | X41: =((Scenario_DT!O$11*(IF(Scenario_DT!O$18=1,1,1+$M41/Scenario_DT!$C$19)*(1+$N41)^MAX(0,Scenario_DT!O$18-3))*(Scenario_DT!O$12+$O41)-Scenario_DT!O$13)*(1-Scenario_DT!O$14)+Scenario_DT!O$13-Scenario_DT!O$15)*Scenario_DT!O$16 -> 2932.0493 | Y41: =((Scenario_DT!P$11*(IF(Scenario_DT!P$18=1,1,1+$M41/Scenario_DT!$C$19)*(1+$N41)^MAX(0,Scenario_DT!P$18-3))*(Scenario_DT!P$12+$O41)-Scenario_DT!P$13)*(1-Scenario_DT!P$14)+Scenario_DT!P$13-Scenario_DT!P$15)*Scenario_DT!P$16 -> 3082.3126 | ... AA41: =((Scenario_DT!R$11*(IF(Scenario_DT!R$18=1,1,1+$M41/Scenario_DT!$C$19)*(1+$N41)^MAX(0,Scenario_DT!R$18-3))*(Scenario_DT!R$12+$O41)-Scenario_DT!R$13)*(1-Scenario_DT!R$14)+Scenario_DT!R$13-Scenario_DT!R$15)*Scenario_DT!R$16 -> 3406.3463 | AB41: =(Scenario_DT!$R$11*(1+$M41/Scenario_DT!$C$19)*(1+$N41)^7*(Scenario_DT!$R$12+$O41)*(1+MIN(DCF_FCFF!$C$26+$Q41,(DCF_FCFF!$C$25+$P41)-0.02))*(1-DCF_FCFF!$C$27)*(1-DCF_FCFF!$C$28)/((DCF_FCFF!$C$25+$P41)-MIN(DCF_FCFF!$C$26+$Q41,(DCF_FCFF!$C$25+$P41)-0.02)))*(1+(DCF_FCFF!$C$25+$P41))^(-(Inputs!$C$9+9)) -> 24432.617 | AC41: =SUMPRODUCT(R41:AA41*(1+(DCF_FCFF!$C$25+$P41))^(-Scenario_DT!$I$17:$R$17))+AB41 -> 40879.643 | AD41: =((AC41-DCF_FCFF!$C$48)*(1-DCF_FCFF!$C$50)+DCF_FCFF!$C$57+DCF_FCFF!$C$58)/DCF_FCFF!$C$60 -> 295.9498 | AF41: 350 | AG41: =COUNTIFS($AD$32:$AD$531,">="&AF41,$AD$32:$AD$531,"<"&AF41+25) -> 77
B42: 11 | C42: 0.1999082 | D42: 0.0073622698 | E42: 0.78692438 | F42: 0.66485086 | G42: 0.70516538 | H42: =NORMSINV(C42) -> -0.84194917 | I42: =NORMSINV(D42) -> -2.4390841 | J42: =NORMSINV(E42) -> 0.79579492 | K42: =NORMSINV(F42) -> 0.42573866 | L42: =NORMSINV(G42) -> 0.5393154 | M42: =H42*$C$5 -> -0.016838983 | N42: =($C$10*H42+SQRT(1-$C$10^2)*I42)*$C$6 -> -0.020266267 | O42: =J42*$C$7 -> 0.009549539 | P42: =K42*$C$8 -> 0.002554432 | Q42: =L42*$C$9 -> 0.0021572616 | R42: =((Scenario_DT!I$11*(IF(Scenario_DT!I$18=1,1,1+$M42/Scenario_DT!$C$19)*(1+$N42)^MAX(0,Scenario_DT!I$18-3))*(Scenario_DT!I$12+$O42)-Scenario_DT!I$13)*(1-Scenario_DT!I$14)+Scenario_DT!I$13-Scenario_DT!I$15)*Scenario_DT!I$16 -> 924.44836 | S42: =((Scenario_DT!J$11*(IF(Scenario_DT!J$18=1,1,1+$M42/Scenario_DT!$C$19)*(1+$N42)^MAX(0,Scenario_DT!J$18-3))*(Scenario_DT!J$12+$O42)-Scenario_DT!J$13)*(1-Scenario_DT!J$14)+Scenario_DT!J$13-Scenario_DT!J$15)*Scenario_DT!J$16 -> 1820.7043 | T42: =((Scenario_DT!K$11*(IF(Scenario_DT!K$18=1,1,1+$M42/Scenario_DT!$C$19)*(1+$N42)^MAX(0,Scenario_DT!K$18-3))*(Scenario_DT!K$12+$O42)-Scenario_DT!K$13)*(1-Scenario_DT!K$14)+Scenario_DT!K$13-Scenario_DT!K$15)*Scenario_DT!K$16 -> 2084.3094 | U42: =((Scenario_DT!L$11*(IF(Scenario_DT!L$18=1,1,1+$M42/Scenario_DT!$C$19)*(1+$N42)^MAX(0,Scenario_DT!L$18-3))*(Scenario_DT!L$12+$O42)-Scenario_DT!L$13)*(1-Scenario_DT!L$14)+Scenario_DT!L$13-Scenario_DT!L$15)*Scenario_DT!L$16 -> 2433.8907 | V42: =((Scenario_DT!M$11*(IF(Scenario_DT!M$18=1,1,1+$M42/Scenario_DT!$C$19)*(1+$N42)^MAX(0,Scenario_DT!M$18-3))*(Scenario_DT!M$12+$O42)-Scenario_DT!M$13)*(1-Scenario_DT!M$14)+Scenario_DT!M$13-Scenario_DT!M$15)*Scenario_DT!M$16 -> 2502.7125 | W42: =((Scenario_DT!N$11*(IF(Scenario_DT!N$18=1,1,1+$M42/Scenario_DT!$C$19)*(1+$N42)^MAX(0,Scenario_DT!N$18-3))*(Scenario_DT!N$12+$O42)-Scenario_DT!N$13)*(1-Scenario_DT!N$14)+Scenario_DT!N$13-Scenario_DT!N$15)*Scenario_DT!N$16 -> 2573.4346 | X42: =((Scenario_DT!O$11*(IF(Scenario_DT!O$18=1,1,1+$M42/Scenario_DT!$C$19)*(1+$N42)^MAX(0,Scenario_DT!O$18-3))*(Scenario_DT!O$12+$O42)-Scenario_DT!O$13)*(1-Scenario_DT!O$14)+Scenario_DT!O$13-Scenario_DT!O$15)*Scenario_DT!O$16 -> 2646.1091 | Y42: =((Scenario_DT!P$11*(IF(Scenario_DT!P$18=1,1,1+$M42/Scenario_DT!$C$19)*(1+$N42)^MAX(0,Scenario_DT!P$18-3))*(Scenario_DT!P$12+$O42)-Scenario_DT!P$13)*(1-Scenario_DT!P$14)+Scenario_DT!P$13-Scenario_DT!P$15)*Scenario_DT!P$16 -> 2720.7896 | ... AA42: =((Scenario_DT!R$11*(IF(Scenario_DT!R$18=1,1,1+$M42/Scenario_DT!$C$19)*(1+$N42)^MAX(0,Scenario_DT!R$18-3))*(Scenario_DT!R$12+$O42)-Scenario_DT!R$13)*(1-Scenario_DT!R$14)+Scenario_DT!R$13-Scenario_DT!R$15)*Scenario_DT!R$16 -> 2876.3904 | AB42: =(Scenario_DT!$R$11*(1+$M42/Scenario_DT!$C$19)*(1+$N42)^7*(Scenario_DT!$R$12+$O42)*(1+MIN(DCF_FCFF!$C$26+$Q42,(DCF_FCFF!$C$25+$P42)-0.02))*(1-DCF_FCFF!$C$27)*(1-DCF_FCFF!$C$28)/((DCF_FCFF!$C$25+$P42)-MIN(DCF_FCFF!$C$26+$Q42,(DCF_FCFF!$C$25+$P42)-0.02)))*(1+(DCF_FCFF!$C$25+$P42))^(-(Inputs!$C$9+9)) -> 23625.949 | AC42: =SUMPRODUCT(R42:AA42*(1+(DCF_FCFF!$C$25+$P42))^(-Scenario_DT!$I$17:$R$17))+AB42 -> 38926.241 | AD42: =((AC42-DCF_FCFF!$C$48)*(1-DCF_FCFF!$C$50)+DCF_FCFF!$C$57+DCF_FCFF!$C$58)/DCF_FCFF!$C$60 -> 277.19954 | AF42: 375 | AG42: =COUNTIFS($AD$32:$AD$531,">="&AF42,$AD$32:$AD$531,"<"&AF42+25) -> 49
B43: 12 | C43: 0.78072903 | D43: 0.45891578 | E43: 0.5687412 | F43: 0.139797 | G43: 0.11453007 | H43: =NORMSINV(C43) -> 0.77465772 | I43: =NORMSINV(D43) -> -0.10316559 | J43: =NORMSINV(E43) -> 0.17317025 | K43: =NORMSINV(F43) -> -1.0812318 | L43: =NORMSINV(G43) -> -1.2027834 | M43: =H43*$C$5 -> 0.015493154 | N43: =($C$10*H43+SQRT(1-$C$10^2)*I43)*$C$6 -> 0.0023838787 | O43: =J43*$C$7 -> 0.002078043 | P43: =K43*$C$8 -> -0.0064873911 | Q43: =L43*$C$9 -> -0.0048111336 | R43: =((Scenario_DT!I$11*(IF(Scenario_DT!I$18=1,1,1+$M43/Scenario_DT!$C$19)*(1+$N43)^MAX(0,Scenario_DT!I$18-3))*(Scenario_DT!I$12+$O43)-Scenario_DT!I$13)*(1-Scenario_DT!I$14)+Scenario_DT!I$13-Scenario_DT!I$15)*Scenario_DT!I$16 -> 913.91435 | S43: =((Scenario_DT!J$11*(IF(Scenario_DT!J$18=1,1,1+$M43/Scenario_DT!$C$19)*(1+$N43)^MAX(0,Scenario_DT!J$18-3))*(Scenario_DT!J$12+$O43)-Scenario_DT!J$13)*(1-Scenario_DT!J$14)+Scenario_DT!J$13-Scenario_DT!J$15)*Scenario_DT!J$16 -> 1875.5987 | T43: =((Scenario_DT!K$11*(IF(Scenario_DT!K$18=1,1,1+$M43/Scenario_DT!$C$19)*(1+$N43)^MAX(0,Scenario_DT!K$18-3))*(Scenario_DT!K$12+$O43)-Scenario_DT!K$13)*(1-Scenario_DT!K$14)+Scenario_DT!K$13-Scenario_DT!K$15)*Scenario_DT!K$16 -> 2142.2974 | U43: =((Scenario_DT!L$11*(IF(Scenario_DT!L$18=1,1,1+$M43/Scenario_DT!$C$19)*(1+$N43)^MAX(0,Scenario_DT!L$18-3))*(Scenario_DT!L$12+$O43)-Scenario_DT!L$13)*(1-Scenario_DT!L$14)+Scenario_DT!L$13-Scenario_DT!L$15)*Scenario_DT!L$16 -> 2552.2661 | V43: =((Scenario_DT!M$11*(IF(Scenario_DT!M$18=1,1,1+$M43/Scenario_DT!$C$19)*(1+$N43)^MAX(0,Scenario_DT!M$18-3))*(Scenario_DT!M$12+$O43)-Scenario_DT!M$13)*(1-Scenario_DT!M$14)+Scenario_DT!M$13-Scenario_DT!M$15)*Scenario_DT!M$16 -> 2685.5888 | W43: =((Scenario_DT!N$11*(IF(Scenario_DT!N$18=1,1,1+$M43/Scenario_DT!$C$19)*(1+$N43)^MAX(0,Scenario_DT!N$18-3))*(Scenario_DT!N$12+$O43)-Scenario_DT!N$13)*(1-Scenario_DT!N$14)+Scenario_DT!N$13-Scenario_DT!N$15)*Scenario_DT!N$16 -> 2825.8721 | X43: =((Scenario_DT!O$11*(IF(Scenario_DT!O$18=1,1,1+$M43/Scenario_DT!$C$19)*(1+$N43)^MAX(0,Scenario_DT!O$18-3))*(Scenario_DT!O$12+$O43)-Scenario_DT!O$13)*(1-Scenario_DT!O$14)+Scenario_DT!O$13-Scenario_DT!O$15)*Scenario_DT!O$16 -> 2973.4821 | Y43: =((Scenario_DT!P$11*(IF(Scenario_DT!P$18=1,1,1+$M43/Scenario_DT!$C$19)*(1+$N43)^MAX(0,Scenario_DT!P$18-3))*(Scenario_DT!P$12+$O43)-Scenario_DT!P$13)*(1-Scenario_DT!P$14)+Scenario_DT!P$13-Scenario_DT!P$15)*Scenario_DT!P$16 -> 3128.804 | ... AA43: =((Scenario_DT!R$11*(IF(Scenario_DT!R$18=1,1,1+$M43/Scenario_DT!$C$19)*(1+$N43)^MAX(0,Scenario_DT!R$18-3))*(Scenario_DT!R$12+$O43)-Scenario_DT!R$13)*(1-Scenario_DT!R$14)+Scenario_DT!R$13-Scenario_DT!R$15)*Scenario_DT!R$16 -> 3464.2269 | AB43: =(Scenario_DT!$R$11*(1+$M43/Scenario_DT!$C$19)*(1+$N43)^7*(Scenario_DT!$R$12+$O43)*(1+MIN(DCF_FCFF!$C$26+$Q43,(DCF_FCFF!$C$25+$P43)-0.02))*(1-DCF_FCFF!$C$27)*(1-DCF_FCFF!$C$28)/((DCF_FCFF!$C$25+$P43)-MIN(DCF_FCFF!$C$26+$Q43,(DCF_FCFF!$C$25+$P43)-0.02)))*(1+(DCF_FCFF!$C$25+$P43))^(-(Inputs!$C$9+9)) -> 31826.429 | AC43: =SUMPRODUCT(R43:AA43*(1+(DCF_FCFF!$C$25+$P43))^(-Scenario_DT!$I$17:$R$17))+AB43 -> 49172.924 | AD43: =((AC43-DCF_FCFF!$C$48)*(1-DCF_FCFF!$C$50)+DCF_FCFF!$C$57+DCF_FCFF!$C$58)/DCF_FCFF!$C$60 -> 375.55509 | AF43: 400 | AG43: =COUNTIFS($AD$32:$AD$531,">="&AF43,$AD$32:$AD$531,"<"&AF43+25) -> 31
... B54: 23 | C54: 0.45577629 | D54: 0.20236336 | E54: 0.30595662 | F54: 0.57921957 | G54: 0.17677278 | H54: =NORMSINV(C54) -> -0.11108041 | I54: =NORMSINV(D54) -> -0.83320924 | J54: =NORMSINV(E54) -> -0.50734432 | K54: =NORMSINV(F54) -> 0.19989735 | L54: =NORMSINV(G54) -> -0.927734 | M54: =H54*$C$5 -> -0.0022216083 | N54: =($C$10*H54+SQRT(1-$C$10^2)*I54)*$C$6 -> -0.0062169646 | O54: =J54*$C$7 -> -0.0060881318 | P54: =K54*$C$8 -> 0.0011993841 | Q54: =L54*$C$9 -> -0.003710936 | R54: =((Scenario_DT!I$11*(IF(Scenario_DT!I$18=1,1,1+$M54/Scenario_DT!$C$19)*(1+$N54)^MAX(0,Scenario_DT!I$18-3))*(Scenario_DT!I$12+$O54)-Scenario_DT!I$13)*(1-Scenario_DT!I$14)+Scenario_DT!I$13-Scenario_DT!I$15)*Scenario_DT!I$16 -> 902.40093 | S54: =((Scenario_DT!J$11*(IF(Scenario_DT!J$18=1,1,1+$M54/Scenario_DT!$C$19)*(1+$N54)^MAX(0,Scenario_DT!J$18-3))*(Scenario_DT!J$12+$O54)-Scenario_DT!J$13)*(1-Scenario_DT!J$14)+Scenario_DT!J$13-Scenario_DT!J$15)*Scenario_DT!J$16 -> 1807.7097 | T54: =((Scenario_DT!K$11*(IF(Scenario_DT!K$18=1,1,1+$M54/Scenario_DT!$C$19)*(1+$N54)^MAX(0,Scenario_DT!K$18-3))*(Scenario_DT!K$12+$O54)-Scenario_DT!K$13)*(1-Scenario_DT!K$14)+Scenario_DT!K$13-Scenario_DT!K$15)*Scenario_DT!K$16 -> 2071.3397 | U54: =((Scenario_DT!L$11*(IF(Scenario_DT!L$18=1,1,1+$M54/Scenario_DT!$C$19)*(1+$N54)^MAX(0,Scenario_DT!L$18-3))*(Scenario_DT!L$12+$O54)-Scenario_DT!L$13)*(1-Scenario_DT!L$14)+Scenario_DT!L$13-Scenario_DT!L$15)*Scenario_DT!L$16 -> 2455.3491 | V54: =((Scenario_DT!M$11*(IF(Scenario_DT!M$18=1,1,1+$M54/Scenario_DT!$C$19)*(1+$N54)^MAX(0,Scenario_DT!M$18-3))*(Scenario_DT!M$12+$O54)-Scenario_DT!M$13)*(1-Scenario_DT!M$14)+Scenario_DT!M$13-Scenario_DT!M$15)*Scenario_DT!M$16 -> 2561.2569 | W54: =((Scenario_DT!N$11*(IF(Scenario_DT!N$18=1,1,1+$M54/Scenario_DT!$C$19)*(1+$N54)^MAX(0,Scenario_DT!N$18-3))*(Scenario_DT!N$12+$O54)-Scenario_DT!N$13)*(1-Scenario_DT!N$14)+Scenario_DT!N$13-Scenario_DT!N$15)*Scenario_DT!N$16 -> 2671.7155 | X54: =((Scenario_DT!O$11*(IF(Scenario_DT!O$18=1,1,1+$M54/Scenario_DT!$C$19)*(1+$N54)^MAX(0,Scenario_DT!O$18-3))*(Scenario_DT!O$12+$O54)-Scenario_DT!O$13)*(1-Scenario_DT!O$14)+Scenario_DT!O$13-Scenario_DT!O$15)*Scenario_DT!O$16 -> 2786.9221 | Y54: =((Scenario_DT!P$11*(IF(Scenario_DT!P$18=1,1,1+$M54/Scenario_DT!$C$19)*(1+$N54)^MAX(0,Scenario_DT!P$18-3))*(Scenario_DT!P$12+$O54)-Scenario_DT!P$13)*(1-Scenario_DT!P$14)+Scenario_DT!P$13-Scenario_DT!P$15)*Scenario_DT!P$16 -> 2907.0825 | ... AA54: =((Scenario_DT!R$11*(IF(Scenario_DT!R$18=1,1,1+$M54/Scenario_DT!$C$19)*(1+$N54)^MAX(0,Scenario_DT!R$18-3))*(Scenario_DT!R$12+$O54)-Scenario_DT!R$13)*(1-Scenario_DT!R$14)+Scenario_DT!R$13-Scenario_DT!R$15)*Scenario_DT!R$16 -> 3163.1332 | AB54: =(Scenario_DT!$R$11*(1+$M54/Scenario_DT!$C$19)*(1+$N54)^7*(Scenario_DT!$R$12+$O54)*(1+MIN(DCF_FCFF!$C$26+$Q54,(DCF_FCFF!$C$25+$P54)-0.02))*(1-DCF_FCFF!$C$27)*(1-DCF_FCFF!$C$28)/((DCF_FCFF!$C$25+$P54)-MIN(DCF_FCFF!$C$26+$Q54,(DCF_FCFF!$C$25+$P54)-0.02)))*(1+(DCF_FCFF!$C$25+$P54))^(-(Inputs!$C$9+9)) -> 23986.039 | AC54: =SUMPRODUCT(R54:AA54*(1+(DCF_FCFF!$C$25+$P54))^(-Scenario_DT!$I$17:$R$17))+AB54 -> 39880.184 | AD54: =((AC54-DCF_FCFF!$C$48)*(1-DCF_FCFF!$C$50)+DCF_FCFF!$C$57+DCF_FCFF!$C$58)/DCF_FCFF!$C$60 -> 286.35622 | AF54: 675 | AG54: =COUNTIFS($AD$32:$AD$531,">="&AF54,$AD$32:$AD$531,"<"&AF54+25) -> 0
B55: 24 | C55: 0.85661428 | D55: 0.75851953 | E55: 0.71946296 | F55: 0.43209304 | G55: 0.62730884 | H55: =NORMSINV(C55) -> 1.0652309 | I55: =NORMSINV(D55) -> 0.70154824 | J55: =NORMSINV(E55) -> 0.58124686 | K55: =NORMSINV(F55) -> -0.17104793 | L55: =NORMSINV(G55) -> 0.32473411 | M55: =H55*$C$5 -> 0.021304619 | N55: =($C$10*H55+SQRT(1-$C$10^2)*I55)*$C$6 -> 0.0091213926 | O55: =J55*$C$7 -> 0.0069749623 | P55: =K55*$C$8 -> -0.0010262876 | Q55: =L55*$C$9 -> 0.0012989364 | R55: =((Scenario_DT!I$11*(IF(Scenario_DT!I$18=1,1,1+$M55/Scenario_DT!$C$19)*(1+$N55)^MAX(0,Scenario_DT!I$18-3))*(Scenario_DT!I$12+$O55)-Scenario_DT!I$13)*(1-Scenario_DT!I$14)+Scenario_DT!I$13-Scenario_DT!I$15)*Scenario_DT!I$16 -> 920.81848 | S55: =((Scenario_DT!J$11*(IF(Scenario_DT!J$18=1,1,1+$M55/Scenario_DT!$C$19)*(1+$N55)^MAX(0,Scenario_DT!J$18-3))*(Scenario_DT!J$12+$O55)-Scenario_DT!J$13)*(1-Scenario_DT!J$14)+Scenario_DT!J$13-Scenario_DT!J$15)*Scenario_DT!J$16 -> 1905.1273 | T55: =((Scenario_DT!K$11*(IF(Scenario_DT!K$18=1,1,1+$M55/Scenario_DT!$C$19)*(1+$N55)^MAX(0,Scenario_DT!K$18-3))*(Scenario_DT!K$12+$O55)-Scenario_DT!K$13)*(1-Scenario_DT!K$14)+Scenario_DT!K$13-Scenario_DT!K$15)*Scenario_DT!K$16 -> 2173.0963 | U55: =((Scenario_DT!L$11*(IF(Scenario_DT!L$18=1,1,1+$M55/Scenario_DT!$C$19)*(1+$N55)^MAX(0,Scenario_DT!L$18-3))*(Scenario_DT!L$12+$O55)-Scenario_DT!L$13)*(1-Scenario_DT!L$14)+Scenario_DT!L$13-Scenario_DT!L$15)*Scenario_DT!L$16 -> 2602.5344 | V55: =((Scenario_DT!M$11*(IF(Scenario_DT!M$18=1,1,1+$M55/Scenario_DT!$C$19)*(1+$N55)^MAX(0,Scenario_DT!M$18-3))*(Scenario_DT!M$12+$O55)-Scenario_DT!M$13)*(1-Scenario_DT!M$14)+Scenario_DT!M$13-Scenario_DT!M$15)*Scenario_DT!M$16 -> 2757.027 | W55: =((Scenario_DT!N$11*(IF(Scenario_DT!N$18=1,1,1+$M55/Scenario_DT!$C$19)*(1+$N55)^MAX(0,Scenario_DT!N$18-3))*(Scenario_DT!N$12+$O55)-Scenario_DT!N$13)*(1-Scenario_DT!N$14)+Scenario_DT!N$13-Scenario_DT!N$15)*Scenario_DT!N$16 -> 2920.6958 | X55: =((Scenario_DT!O$11*(IF(Scenario_DT!O$18=1,1,1+$M55/Scenario_DT!$C$19)*(1+$N55)^MAX(0,Scenario_DT!O$18-3))*(Scenario_DT!O$12+$O55)-Scenario_DT!O$13)*(1-Scenario_DT!O$14)+Scenario_DT!O$13-Scenario_DT!O$15)*Scenario_DT!O$16 -> 3094.0889 | Y55: =((Scenario_DT!P$11*(IF(Scenario_DT!P$18=1,1,1+$M55/Scenario_DT!$C$19)*(1+$N55)^MAX(0,Scenario_DT!P$18-3))*(Scenario_DT!P$12+$O55)-Scenario_DT!P$13)*(1-Scenario_DT!P$14)+Scenario_DT!P$13-Scenario_DT!P$15)*Scenario_DT!P$16 -> 3277.787 | ... AA55: =((Scenario_DT!R$11*(IF(Scenario_DT!R$18=1,1,1+$M55/Scenario_DT!$C$19)*(1+$N55)^MAX(0,Scenario_DT!R$18-3))*(Scenario_DT!R$12+$O55)-Scenario_DT!R$13)*(1-Scenario_DT!R$14)+Scenario_DT!R$13-Scenario_DT!R$15)*Scenario_DT!R$16 -> 3678.5973 | AB55: =(Scenario_DT!$R$11*(1+$M55/Scenario_DT!$C$19)*(1+$N55)^7*(Scenario_DT!$R$12+$O55)*(1+MIN(DCF_FCFF!$C$26+$Q55,(DCF_FCFF!$C$25+$P55)-0.02))*(1-DCF_FCFF!$C$27)*(1-DCF_FCFF!$C$28)/((DCF_FCFF!$C$25+$P55)-MIN(DCF_FCFF!$C$26+$Q55,(DCF_FCFF!$C$25+$P55)-0.02)))*(1+(DCF_FCFF!$C$25+$P55))^(-(Inputs!$C$9+9)) -> 32837.244 | AC55: =SUMPRODUCT(R55:AA55*(1+(DCF_FCFF!$C$25+$P55))^(-Scenario_DT!$I$17:$R$17))+AB55 -> 50339.93 | AD55: =((AC55-DCF_FCFF!$C$48)*(1-DCF_FCFF!$C$50)+DCF_FCFF!$C$57+DCF_FCFF!$C$58)/DCF_FCFF!$C$60 -> 386.7569
